Workbook
Name Lista_Calificacion: 'Otras listas'!$W$6:$W$10
Name Lista_Combustible: 'Otras listas'!$L$6:$L$10
Name Lista_Conductores: Conductores[Conductor]
Name Lista_Estaciones: 'Otras listas'!$J$6:$J$13
Name Lista_infraccion: 'Otras listas'!$U$6:$U$11
Name Lista_Marcas: Marcas[Marcas]
Name Lista_Modelos: OFFSET(Modelos[[#Headers],[Modelo]],MATCH('Flota Vehicular'!$F1,Modelos[Marcas],0),0,COUNTIF(Modelos[Marcas],'Flota Vehicular'!$F1))
Name Lista_PaqMnnto: 'Otras listas'!$P$6:$P$28
Name Lista_Placas: 'Flota Vehicular'!$H$6:$H$34
Name Lista_Poliza: Seguros!$F$4:$F$23
Name Lista_Servicios: 'Otras listas'!$S$6:$S$28
Name Lista_Talleres: Talleres!$D$4:$D$23
Name Lista_Tipo_Vehiculo: Tipo_Vehiculo[Tipo Vehiculo]
Name Lista_TipoMnnto: 'Otras listas'!$N$6:$N$8

Sheet Flota Vehicular
B1: FLOTA DE VEHICULOS PROYECTO ENAP
C3: DATOS PRINCIPALES Y DISPONIBILIDAD DEL VEHÍCULO | N3: DATOS Y CONTROL DEL MANTENIMIENTO PREVENTIVO
C5: Nro | D5: PLACA | E5: TIPO | F5: MARCA | G5: MODELO | H5: Placa Vehiculo | I5: NRO DE SERIE | J5: COLOR | K5: AÑO | L5: Toneladas (Tn) | M5: Estado Vehiculo | N5: Ciclo para Mnnto Prevent. Motor (Kms) | O5: Ciclo para Mnnto Preventivo Caja y Diferencial | P5: Kms Odómetro Inicial | Q5: Kms Último Mnnto. Preventivo Motor | R5: Kms Último Mnnto Preve Caja y Diferencial | S5: Kms Odómetro Actual | T5: Kms Faltantes Mannto Prev. Cajas y Diferencial | U5: Kms faltantes Mnnto Prev. Motor (Km) | V5: Estado Mantenimiento Preventivo
C6: =ROW(A1) -> 1 | D6: QAA-3164 | E6: ARTICULADO | F6: SHACMAN | G6: CABEZAL | H6: QAA-3164 | I6: 71126425 | J6: BLANCO | K6: 2025 | L6: 25 | M6: =IF(H6="","",IF(_xlfn.MAXIFS(Mantenimiento[Fecha Salida],Mantenimiento[Placa Vehiculo],H6)>TODAY(),"Mantenimiento",IF(IFERROR(INDEX(Seguros[Estado Poliza],MATCH(H6,Seguros[Placa Vehiculo],0)),"")="Vencido","Seguro Vencido","Disponible"))) -> Disponible | N6: 8000 | O6: 60000 | P6: 200 | Q6: =_xlfn.MAXIFS(Mantenimiento[Kilometraje del Odómetro],Mantenimiento[Placa Vehiculo],H6,Mantenimiento[Tipo],"Preventivo") -> 38310 | R6: =_xlfn.MAXIFS(Mantenimiento[Kilometraje del Odómetro],Mantenimiento[Placa Vehiculo],H6,Mantenimiento[Tipo],"Prev Caja y Corona") -> 0 | S6: =_xlfn.MAXIFS(Rutas[Kms Final (Odómetro)],Rutas[Placa Vehiculo],H6) -> 44777 | T6: =IF(H6="","",O6-(IF(S6=0,P6,S6)-R6)) -> 15223 | U6: =IF(H6="","",N6-(IF(S6=0,P6,S6)-Q6)) -> 1533 | V6: =IFERROR(IF(OR(M6="Mantenimiento",U6/N6<=5%),"Mantener",IF(U6/N6<=20%,"Falta poco","Aun no")),"") -> Falta poco
C7: =ROW(A2) -> 2 | D7: QAA-3166 | E7: ARTICULADO | F7: SHACMAN | G7: CABEZAL | H7: QAA-3166 | I7: 71122862 | J7: BLANCO | K7: 2024 | L7: 25 | M7: =IF(H7="","",IF(_xlfn.MAXIFS(Mantenimiento[Fecha Salida],Mantenimiento[Placa Vehiculo],H7)>TODAY(),"Mantenimiento",IF(IFERROR(INDEX(Seguros[Estado Poliza],MATCH(H7,Seguros[Placa Vehiculo],0)),"")="Vencido","Seguro Vencido","Disponible"))) -> Disponible | N7: 8000 | O7: 60000 | P7: 200 | Q7: =_xlfn.MAXIFS(Mantenimiento[Kilometraje del Odómetro],Mantenimiento[Placa Vehiculo],H7,Mantenimiento[Tipo],"Preventivo") -> 52969 | R7: =_xlfn.MAXIFS(Mantenimiento[Kilometraje del Odómetro],Mantenimiento[Placa Vehiculo],H7,Mantenimiento[Tipo],"Prev Caja y Corona") -> 0 | S7: =_xlfn.MAXIFS(Rutas[Kms Final (Odómetro)],Rutas[Placa Vehiculo],H7) -> 59247 | T7: =IF(H7="","",O7-(IF(S7=0,P7,S7)-R7)) -> 753 | U7: =IF(H7="","",N7-(IF(S7=0,P7,S7)-Q7)) -> 1722 | V7: =IFERROR(IF(OR(M7="Mantenimiento",U7/N7<=5%),"Mantener",IF(U7/N7<=20%,"Falta poco","Aun no")),"") -> Aun no
C8: 3 | D8: QAA-2912 | E8: ARTICULADO | F8: DAF | G8: CABEZAL | H8: QAA-2912 | I8: A517778 | J8: AMARILLO | K8: 2023 | L8: 40 | M8: =IF(H8="","",IF(_xlfn.MAXIFS(Mantenimiento[Fecha Salida],Mantenimiento[Placa Vehiculo],H8)>TODAY(),"Mantenimiento",IF(IFERROR(INDEX(Seguros[Estado Poliza],MATCH(H8,Seguros[Placa Vehiculo],0)),"")="Vencido","Seguro Vencido","Disponible"))) -> Disponible | N8: 8000 | O8: 60000 | P8: 200 | Q8: =_xlfn.MAXIFS(Mantenimiento[Kilometraje del Odómetro],Mantenimiento[Placa Vehiculo],H8,Mantenimiento[Tipo],"Preventivo") -> 124870 | R8: =_xlfn.MAXIFS(Mantenimiento[Kilometraje del Odómetro],Mantenimiento[Placa Vehiculo],H8,Mantenimiento[Tipo],"Prev Caja y Corona") -> 82764 | S8: =_xlfn.MAXIFS(Rutas[Kms Final (Odómetro)],Rutas[Placa Vehiculo],H8) -> 131338 | T8: =IF(H8="","",O8-(IF(S8=0,P8,S8)-R8)) -> 11426 | U8: =IF(H8="","",N8-(IF(S8=0,P8,S8)-Q8)) -> 1532 | V8: =IFERROR(IF(OR(M8="Mantenimiento",U8/N8<=5%),"Mantener",IF(U8/N8<=20%,"Falta poco","Aun no")),"") -> Falta poco
C9: 4 | D9: QAA-2915 | E9: ARTICULADO | F9: DAF | G9: CABEZAL | H9: QAA-2915 | I9: A516026 | J9: BLANCO | K9: 2023 | L9: 40 | M9: =IF(H9="","",IF(_xlfn.MAXIFS(Mantenimiento[Fecha Salida],Mantenimiento[Placa Vehiculo],H9)>TODAY(),"Mantenimiento",IF(IFERROR(INDEX(Seguros[Estado Poliza],MATCH(H9,Seguros[Placa Vehiculo],0)),"")="Vencido","Seguro Vencido","Disponible"))) -> Disponible | N9: 8000 | O9: 60000 | P9: 200 | Q9: =_xlfn.MAXIFS(Mantenimiento[Kilometraje del Odómetro],Mantenimiento[Placa Vehiculo],H9,Mantenimiento[Tipo],"Preventivo") -> 127486 | R9: =_xlfn.MAXIFS(Mantenimiento[Kilometraje del Odómetro],Mantenimiento[Placa Vehiculo],H9,Mantenimiento[Tipo],"Prev Caja y Corona") -> 82494 | S9: =_xlfn.MAXIFS(Rutas[Kms Final (Odómetro)],Rutas[Placa Vehiculo],H9) -> 130806 | T9: =IF(H9="","",O9-(IF(S9=0,P9,S9)-R9)) -> 11688 | U9: =IF(H9="","",N9-(IF(S9=0,P9,S9)-Q9)) -> 4680 | V9: =IFERROR(IF(OR(M9="Mantenimiento",U9/N9<=5%),"Mantener",IF(U9/N9<=20%,"Falta poco","Aun no")),"") -> Aun no
C10: 5 | D10: QAA-2916 | E10: ARTICULADO | F10: DAF | G10: CABEZAL | H10: QAA-2916 | I10: A517802 | J10: AMARILLO | K10: 2023 | L10: 40 | M10: =IF(H10="","",IF(_xlfn.MAXIFS(Mantenimiento[Fecha Salida],Mantenimiento[Placa Vehiculo],H10)>TODAY(),"Mantenimiento",IF(IFERROR(INDEX(Seguros[Estado Poliza],MATCH(H10,Seguros[Placa Vehiculo],0)),"")="Vencido","Seguro Vencido","Disponible"))) -> Disponible | N10: 8000 | O10: 60000 | P10: 200 | Q10: =_xlfn.MAXIFS(Mantenimiento[Kilometraje del Odómetro],Mantenimiento[Placa Vehiculo],H10,Mantenimiento[Tipo],"Preventivo") -> 112441 | R10: =_xlfn.MAXIFS(Mantenimiento[Kilometraje del Odómetro],Mantenimiento[Placa Vehiculo],H10,Mantenimiento[Tipo],"Prev Caja y Corona") -> 91080 | S10: =_xlfn.MAXIFS(Rutas[Kms Final (Odómetro)],Rutas[Placa Vehiculo],H10) -> 118200 | T10: =IF(H10="","",O10-(IF(S10=0,P10,S10)-R10)) -> 32880 | U10: =IF(H10="","",N10-(IF(S10=0,P10,S10)-Q10)) -> 2241 | V10: =IFERROR(IF(OR(M10="Mantenimiento",U10/N10<=5%),"Mantener",IF(U10/N10<=20%,"Falta poco","Aun no")),"") -> Aun no
C11: 6 | D11: PAB-3424 | E11: CAMIÓN RIGIDO | F11: HINO | G11: RIGIDO | H11: PAB-3424 | I11: P11CVT20663 | J11: BLANCO | K11: 2021 | L11: 6 | M11: =IF(H11="","",IF(_xlfn.MAXIFS(Mantenimiento[Fecha Salida],Mantenimiento[Placa Vehiculo],H11)>TODAY(),"Mantenimiento",IF(IFERROR(INDEX(Seguros[Estado Poliza],MATCH(H11,Seguros[Placa Vehiculo],0)),"")="Vencido","Seguro Vencido","Disponible"))) -> Disponible | N11: 8000 | O11: 60000 | P11: 150000 | Q11: =_xlfn.MAXIFS(Mantenimiento[Kilometraje del Odómetro],Mantenimiento[Placa Vehiculo],H11,Mantenimiento[Tipo],"Preventivo") -> 365806 | R11: =_xlfn.MAXIFS(Mantenimiento[Kilometraje del Odómetro],Mantenimiento[Placa Vehiculo],H11,Mantenimiento[Tipo],"Prev Caja y Corona") -> 358316 | S11: =_xlfn.MAXIFS(Rutas[Kms Final (Odómetro)],Rutas[Placa Vehiculo],H11) -> 370695 | T11: =IF(H11="","",O11-(IF(S11=0,P11,S11)-R11)) -> 47621 | U11: =IF(H11="","",N11-(IF(S11=0,P11,S11)-Q11)) -> 3111 | V11: =IFERROR(IF(OR(M11="Mantenimiento",U11/N11<=5%),"Mantener",IF(U11/N11<=20%,"Falta poco","Aun no")),"") -> Aun no
C12: 7 | D12: QAA-3165 | E12: ARTICULADO | F12: SHACMAN | G12: CABEZAL | H12: QAA-3165 | I12: 71126426 | J12: BLANCO | K12: 2024 | L12: 25 | M12: =IF(H12="","",IF(_xlfn.MAXIFS(Mantenimiento[Fecha Salida],Mantenimiento[Placa Vehiculo],H12)>TODAY(),"Mantenimiento",IF(IFERROR(INDEX(Seguros[Estado Poliza],MATCH(H12,Seguros[Placa Vehiculo],0)),"")="Vencido","Seguro Vencido","Disponible"))) -> Disponible | N12: 8000 | O12: 60000 | P12: 200 | Q12: =_xlfn.MAXIFS(Mantenimiento[Kilometraje del Odómetro],Mantenimiento[Placa Vehiculo],H12,Mantenimiento[Tipo],"Preventivo") -> 63543 | R12: =_xlfn.MAXIFS(Mantenimiento[Kilometraje del Odómetro],Mantenimiento[Placa Vehiculo],H12,Mantenimiento[Tipo],"Prev Caja y Corona") -> 63543 | S12: =_xlfn.MAXIFS(Rutas[Kms Final (Odómetro)],Rutas[Placa Vehiculo],H12) -> 65856 | T12: =IF(H12="","",O12-(IF(S12=0,P12,S12)-R12)) -> 57687 | U12: =IF(H12="","",N12-(IF(S12=0,P12,S12)-Q12)) -> 5687 | V12: =IFERROR(IF(OR(M12="Mantenimiento",U12/N12<=5%),"Mantener",IF(U12/N12<=20%,"Falta poco","Aun no")),"") -> Aun no
C13: 8 | D13: QAA-1976 | E13: ARTICULADO | F13: HINO | G13: CABEZAL | H13: QAA-1976 | I13: E13CWT20044 | J13: BLANCO | K13: 2023 | L13: 27 | M13: =IF(H13="","",IF(_xlfn.MAXIFS(Mantenimiento[Fecha Salida],Mantenimiento[Placa Vehiculo],H13)>TODAY(),"Mantenimiento",IF(IFERROR(INDEX(Seguros[Estado Poliza],MATCH(H13,Seguros[Placa Vehiculo],0)),"")="Vencido","Seguro Vencido","Disponible"))) -> Disponible | N13: 6000 | O13: 60000 | P13: 150000 | Q13: =_xlfn.MAXIFS(Mantenimiento[Kilometraje del Odómetro],Mantenimiento[Placa Vehiculo],H13,Mantenimiento[Tipo],"Preventivo") -> 275504 | R13: =_xlfn.MAXIFS(Mantenimiento[Kilometraje del Odómetro],Mantenimiento[Placa Vehiculo],H13,Mantenimiento[Tipo],"Prev Caja y Corona") -> 268934 | S13: =_xlfn.MAXIFS(Rutas[Kms Final (Odómetro)],Rutas[Placa Vehiculo],H13) -> 274819 | T13: =IF(H13="","",O13-(IF(S13=0,P13,S13)-R13)) -> 54115 | U13: =IF(H13="","",N13-(IF(S13=0,P13,S13)-Q13)) -> 6685 | V13: =IFERROR(IF(OR(M13="Mantenimiento",U13/N13<=5%),"Mantener",IF(U13/N13<=20%,"Falta poco","Aun no")),"") -> Aun no
C14: 9 | D14: IAA-2747 | E14: CAMIÓN RIGIDO | F14: HINO | G14: RIGIDO | H14: IAA-2747 | I14: J08EWG10689 | J14: BLANCO | K14: 2022 | L14: 18.87 | M14: =IF(H14="","",IF(_xlfn.MAXIFS(Mantenimiento[Fecha Salida],Mantenimiento[Placa Vehiculo],H14)>TODAY(),"Mantenimiento",IF(IFERROR(INDEX(Seguros[Estado Poliza],MATCH(H14,Seguros[Placa Vehiculo],0)),"")="Vencido","Seguro Vencido","Disponible"))) -> Disponible | N14: 5000 | O14: 60000 | P14: 160000 | Q14: =_xlfn.MAXIFS(Mantenimiento[Kilometraje del Odómetro],Mantenimiento[Placa Vehiculo],H14,Mantenimiento[Tipo],"Preventivo") -> 430325 | R14: =_xlfn.MAXIFS(Mantenimiento[Kilometraje del Odómetro],Mantenimiento[Placa Vehiculo],H14,Mantenimiento[Tipo],"Prev Caja y Corona") -> 402043 | S14: =_xlfn.MAXIFS(Rutas[Kms Final (Odómetro)],Rutas[Placa Vehiculo],H14) -> 431668 | T14: =IF(H14="","",O14-(IF(S14=0,P14,S14)-R14)) -> 30375 | U14: =IF(H14="","",N14-(IF(S14=0,P14,S14)-Q14)) -> 3657 | V14: =IFERROR(IF(OR(M14="Mantenimiento",U14/N14<=5%),"Mantener",IF(U14/N14<=20%,"Falta poco","Aun no")),"") -> Aun no
C15: 10 | D15: QAA-3180 | E15: ARTICULADO | F15: SHACMAN | G15: CABEZAL | H15: QAA-3180 | I15: 71130145 | J15: PLOMO | K15: 2025 | L15: 25 | M15: =IF(H15="","",IF(_xlfn.MAXIFS(Mantenimiento[Fecha Salida],Mantenimiento[Placa Vehiculo],H15)>TODAY(),"Mantenimiento",IF(IFERROR(INDEX(Seguros[Estado Poliza],MATCH(H15,Seguros[Placa Vehiculo],0)),"")="Vencido","Seguro Vencido","Disponible"))) -> Disponible | N15: 6000 | O15: 60000 | P15: 300 | Q15: =_xlfn.MAXIFS(Mantenimiento[Kilometraje del Odómetro],Mantenimiento[Placa Vehiculo],H15,Mantenimiento[Tipo],"Preventivo") -> 18278 | R15: =_xlfn.MAXIFS(Mantenimiento[Kilometraje del Odómetro],Mantenimiento[Placa Vehiculo],H15,Mantenimiento[Tipo],"Prev Caja y Corona") -> 0 | S15: =_xlfn.MAXIFS(Rutas[Kms Final (Odómetro)],Rutas[Placa Vehiculo],H15) -> 14931 | T15: =IF(H15="","",O15-(IF(S15=0,P15,S15)-R15)) -> 45069 | U15: =IF(H15="","",N15-(IF(S15=0,P15,S15)-Q15)) -> 9347 | V15: =IFERROR(IF(OR(M15="Mantenimiento",U15/N15<=5%),"Mantener",IF(U15/N15<=20%,"Falta poco","Aun no")),"") -> Aun no
C16: 11 | D16: PFF-2857 | E16: CAMIONETA | F16: CHEVROLET | G16: DMAX | H16: PFF-2857 | I16: 4JK1ZH1718 | J16: BLANCO | K16: 2024 | L16: 1 | M16: =IF(H16="","",IF(_xlfn.MAXIFS(Mantenimiento[Fecha Salida],Mantenimiento[Placa Vehiculo],H16)>TODAY(),"Mantenimiento",IF(IFERROR(INDEX(Seguros[Estado Poliza],MATCH(H16,Seguros[Placa Vehiculo],0)),"")="Vencido","Seguro Vencido","Disponible"))) -> Disponible | N16: 6000 | O16: 40000 | P16: 300 | Q16: =_xlfn.MAXIFS(Mantenimiento[Kilometraje del Odómetro],Mantenimiento[Placa Vehiculo],H16,Mantenimiento[Tipo],"Preventivo") -> 111097 | R16: =_xlfn.MAXIFS(Mantenimiento[Kilometraje del Odómetro],Mantenimiento[Placa Vehiculo],H16,Mantenimiento[Tipo],"Prev Caja y Corona") -> 85960 | S16: =_xlfn.MAXIFS(Rutas[Kms Final (Odómetro)],Rutas[Placa Vehiculo],H16) -> 115045 | T16: =IF(H16="","",O16-(IF(S16=0,P16,S16)-R16)) -> 10915 | U16: =IF(H16="","",N16-(IF(S16=0,P16,S16)-Q16)) -> 2052 | V16: =IFERROR(IF(OR(M16="Mantenimiento",U16/N16<=5%),"Mantener",IF(U16/N16<=20%,"Falta poco","Aun no")),"") -> Aun no
C17: =ROW(A12) -> 12 | D17: QAA-3074 | E17: ARTICULADO | F17: DAF | G17: CABEZAL | H17: QAA-3074 | I17: A548013 | J17: AMARILLO | K17: 2024 | L17: 26 | M17: =IF(H17="","",IF(_xlfn.MAXIFS(Mantenimiento[Fecha Salida],Mantenimiento[Placa Vehiculo],H17)>TODAY(),"Mantenimiento",IF(IFERROR(INDEX(Seguros[Estado Poliza],MATCH(H17,Seguros[Placa Vehiculo],0)),"")="Vencido","Seguro Vencido","Disponible"))) -> Disponible | N17: 8000 | O17: 60000 | P17: 200 | Q17: =_xlfn.MAXIFS(Mantenimiento[Kilometraje del Odómetro],Mantenimiento[Placa Vehiculo],H17,Mantenimiento[Tipo],"Preventivo") -> 28686 | R17: =_xlfn.MAXIFS(Mantenimiento[Kilometraje del Odómetro],Mantenimiento[Placa Vehiculo],H17,Mantenimiento[Tipo],"Prev Caja y Corona") -> 0 | S17: =_xlfn.MAXIFS(Rutas[Kms Final (Odómetro)],Rutas[Placa Vehiculo],H17) -> 33139 | T17: =IF(H17="","",O17-(IF(S17=0,P17,S17)-R17)) -> 26861 | U17: =IF(H17="","",N17-(IF(S17=0,P17,S17)-Q17)) -> 3547 | V17: =IFERROR(IF(OR(M17="Mantenimiento",U17/N17<=5%),"Mantener",IF(U17/N17<=20%,"Falta poco","Aun no")),"") -> Aun no
C18: 13 | D18: QAA-3220 | E18: ARTICULADO | F18: DAF | G18: CABEZAL | H18: QAA-3220 | I18: A547787 | J18: AMARILLO | K18: 2024 | L18: 26 | M18: =IF(H18="","",IF(_xlfn.MAXIFS(Mantenimiento[Fecha Salida],Mantenimiento[Placa Vehiculo],H18)>TODAY(),"Mantenimiento",IF(IFERROR(INDEX(Seguros[Estado Poliza],MATCH(H18,Seguros[Placa Vehiculo],0)),"")="Vencido","Seguro Vencido","Disponible"))) -> Disponible | N18: 8000 | O18: 60000 | P18: 3000 | Q18: =_xlfn.MAXIFS(Mantenimiento[Kilometraje del Odómetro],Mantenimiento[Placa Vehiculo],H18,Mantenimiento[Tipo],"Preventivo") -> 54068 | R18: =_xlfn.MAXIFS(Mantenimiento[Kilometraje del Odómetro],Mantenimiento[Placa Vehiculo],H18,Mantenimiento[Tipo],"Prev Caja y Corona") -> 0 | S18: =_xlfn.MAXIFS(Rutas[Kms Final (Odómetro)],Rutas[Placa Vehiculo],H18) -> 57649 | T18: =IF(H18="","",O18-(IF(S18=0,P18,S18)-R18)) -> 2351 | U18: =IF(H18="","",N18-(IF(S18=0,P18,S18)-Q18)) -> 4419 | V18: =IFERROR(IF(OR(M18="Mantenimiento",U18/N18<=5%),"Mantener",IF(U18/N18<=20%,"Falta poco","Aun no")),"") -> Aun no
C19: 14 | D19: QAA-3108 | E19: ARTICULADO | F19: DAF | G19: CABEZAL | H19: QAA-3108 | I19: A625086 | J19: AMARILLO | K19: 2026 | L19: 26 | M19: =IF(H19="","",IF(_xlfn.MAXIFS(Mantenimiento[Fecha Salida],Mantenimiento[Placa Vehiculo],H19)>TODAY(),"Mantenimiento",IF(IFERROR(INDEX(Seguros[Estado Poliza],MATCH(H19,Seguros[Placa Vehiculo],0)),"")="Vencido","Seguro Vencido","Disponible"))) -> Disponible | N19: 8000 | O19: 60000 | P19: 300 | Q19: =_xlfn.MAXIFS(Mantenimiento[Kilometraje del Odómetro],Mantenimiento[Placa Vehiculo],H19,Mantenimiento[Tipo],"Preventivo") -> 0 | R19: =_xlfn.MAXIFS(Mantenimiento[Kilometraje del Odómetro],Mantenimiento[Placa Vehiculo],H19,Mantenimiento[Tipo],"Prev Caja y Corona") -> 0 | S19: =_xlfn.MAXIFS(Rutas[Kms Final (Odómetro)],Rutas[Placa Vehiculo],H19) -> 6798 | T19: =IF(H19="","",O19-(IF(S19=0,P19,S19)-R19)) -> 53202 | U19: =IF(H19="","",N19-(IF(S19=0,P19,S19)-Q19)) -> 1202 | V19: =IFERROR(IF(OR(M19="Mantenimiento",U19/N19<=5%),"Mantener",IF(U19/N19<=20%,"Falta poco","Aun no")),"") -> Falta poco
C20: 15 | D20: QAA-1974 | E20: ARTICULADO | F20: HINO | G20: CABEZAL | H20: QAA-1974 | I20: E13CWT20046 | J20: BLANCO | K20: 2018 | L20: 17 | M20: =IF(H20="","",IF(_xlfn.MAXIFS(Mantenimiento[Fecha Salida],Mantenimiento[Placa Vehiculo],H20)>TODAY(),"Mantenimiento",IF(IFERROR(INDEX(Seguros[Estado Poliza],MATCH(H20,Seguros[Placa Vehiculo],0)),"")="Vencido","Seguro Vencido","Disponible"))) -> Disponible | N20: 6000 | O20: 80000 | P20: 1500 | Q20: =_xlfn.MAXIFS(Mantenimiento[Kilometraje del Odómetro],Mantenimiento[Placa Vehiculo],H20,Mantenimiento[Tipo],"Preventivo") -> 228659 | R20: =_xlfn.MAXIFS(Mantenimiento[Kilometraje del Odómetro],Mantenimiento[Placa Vehiculo],H20,Mantenimiento[Tipo],"Prev Caja y Corona") -> 203550 | S20: =_xlfn.MAXIFS(Rutas[Kms Final (Odómetro)],Rutas[Placa Vehiculo],H20) -> 230044 | T20: =IF(H20="","",O20-(IF(S20=0,P20,S20)-R20)) -> 53506 | U20: =IF(H20="","",N20-(IF(S20=0,P20,S20)-Q20)) -> 4615 | V20: =IFERROR(IF(OR(M20="Mantenimiento",U20/N20<=5%),"Mantener",IF(U20/N20<=20%,"Falta poco","Aun no")),"") -> Aun no
C21: 16 | D21: PFG-2722 | E21: ARTICULADO | F21: QINGLING | G21: CABEZAL | H21: PFG-2722 | I21: G533087 | J21: BLANCO | K21: 2024 | L21: 20 | M21: =IF(H21="","",IF(_xlfn.MAXIFS(Mantenimiento[Fecha Salida],Mantenimiento[Placa Vehiculo],H21)>TODAY(),"Mantenimiento",IF(IFERROR(INDEX(Seguros[Estado Poliza],MATCH(H21,Seguros[Placa Vehiculo],0)),"")="Vencido","Seguro Vencido","Disponible"))) -> Disponible | N21: 10000 | O21: 60000 | P21: 150000 | Q21: =_xlfn.MAXIFS(Mantenimiento[Kilometraje del Odómetro],Mantenimiento[Placa Vehiculo],H21,Mantenimiento[Tipo],"Preventivo") -> 210065 | R21: =_xlfn.MAXIFS(Mantenimiento[Kilometraje del Odómetro],Mantenimiento[Placa Vehiculo],H21,Mantenimiento[Tipo],"Prev Caja y Corona") -> 191408 | S21: =_xlfn.MAXIFS(Rutas[Kms Final (Odómetro)],Rutas[Placa Vehiculo],H21) -> 214526 | T21: =IF(H21="","",O21-(IF(S21=0,P21,S21)-R21)) -> 36882 | U21: =IF(H21="","",N21-(IF(S21=0,P21,S21)-Q21)) -> 5539 | V21: =IFERROR(IF(OR(M21="Mantenimiento",U21/N21<=5%),"Mantener",IF(U21/N21<=20%,"Falta poco","Aun no")),"") -> Aun no
C22: 17 | D22: KR-1189/42416 | E22: VACUMM | F22: VACUUM | G22: 160 BARRILES | H22: KR-1189/42416 | I22: 8R8RFNS26B9J01843 | J22: BLANCO-ROJO | K22: 2011 | L22: 5 | M22: =IF(H22="","",IF(_xlfn.MAXIFS(Mantenimiento[Fecha Salida],Mantenimiento[Placa Vehiculo],H22)>TODAY(),"Mantenimiento",IF(IFERROR(INDEX(Seguros[Estado Poliza],MATCH(H22,Seguros[Placa Vehiculo],0)),"")="Vencido","Seguro Vencido","Disponible"))) -> Disponible | N22: 250 | P22: 2 | Q22: =_xlfn.MAXIFS(Mantenimiento[Kilometraje del Odómetro],Mantenimiento[Placa Vehiculo],H22,Mantenimiento[Tipo],"Preventivo") -> 2165 | R22: =_xlfn.MAXIFS(Mantenimiento[Kilometraje del Odómetro],Mantenimiento[Placa Vehiculo],H22,Mantenimiento[Tipo],"Prev Caja y Corona") -> 0 | S22: =_xlfn.MAXIFS(Rutas[Kms Final (Odómetro)],Rutas[Placa Vehiculo],H22) -> 2316 | U22: =IF(H22="","",N22-(IF(S22=0,P22,S22)-Q22)) -> 99 | V22: =IFERROR(IF(OR(M22="Mantenimiento",U22/N22<=5%),"Mantener",IF(U22/N22<=20%,"Falta poco","Aun no")),"") -> Aun no
C23: 18 | D23: KR-1172/42409 | E23: VACUMM | F23: VACUUM | G23: 160 BARRILES | H23: KR-1172/42409 | I23: 8R8RFNS2899J01854 | J23: BLANCO-ROJO | K23: 2009 | L23: 5 | M23: =IF(H23="","",IF(_xlfn.MAXIFS(Mantenimiento[Fecha Salida],Mantenimiento[Placa Vehiculo],H23)>TODAY(),"Mantenimiento",IF(IFERROR(INDEX(Seguros[Estado Poliza],MATCH(H23,Seguros[Placa Vehiculo],0)),"")="Vencido","Seguro Vencido","Disponible"))) -> Disponible | N23: 250 | P23: 1000 | Q23: =_xlfn.MAXIFS(Mantenimiento[Kilometraje del Odómetro],Mantenimiento[Placa Vehiculo],H23,Mantenimiento[Tipo],"Preventivo") -> 4896 | R23: =_xlfn.MAXIFS(Mantenimiento[Kilometraje del Odómetro],Mantenimiento[Placa Vehiculo],H23,Mantenimiento[Tipo],"Prev Caja y Corona") -> 0 | S23: =_xlfn.MAXIFS(Rutas[Kms Final (Odómetro)],Rutas[Placa Vehiculo],H23) -> 4986 | U23: =IF(H23="","",N23-(IF(S23=0,P23,S23)-Q23)) -> 160 | V23: =IFERROR(IF(OR(M23="Mantenimiento",U23/N23<=5%),"Mantener",IF(U23/N23<=20%,"Falta poco","Aun no")),"") -> Aun no
C24: 19 | D24: KR-1344/42429 | E24: VACUMM | F24: VACUUM | G24: 200 BARRILES | H24: KR-1344/42429 | I24: 8R8RFNS39H9J02079 | J24: BLANCO-ROJO | K24: 2017 | L24: 5 | M24: =IF(H24="","",IF(_xlfn.MAXIFS(Mantenimiento[Fecha Salida],Mantenimiento[Placa Vehiculo],H24)>TODAY(),"Mantenimiento",IF(IFERROR(INDEX(Seguros[Estado Poliza],MATCH(H24,Seguros[Placa Vehiculo],0)),"")="Vencido","Seguro Vencido","Disponible"))) -> Disponible | N24: 250 | P24: 1 | Q24: =_xlfn.MAXIFS(Mantenimiento[Kilometraje del Odómetro],Mantenimiento[Placa Vehiculo],H24,Mantenimiento[Tipo],"Preventivo") -> 2060 | R24: =_xlfn.MAXIFS(Mantenimiento[Kilometraje del Odómetro],Mantenimiento[Placa Vehiculo],H24,Mantenimiento[Tipo],"Prev Caja y Corona") -> 0 | S24: =_xlfn.MAXIFS(Rutas[Kms Final (Odómetro)],Rutas[Placa Vehiculo],H24) -> 2154 | U24: =IF(H24="","",N24-(IF(S24=0,P24,S24)-Q24)) -> 156 | V24: =IFERROR(IF(OR(M24="Mantenimiento",U24/N24<=5%),"Mantener",IF(U24/N24<=20%,"Falta poco","Aun no")),"") -> Aun no
C25: 20 | D25: KR-1090/42407 | E25: VACUMM | F25: VACUUM | G25: 160 BARRILES | H25: KR-1090/42407 | I25: 8R8RFNS2699J01626 | J25: BLANCO-ROJO | K25: 2009 | L25: 5 | M25: =IF(H25="","",IF(_xlfn.MAXIFS(Mantenimiento[Fecha Salida],Mantenimiento[Placa Vehiculo],H25)>TODAY(),"Mantenimiento",IF(IFERROR(INDEX(Seguros[Estado Poliza],MATCH(H25,Seguros[Placa Vehiculo],0)),"")="Vencido","Seguro Vencido","Disponible"))) -> Disponible | N25: 250 | P25: 2000 | Q25: =_xlfn.MAXIFS(Mantenimiento[Kilometraje del Odómetro],Mantenimiento[Placa Vehiculo],H25,Mantenimiento[Tipo],"Preventivo") -> 3007 | R25: =_xlfn.MAXIFS(Mantenimiento[Kilometraje del Odómetro],Mantenimiento[Placa Vehiculo],H25,Mantenimiento[Tipo],"Prev Caja y Corona") -> 0 | S25: =_xlfn.MAXIFS(Rutas[Kms Final (Odómetro)],Rutas[Placa Vehiculo],H25) -> 3000 | U25: =IF(H25="","",N25-(IF(S25=0,P25,S25)-Q25)) -> 257 | V25: =IFERROR(IF(OR(M25="Mantenimiento",U25/N25<=5%),"Mantener",IF(U25/N25<=20%,"Falta poco","Aun no")),"") -> Aun no
C26: 19 | D26: KR-1188/42405 | E26: VACUMM | F26: VACUUM | G26: 160 BARRILES | H26: KR-1188/42405 | I26: 8R8RFNS2299J01851 | J26: BLANCO-ROJO | K26: 2009 | L26: 5 | M26: =IF(H26="","",IF(_xlfn.MAXIFS(Mantenimiento[Fecha Salida],Mantenimiento[Placa Vehiculo],H26)>TODAY(),"Mantenimiento",IF(IFERROR(INDEX(Seguros[Estado Poliza],MATCH(H26,Seguros[Placa Vehiculo],0)),"")="Vencido","Seguro Vencido","Disponible"))) -> Disponible | N26: 250 | P26: 1000 | Q26: =_xlfn.MAXIFS(Mantenimiento[Kilometraje del Odómetro],Mantenimiento[Placa Vehiculo],H26,Mantenimiento[Tipo],"Preventivo") -> 2272 | R26: =_xlfn.MAXIFS(Mantenimiento[Kilometraje del Odómetro],Mantenimiento[Placa Vehiculo],H26,Mantenimiento[Tipo],"Prev Caja y Corona") -> 0 | S26: =_xlfn.MAXIFS(Rutas[Kms Final (Odómetro)],Rutas[Placa Vehiculo],H26) -> 2544 | U26: =IF(H26="","",N26-(IF(S26=0,P26,S26)-Q26)) -> -22 | V26: =IFERROR(IF(OR(M26="Mantenimiento",U26/N26<=5%),"Mantener",IF(U26/N26<=20%,"Falta poco","Aun no")),"") -> Mantener
C27: 21 | D27: KR-1088/42406 | E27: VACUMM | F27: VACUUM | G27: 160 BARRILES | H27: KR-1088/42406 | I27: 8R8RFNS2499J01625 | J27: BLANCO-ROJO | K27: 2009 | L27: 5 | M27: =IF(H27="","",IF(_xlfn.MAXIFS(Mantenimiento[Fecha Salida],Mantenimiento[Placa Vehiculo],H27)>TODAY(),"Mantenimiento",IF(IFERROR(INDEX(Seguros[Estado Poliza],MATCH(H27,Seguros[Placa Vehiculo],0)),"")="Vencido","Seguro Vencido","Disponible"))) -> Disponible | N27: 250 | P27: 1500 | Q27: =_xlfn.MAXIFS(Mantenimiento[Kilometraje del Odómetro],Mantenimiento[Placa Vehiculo],H27,Mantenimiento[Tipo],"Preventivo") -> 3359 | R27: =_xlfn.MAXIFS(Mantenimiento[Kilometraje del Odómetro],Mantenimiento[Placa Vehiculo],H27,Mantenimiento[Tipo],"Prev Caja y Corona") -> 0 | S27: =_xlfn.MAXIFS(Rutas[Kms Final (Odómetro)],Rutas[Placa Vehiculo],H27) -> 3358 | U27: =IF(H27="","",N27-(IF(S27=0,P27,S27)-Q27)) -> 251 | V27: =IFERROR(IF(OR(M27="Mantenimiento",U27/N27<=5%),"Mantener",IF(U27/N27<=20%,"Falta poco","Aun no")),"") -> Aun no
C28: 21 | D28: KR-1185/42408 | E28: VACUMM | F28: VACUUM | G28: 160 BARRILES | H28: KR-1185/42408 | I28: 8R8RFNS2199J01842 | J28: BLANCO-ROJO | K28: 2009 | L28: 5 | M28: =IF(H28="","",IF(_xlfn.MAXIFS(Mantenimiento[Fecha Salida],Mantenimiento[Placa Vehiculo],H28)>TODAY(),"Mantenimiento",IF(IFERROR(INDEX(Seguros[Estado Poliza],MATCH(H28,Seguros[Placa Vehiculo],0)),"")="Vencido","Seguro Vencido","Disponible"))) -> Disponible | N28: 250 | P28: 2000 | Q28: =_xlfn.MAXIFS(Mantenimiento[Kilometraje del Odómetro],Mantenimiento[Placa Vehiculo],H28,Mantenimiento[Tipo],"Preventivo") -> 2438 | R28: =_xlfn.MAXIFS(Mantenimiento[Kilometraje del Odómetro],Mantenimiento[Placa Vehiculo],H28,Mantenimiento[Tipo],"Prev Caja y Corona") -> 0 | S28: =_xlfn.MAXIFS(Rutas[Kms Final (Odómetro)],Rutas[Placa Vehiculo],H28) -> 2695 | U28: =IF(H28="","",N28-(IF(S28=0,P28,S28)-Q28)) -> -7 | V28: =IFERROR(IF(OR(M28="Mantenimiento",U28/N28<=5%),"Mantener",IF(U28/N28<=20%,"Falta poco","Aun no")),"") -> Mantener
C29: 22 | D29: KR-1184/42418 | E29: VACUMM | F29: VACUUM | G29: 160 BARRILES | H29: KR-1184/42418 | I29: 8R8RFNS22B9J01855 | J29: BLANCO-ROJO | K29: 2011 | L29: 5 | M29: =IF(H29="","",IF(_xlfn.MAXIFS(Mantenimiento[Fecha Salida],Mantenimiento[Placa Vehiculo],H29)>TODAY(),"Mantenimiento",IF(IFERROR(INDEX(Seguros[Estado Poliza],MATCH(H29,Seguros[Placa Vehiculo],0)),"")="Vencido","Seguro Vencido","Disponible"))) -> Disponible | N29: 250 | P29: 2 | Q29: =_xlfn.MAXIFS(Mantenimiento[Kilometraje del Odómetro],Mantenimiento[Placa Vehiculo],H29,Mantenimiento[Tipo],"Preventivo") -> 1364 | R29: =_xlfn.MAXIFS(Mantenimiento[Kilometraje del Odómetro],Mantenimiento[Placa Vehiculo],H29,Mantenimiento[Tipo],"Prev Caja y Corona") -> 0 | S29: =_xlfn.MAXIFS(Rutas[Kms Final (Odómetro)],Rutas[Placa Vehiculo],H29) -> 1418 | U29: =IF(H29="","",N29-(IF(S29=0,P29,S29)-Q29)) -> 196 | V29: =IFERROR(IF(OR(M29="Mantenimiento",U29/N29<=5%),"Mantener",IF(U29/N29<=20%,"Falta poco","Aun no")),"") -> Aun no
C30: 23 | D30: KR-1108/42403 | E30: VACUMM | F30: VACUUM | G30: 160 BARRILES | H30: KR-1108/42403 | I30: 8R8RFNS25B9J01624 | J30: BLANCO-ROJO | K30: 2011 | L30: 5 | M30: =IF(H30="","",IF(_xlfn.MAXIFS(Mantenimiento[Fecha Salida],Mantenimiento[Placa Vehiculo],H30)>TODAY(),"Mantenimiento",IF(IFERROR(INDEX(Seguros[Estado Poliza],MATCH(H30,Seguros[Placa Vehiculo],0)),"")="Vencido","Seguro Vencido","Disponible"))) -> Disponible | N30: 250 | P30: 30 | Q30: =_xlfn.MAXIFS(Mantenimiento[Kilometraje del Odómetro],Mantenimiento[Placa Vehiculo],H30,Mantenimiento[Tipo],"Preventivo") -> 4061 | R30: =_xlfn.MAXIFS(Mantenimiento[Kilometraje del Odómetro],Mantenimiento[Placa Vehiculo],H30,Mantenimiento[Tipo],"Prev Caja y Corona") -> 0 | S30: =_xlfn.MAXIFS(Rutas[Kms Final (Odómetro)],Rutas[Placa Vehiculo],H30) -> 4113 | U30: =IF(H30="","",N30-(IF(S30=0,P30,S30)-Q30)) -> 198 | V30: =IFERROR(IF(OR(M30="Mantenimiento",U30/N30<=5%),"Mantener",IF(U30/N30<=20%,"Falta poco","Aun no")),"") -> Aun no
C31: 24 | D31: KR-1094/42424 | E31: VACUMM | F31: VACUUM | G31: 160 BARRILES | H31: KR-1094/42424 | I31: 8R8RFNS22B9J01631 | J31: BLANCO-ROJO | K31: 2011 | L31: 5 | M31: =IF(H31="","",IF(_xlfn.MAXIFS(Mantenimiento[Fecha Salida],Mantenimiento[Placa Vehiculo],H31)>TODAY(),"Mantenimiento",IF(IFERROR(INDEX(Seguros[Estado Poliza],MATCH(H31,Seguros[Placa Vehiculo],0)),"")="Vencido","Seguro Vencido","Disponible"))) -> Disponible | N31: 250 | P31: 30 | Q31: =_xlfn.MAXIFS(Mantenimiento[Kilometraje del Odómetro],Mantenimiento[Placa Vehiculo],H31,Mantenimiento[Tipo],"Preventivo") -> 2258 | R31: =_xlfn.MAXIFS(Mantenimiento[Kilometraje del Odómetro],Mantenimiento[Placa Vehiculo],H31,Mantenimiento[Tipo],"Prev Caja y Corona") -> 0 | S31: =_xlfn.MAXIFS(Rutas[Kms Final (Odómetro)],Rutas[Placa Vehiculo],H31) -> 2266 | U31: =IF(H31="","",N31-(IF(S31=0,P31,S31)-Q31)) -> 242 | V31: =IFERROR(IF(OR(M31="Mantenimiento",U31/N31<=5%),"Mantener",IF(U31/N31<=20%,"Falta poco","Aun no")),"") -> Aun no
C32: 25 | D32: OR-2276 | E32: VACUMM | F32: VACUUM | G32: 200 BARRILES | H32: OR-2276 | I32: 8R8RJMS34S8J01377 | J32: BLANCO-ROJO | K32: 2025 | L32: 5 | M32: =IF(H32="","",IF(_xlfn.MAXIFS(Mantenimiento[Fecha Salida],Mantenimiento[Placa Vehiculo],H32)>TODAY(),"Mantenimiento",IF(IFERROR(INDEX(Seguros[Estado Poliza],MATCH(H32,Seguros[Placa Vehiculo],0)),"")="Vencido","Seguro Vencido","Disponible"))) -> Disponible | N32: 250 | P32: 20 | Q32: =_xlfn.MAXIFS(Mantenimiento[Kilometraje del Odómetro],Mantenimiento[Placa Vehiculo],H32,Mantenimiento[Tipo],"Preventivo") -> 200 | R32: =_xlfn.MAXIFS(Mantenimiento[Kilometraje del Odómetro],Mantenimiento[Placa Vehiculo],H32,Mantenimiento[Tipo],"Prev Caja y Corona") -> 0 | S32: =_xlfn.MAXIFS(Rutas[Kms Final (Odómetro)],Rutas[Placa Vehiculo],H32) -> 366 | U32: =IF(H32="","",N32-(IF(S32=0,P32,S32)-Q32)) -> 84 | V32: =IFERROR(IF(OR(M32="Mantenimiento",U32/N32<=5%),"Mantener",IF(U32/N32<=20%,"Falta poco","Aun no")),"") -> Aun no
C33: 26 | D33: KR1343/42430 | E33: VACUMM | F33: VACUUM | G33: 200 BARRILES | H33: KR-1343/42430 | I33: 8R8RFNS35H9J02080 | J33: BLANCO-ROJO | K33: 2017 | L33: 5 | M33: =IF(H33="","",IF(_xlfn.MAXIFS(Mantenimiento[Fecha Salida],Mantenimiento[Placa Vehiculo],H33)>TODAY(),"Mantenimiento",IF(IFERROR(INDEX(Seguros[Estado Poliza],MATCH(H33,Seguros[Placa Vehiculo],0)),"")="Vencido","Seguro Vencido","Disponible"))) -> Disponible | N33: 250 | P33: 1000 | Q33: =_xlfn.MAXIFS(Mantenimiento[Kilometraje del Odómetro],Mantenimiento[Placa Vehiculo],H33,Mantenimiento[Tipo],"Preventivo") -> 7290 | R33: =_xlfn.MAXIFS(Mantenimiento[Kilometraje del Odómetro],Mantenimiento[Placa Vehiculo],H33,Mantenimiento[Tipo],"Prev Caja y Corona") -> 0 | S33: =_xlfn.MAXIFS(Rutas[Kms Final (Odómetro)],Rutas[Placa Vehiculo],H33) -> 7290 | U33: =IF(H33="","",N33-(IF(S33=0,P33,S33)-Q33)) -> 250 | V33: =IFERROR(IF(OR(M33="Mantenimiento",U33/N33<=5%),"Mantener",IF(U33/N33<=20%,"Falta poco","Aun no")),"") -> Aun no
C34: 27 | D34: OR-2472/42435 | E34: VACUMM | F34: VACUUM | G34: 200 BARRILES | H34: OR-2472/42435 | I34: 8R8RRNS37S8J01601 | J34: BLANCO-ROJO | K34: 2025 | L34: 5 | M34: =IF(H34="","",IF(_xlfn.MAXIFS(Mantenimiento[Fecha Salida],Mantenimiento[Placa Vehiculo],H34)>TODAY(),"Mantenimiento",IF(IFERROR(INDEX(Seguros[Estado Poliza],MATCH(H34,Seguros[Placa Vehiculo],0)),"")="Vencido","Seguro Vencido","Disponible"))) -> Disponible | N34: 250 | P34: 50 | Q34: =_xlfn.MAXIFS(Mantenimiento[Kilometraje del Odómetro],Mantenimiento[Placa Vehiculo],H34,Mantenimiento[Tipo],"Preventivo") -> 704 | R34: =_xlfn.MAXIFS(Mantenimiento[Kilometraje del Odómetro],Mantenimiento[Placa Vehiculo],H34,Mantenimiento[Tipo],"Prev Caja y Corona") -> 0 | S34: =_xlfn.MAXIFS(Rutas[Kms Final (Odómetro)],Rutas[Placa Vehiculo],H34) -> 770 | U34: =IF(H34="","",N34-(IF(S34=0,P34,S34)-Q34)) -> 184 | V34: =IFERROR(IF(OR(M34="Mantenimiento",U34/N34<=5%),"Mantener",IF(U34/N34<=20%,"Falta poco","Aun no")),"") -> Aun no

Sheet Seguros
C1: SEGUROS DE VEHICULOS
C3: Nro | D3: Placa Vehiculo | E3: Aseguradora | F3: Poliza seguro | G3: Fecha de inicio | H3: Fecha de Vencimiento | I3: Importe Pagado ($) | J3: Fecha de Pago | K3: Estado Poliza
C4: =ROW(A1) -> 1 | K4: =IF(H4="","",IF(H4<TODAY(),"Vencido","Vigente"))
C5: =ROW(A2) -> 2 | K5: =IF(H5="","",IF(H5<TODAY(),"Vencido","Vigente"))
C6: =ROW(A3) -> 3 | K6: =IF(H6="","",IF(H6<TODAY(),"Vencido","Vigente"))
C7: =ROW(A4) -> 4 | K7: =IF(H7="","",IF(H7<TODAY(),"Vencido","Vigente"))
C8: =ROW(A5) -> 5 | K8: =IF(H8="","",IF(H8<TODAY(),"Vencido","Vigente"))
C9: =ROW(A6) -> 6 | K9: =IF(H9="","",IF(H9<TODAY(),"Vencido","Vigente"))
C10: =ROW(A7) -> 7 | K10: =IF(H10="","",IF(H10<TODAY(),"Vencido","Vigente"))
C11: =ROW(A8) -> 8 | K11: =IF(H11="","",IF(H11<TODAY(),"Vencido","Vigente"))
C12: =ROW(A9) -> 9 | K12: =IF(H12="","",IF(H12<TODAY(),"Vencido","Vigente"))
C13: =ROW(A10) -> 10 | K13: =IF(H13="","",IF(H13<TODAY(),"Vencido","Vigente"))
C14: =ROW(A11) -> 11 | K14: =IF(H14="","",IF(H14<TODAY(),"Vencido","Vigente"))
C15: =ROW(A12) -> 12 | K15: =IF(H15="","",IF(H15<TODAY(),"Vencido","Vigente"))
... C23: =ROW(A20) -> 20 | K23: =IF(H23="","",IF(H23<TODAY(),"Vencido","Vigente"))

Sheet Impuestos
C1: IMPUESTOS DE VEHICULOS
C3: Nro | D3: Placa Vehiculo | E3: Tipo Impuesto | F3: Año Impuesto | G3: Impuesto ($) | H3: Fecha de pago
C4: =ROW(A1) -> 1
C5: =ROW(A2) -> 2
C6: =ROW(A3) -> 3
C7: =ROW(A4) -> 4
C8: =ROW(A5) -> 5
C9: =ROW(A6) -> 6
C10: =ROW(A7) -> 7
C11: =ROW(A8) -> 8
C12: =ROW(A9) -> 9
C13: =ROW(A10) -> 10
C14: =ROW(A11) -> 11
C15: =ROW(A12) -> 12
... C23: =ROW(A20) -> 20

Sheet Conductores
B1: DATOS DE LOS CONDUCTORES
C3: Nro | D3: Doc Identidad | E3: Conductor | F3: Nro Licencia | G3: Dirección | H3: Teléfono/Celular | I3: Calificación
C4: =ROW(A1) -> 1 | D4: 1716252901 | E4: ARGUELLO PAUCAR JOHN FRANKLIN | F4: 1716252901 | G4: La Joya de los Sachas | I4: ★★★★
C5: =ROW(A2) -> 2 | D5: 0201710944 | E5: BAYAS VASQUEZ PEDRO BENJAMIN | F5: '0201710944 | G5: La Joya de los Sachas | H5: 990941137
C6: =ROW(A3) -> 3 | D6: 2100042452 | E6: BRAVO SONGOR MARCO HERNAN | F6: 2100042452 | G6: La Joya de los Sachas
C7: =ROW(A4) -> 4 | D7: 1723808927 | E7: BRIONES SOLORZANO LEONARDO FABIO | F7: 1723808927 | G7: La Joya de los Sachas
C8: =ROW(A5) -> 5 | D8: 2200112569 | E8: CAMACHO MORENO GILSON ADALBERTO | F8: 2200112569 | G8: La Joya de los Sachas
C9: =ROW(A6) -> 6 | D9: 2200019152 | E9: CAMACHO NARANJO CARLOS ANDRES | F9: 2200019152 | G9: La Joya de los Sachas
C10: =ROW(A7) -> 7 | D10: 2200523484 | E10: CASTILLO VILLALVA EDGAR PATRICIO | F10: 2200523484 | G10: La Joya de los Sachas
C11: =ROW(A8) -> 8 | D11: 2100768163 | E11: CORDOVA CELI ANDRES ALEXANDER | F11: 2100768163 | G11: La Joya de los Sachas
C12: =ROW(A9) -> 9 | D12: 2200300065 | E12: ESTACIO DAVILA EDWIN ALEXIS | F12: 2200300065 | G12: La Joya de los Sachas
C13: =ROW(A10) -> 10 | D13: 1714847884 | E13: GALEAS AGUILA FREDY RODOLFO | F13: 1714847884 | G13: La Joya de los Sachas
C14: =ROW(A11) -> 11 | D14: 1720613981 | E14: LOPEZ GUERRERO CRISTIAN ALEJANDRO | F14: 1720613981 | G14: La Joya de los Sachas
C15: =ROW(A12) -> 12 | D15: 1803398831 | E15: LUNA HERNANDEZ LUIS ALBERTO | F15: 1803398831 | G15: La Joya de los Sachas
C16: =ROW(A13) -> 13 | D16: 2200401434 | E16: MOSCUY RAMIREZ MILVIO PAUL | F16: 2200401434 | G16: La Joya de los Sachas
C17: =ROW(A14) -> 14 | D17: 0802477646 | E17: NAZARENO PALOMINO JORGE MANUEL | F17: 0802477646 | G17: La Joya de los Sachas
C18: =ROW(A15) -> 15 | D18: 1500330251 | E18: ORDOÑEZ CALLE JOSE SALVADOR | F18: 1500330251 | G18: La Joya de los Sachas
C19: =ROW(A16) -> 16 | D19: 2250130446 | E19: ORDOÑEZ MENENDEZ JOSUE ELISEO | F19: 2250130446 | G19: La Joya de los Sachas
C20: =ROW(A17) -> 17 | D20: 1306109628 | E20: PONCE RUIZ SIXTO LUBERNDI | F20: 1306109628 | G20: La Joya de los Sachas
C21: =ROW(A18) -> 18 | D21: 2200002521 | E21: TANDAZO ROSILLO VICTOR HUGO | F21: 2200002521 | G21: La Joya de los Sachas
C22: =ROW(A19) -> 19 | D22: 2200222327 | E22: VARGAS CARAVAJAL ROMEL LEONEL | F22: 2200222327 | G22: La Joya de los Sachas
C23: =ROW(A20) -> 20 | D23: 0504385162 | E23: AGURTO LOPEZ ERWIN JESULIN | F23: 0504385162 | G23: La Joya de los Sachas
C24: =ROW(A21) -> 21 | D24: 1250713219 | E24: ANCHUNDIA LISANDRO | F24: 1250713219 | G24: La Joya de los Sachas
C25: =ROW(A22) -> 22 | D25: 2200383160 | E25: BARRAGAN GARCIA GISSELA NOEMI | F25: 2200383160 | G25: La Joya de los Sachas
C26: =ROW(A23) -> 23 | D26: 2200313860 | E26: CAMACHO ZURITA ALEX ADRIAN | F26: 2200313860 | G26: La Joya de los Sachas
C27: =ROW(A24) -> 24 | D27: 2100274360 | E27: DEL VALLE CASTRO JAIME FERNANDO | F27: 2100274360 | G27: La Joya de los Sachas
C28: =ROW(A25) -> 25 | D28: 2101148886 | E28: GAROFALO PALAGUACHAY YOMAIRA MARICELA | F28: 2101148886 | G28: La Joya de los Sachas
C29: =ROW(A26) -> 26 | D29: 1103796205 | E29: HUANCA MAITA SANTOS ARCECIO | F29: 1103796205 | G29: La Joya de los Sachas
C30: =ROW(A27) -> 27 | D30: 2100573563 | E30: JARAMILLO CONZA LUIS ALBERTO | F30: 2100573563 | G30: La Joya de los Sachas
C31: =ROW(A28) -> 28 | D31: 2200644355 | E31: MANOBANDA SANCHEZ WILMER BENIGNO | F31: 2200644355 | G31: La Joya de los Sachas
C32: =ROW(A29) -> 29 | D32: 2200310676 | E32: MORAN PRIAS PEDRO PABLO | F32: 2200310676 | G32: La Joya de los Sachas
C33: =ROW(A31) -> 31 | D33: 2200247951 | E33: MORENO GALEAS JOSE LEODAN | F33: 2200247951 | G33: La Joya de los Sachas
C34: =ROW(A32) -> 32 | D34: 2100699962 | E34: NARANJO PERALTA VANESSA KATERINE | F34: 2100699962 | G34: La Joya de los Sachas
C35: =ROW(A33) -> 33 | D35: 2100152798 | E35: QUINTANILLA GARCIA LUIS HUMBERTO | F35: 2100152798 | G35: La Joya de los Sachas
C36: =ROW(A34) -> 34 | D36: 2250305303 | E36: QUINTERO BRAVO KAREN LISETH | F36: 2250305303 | G36: La Joya de los Sachas
C37: =ROW(A35) -> 35 | D37: 1105424103 | E37: REYES CELI JAVIER MAURICIO | F37: 1105424103 | G37: La Joya de los Sachas
C38: =ROW(A36) -> 36 | D38: 2100606256 | E38: RIVERA GAONA CARLOS FABIAN | F38: 2100606256 | G38: La Joya de los Sachas
C39: =ROW(A37) -> 37 | E39: TACURI GUEVARA LUIS EDUARDO | G39: La Joya de los Sachas
C40: 38 | E40: SILVA FERNANDO | G40: La Joya de los Sachas
C41: =ROW(A38) -> 38 | E41: SAMANIEGO RICHARD | G41: La Joya de los Sachas
C42: =ROW(A39) -> 39 | E42: INTRIAGO ANDRES | G42: La Joya de los Sachas
C43: =ROW(A40) -> 40 | E43: ARGUELLO MAURICIO | G43: La Joya de los Sachas
C44: =ROW(A41) -> 41 | E44: NAVARRETE WILNER | G44: La Joya de los Sachas
C45: =ROW(A42) -> 42 | E45: CONTENTO DIEDER | G45: La Joya de los Sachas
C46: =ROW(A43) -> 43 | E46: SIMALEZA JIMMY | G46: La Joya de los Sachas
C47: =ROW(A44) -> 44 | E47: ABADA JOSSELYN | G47: La Joya de los Sachas
C48: =ROW(A45) -> 45 | E48: PEREZ JOFFRE | G48: La Joya de los Sachas
C49: =ROW(A46) -> 46 | E49: VERDESOTO ANGEL | G49: La Joya de los Sachas
C50: =ROW(A47) -> 47 | E50: QUISHPE CARLOS
C51: =ROW(A48) -> 48 | E51: LLANOS FRANKLIN
C52: =ROW(A49) -> 49 | E52: AGILA LUIS
C53: =ROW(A50) -> 50 | E53: MANOBANDA SANCHEZ WILMER BENIGNO
C54: =ROW(A51) -> 51 | E54: MENDOZA ENRIQUE
C55: =ROW(A52) -> 52 | E55: LOZANO ALEX
C56: =ROW(A53) -> 53
C57: =ROW(A54) -> 54
C58: =ROW(A55) -> 55
C59: =ROW(A56) -> 56
C60: =ROW(A30) -> 30

Sheet Talleres
B1: TALLERES DE MANTENIMIENTO
C3: Nro | D3: Nombre del Taller | E3: Dirección | F3: Teléfono/Celular | G3: Correo | H3: Contacto Principal
C4: =ROW(A1) -> 1 | D4: MECÁNICA ORIENTOIL | E4: VIA AL COCA KM 3 SECTOR LA PARKER | G4: mecanica-orientoil@hotmail.com | H4: Jefferson Ortiz
C5: =ROW(A2) -> 2 | D5: LUBRICADORA HOMECAR | E5: FRENTE AL SINDICATO DE CHOFERES | F5: 968331684 | G5: jorgerodriguez64@gmail.com | H5: Jorge Rodriguez
C6: =ROW(A3) -> 3 | D6: ORDOÑEZ CAR DETAILING CENTER | E6: AV. FUNDADORES VIA LA PARKER | F6: 995441360 | H6: Juan Carlos Ordoñez
C7: =ROW(A4) -> 4 | D7: LAVADORA Y LUBIRCADORA G & J | E7: SECTOR LOS LAULERES | F7: 993880324 | H7: Govannela Pinargote
C8: =ROW(A5) -> 5
C9: =ROW(A6) -> 6
C10: =ROW(A7) -> 7
C11: =ROW(A8) -> 8
C12: =ROW(A9) -> 9
C13: =ROW(A10) -> 10
C14: =ROW(A11) -> 11
C15: =ROW(A12) -> 12
C16: =ROW(A13) -> 13
C17: =ROW(A14) -> 14
C18: =ROW(A15) -> 15
C19: =ROW(A16) -> 16
... C23: =ROW(A20) -> 20

Sheet Otras listas
B1: OTRAS LISTAS DE DATOS
C3: VEHÍCULO | J3: COMBUSTIBLE | N3: MANTENIMIENTO | U3: OTROS
C5: Tipo Vehiculo | E5: Marcas | G5: Marcas | H5: Modelo | J5: Estación de Combustible | L5: Tipo de Combustible | N5: Tipo Mantenimiento | P5: Paquete de Mantenimiento | R5: Paquete de Mantenimiento | S5: Servicios de Mantenimiento | U5: Infracción | W5: Calificación
C6: ARTICULADO | E6: DAF | G6: DAF | H6: CABEZAL | J6: BASE ORIENTOIL | L6: Diesel | N6: Preventivo | P6: Preventivo 01 | R6: Preventivo 01 | S6: Ajuste del Tiempo del Motor | U6: Accidente imprudencial | W6: ★
C7: CAMIÓN RIGIDO | E7: SHACMAN | G7: SHACMAN | H7: CABEZAL | J7: GASOLINERA MIRAFLORES | L7: GLP | N7: Correctivo | P7: Preventivo 02 | R7: Preventivo 01 | S7: Cambio de Aceite y Filtro de Aceite | U7: Alta velocidad | W7: ★★
C8: VACUMM | E8: HINO | G8: HINO | H8: RIGIDO | J8: GASOLINERA SAN JOSE | L8: GASOLINA | N8: Prev Caja y Corona | P8: Preventivo 03 | R8: Preventivo 01 | S8: Cambio de Filtro de Aire | U8: Conductor alcoholizado | W8: ★★★
C9: CAMIONETA | E9: VACUUM | G9: HINO | H9: CABEZAL | J9: ESTACIÓN PARAÍSO | L9: Premium | P9: Preventivo 04 | R9: Preventivo 01 | S9: Inspección de la Correa de Distribución | U9: Conductor temerario | W9: ★★★★
E10: CHEVROLET | G10: VACUUM | H10: 130 BARRILES | J10: CABEZAL | P10: Preventivo 05 | R10: Preventivo 01 | S10: Inspección del Sistema de Frenos | U10: Mal estacionado | W10: ★★★★★
E11: QINGLING | G11: VACUUM | H11: 160 BARRILES | J11: GASOLINERA DIVINO NIÑO | P11: Correctivo 01 | R11: Preventivo 02 | S11: Inspección del Sistema de Suspensión | U11: Se pasó la luz roja
G12: VACUUM | H12: 200 BARRILES | J12: GASOLINERA P&S | P12: Correctivo 02 | R12: Preventivo 02 | S12: Mantenimiento de la Batería
G13: CHEVROLET | H13: DMAX | P13: Correctivo 03 | R13: Preventivo 02 | S13: Mantenimiento del Sistema de Combustible
G14: QINGLING | H14: CABEZAL | P14: Correctivo 04 | R14: Preventivo 02 | S14: Mantenimiento del Sistema de Dirección
P15: Correctivo 05 | R15: Preventivo 03 | S15: Reemplazo de Bujías, Cables y Correas Serpentinas
P16: Correctivo 06 | R16: Preventivo 03 | S16: Revisión de Amortiguadores
P17: Correctivo 07 | R17: Preventivo 03 | S17: Revisión de Luces
P18: Correctivo 08 | R18: Preventivo 03 | S18: Revisión del Dispositivo de Acoplamiento
P19: Correctivo 09 | R19: Preventivo 04 | S19: Revisión del Sistema de Admisión, Mangueras y Tuberías
P20: Correctivo 10 | R20: Preventivo 04 | S20: Revisión del Sistema de Escape
P21: Caja y Corona 01 | R21: Preventivo 04 | S21: Servicio Completo de Mantenimiento Automotriz
P22: Caja y Corona 02 | R22: Preventivo 05 | S22: Verificación de Neumáticos
P23: Caja y Corona 03 | R23: Preventivo 05 | S23: Verificación de Niveles de Fluidos
P24: Caja y Corona 04 | R24: Preventivo 05 | S24: Verificación del Funcionamiento del Motor
P25: Caja Y Corona 05 | R25: Preventivo 05 | S25: Verificación del Sistema de Transmisión
R26: Correctivo 01 | S26: Planchado y pintado
R27: Correctivo 02 | S27: Cambio de puertas
R28: Correctivo 03 | S28: Eliminación de inperfecciones de la pintura

Sheet Rutas
B1: RUTAS DE VIAJE
C3: Nro | D3: Fecha de Salida | E3: Fecha de Llegada | F3: Placa Vehiculo | G3: Estado Vehículo | H3: Conductor | I3: Origen | J3: Destino | K3: Kms Inicial (Odómetro) | L3: Kms Final (Odómetro) | M3: Kms Recorridos | N3: Horas trabjadas | O3: Peso de carga (BLS) | P3: Costo por Km de carga ($/Km) | Q3: Ingreso Total ($) | R3: Estación de Combustible | S3: Tipo de Combustible | T3: Precio x Galón ($/gal) | U3: Total Combustible ($) | V3: Gasto peajes ($) | W3: Gasto comidas ($) | X3: Otros Gastos ($) | Y3: Gasto Total ($) | Z3: TICKET | AA3: Volumen de Combustible (gal) | AB3: Recorrido por und. de comb. (Km/gal) | AC3: Ingreso por Kms de recorrido ($/Km) | AD3: Observaciones
C4: =ROW(A1) -> 1 | D4: 45630 | E4: 45633 | F4: QAA-2912 | G4: =IF(AND(E4<>"",E4<TODAY()),"Disponible",IFERROR(INDEX(Vehiculos[Estado Vehiculo],MATCH(F4,Vehiculos[Placa Vehiculo],0)),"")) -> Disponible | H4: MOSCUY RAMIREZ MILVIO PAUL | I4: BASE ORIENTOIL | J4: MDC | K4: 67507 | L4: 68206 | M4: =L4-K4 -> 699 | P4: 5 | Q4: =M4*P4 -> 3495 | R4: BASE ORIENTOIL | S4: Diesel | T4: 1.8 | U4: =Rutas[[#This Row],[Precio x Galón ($/gal)]]*Rutas[[#This Row],[Volumen de Combustible (gal)]] -> 192.834 | Y4: =U4+SUM(V4:X4) -> 192.834 | AA4: 107.13 | AB4: =IFERROR(M4/AA4,0) -> 6.524783 | AC4: =IFERROR(Q4/M4,0) -> 5
C5: =ROW(A2) -> 2 | D5: 45633 | E5: 45639 | F5: QAA-2912 | G5: =IF(AND(E5<>"",E5<TODAY()),"Disponible",IFERROR(INDEX(Vehiculos[Estado Vehiculo],MATCH(F5,Vehiculos[Placa Vehiculo],0)),"")) -> Disponible | H5: MOSCUY RAMIREZ MILVIO PAUL | I5: BASE ORIENTOIL | J5: MDC | K5: 68206 | L5: 68985 | M5: =L5-K5 -> 779 | Q5: =M5*P5 -> 0 | R5: BASE ORIENTOIL | S5: Diesel | T5: 1.8 | U5: =Rutas[[#This Row],[Precio x Galón ($/gal)]]*Rutas[[#This Row],[Volumen de Combustible (gal)]] -> 184.32 | Y5: =U5+SUM(V5:X5) -> 184.32 | AA5: 102.4 | AB5: =IFERROR(M5/AA5,0) -> 7.6074219 | AC5: =IFERROR(Q5/M5,0) -> 0
C6: =ROW(A3) -> 3 | D6: 45639 | E6: 45645 | F6: QAA-2912 | G6: =IF(AND(E6<>"",E6<TODAY()),"Disponible",IFERROR(INDEX(Vehiculos[Estado Vehiculo],MATCH(F6,Vehiculos[Placa Vehiculo],0)),"")) -> Disponible | H6: MOSCUY RAMIREZ MILVIO PAUL | I6: BASE ORIENTOIL | J6: MDC | K6: 68985 | L6: 69722 | M6: =L6-K6 -> 737 | Q6: =M6*P6 -> 0 | R6: BASE ORIENTOIL | S6: Diesel | T6: 1.8 | U6: =Rutas[[#This Row],[Precio x Galón ($/gal)]]*Rutas[[#This Row],[Volumen de Combustible (gal)]] -> 186.498 | Y6: =U6+SUM(V6:X6) -> 186.498 | AA6: 103.61 | AB6: =IFERROR(M6/AA6,0) -> 7.113213 | AC6: =IFERROR(Q6/M6,0) -> 0
C7: =ROW(A4) -> 4 | D7: 45645 | E7: 45650 | F7: QAA-2912 | G7: =IF(AND(E7<>"",E7<TODAY()),"Disponible",IFERROR(INDEX(Vehiculos[Estado Vehiculo],MATCH(F7,Vehiculos[Placa Vehiculo],0)),"")) -> Disponible | H7: MOSCUY RAMIREZ MILVIO PAUL | I7: BASE ORIENTOIL | J7: MDC | K7: 69722 | L7: 70409 | M7: =L7-K7 -> 687 | Q7: =M7*P7 -> 0 | R7: BASE ORIENTOIL | S7: Diesel | T7: 1.8 | U7: =Rutas[[#This Row],[Precio x Galón ($/gal)]]*Rutas[[#This Row],[Volumen de Combustible (gal)]] -> 177.318 | Y7: =U7+SUM(V7:X7) -> 177.318 | AA7: 98.51 | AB7: =IFERROR(M7/AA7,0) -> 6.9739113 | AC7: =IFERROR(Q7/M7,0) -> 0
C8: =ROW(A5) -> 5 | D8: 45650 | E8: 45656 | F8: QAA-2912 | G8: =IF(AND(E8<>"",E8<TODAY()),"Disponible",IFERROR(INDEX(Vehiculos[Estado Vehiculo],MATCH(F8,Vehiculos[Placa Vehiculo],0)),"")) -> Disponible | H8: MOSCUY RAMIREZ MILVIO PAUL | I8: BASE ORIENTOIL | J8: MDC | K8: 70409 | L8: 71246 | M8: =L8-K8 -> 837 | Q8: =M8*P8 -> 0 | R8: BASE ORIENTOIL | S8: Diesel | T8: 1.8 | U8: =Rutas[[#This Row],[Precio x Galón ($/gal)]]*Rutas[[#This Row],[Volumen de Combustible (gal)]] -> 177.822 | Y8: =U8+SUM(V8:X8) -> 177.822 | AA8: 98.79 | AB8: =IFERROR(M8/AA8,0) -> 8.4725175 | AC8: =IFERROR(Q8/M8,0) -> 0
C9: =ROW(A6) -> 6 | D9: 45656 | E9: 45657 | F9: QAA-2912 | G9: =IF(AND(E9<>"",E9<TODAY()),"Disponible",IFERROR(INDEX(Vehiculos[Estado Vehiculo],MATCH(F9,Vehiculos[Placa Vehiculo],0)),"")) -> Disponible | H9: MOSCUY RAMIREZ MILVIO PAUL | I9: BASE ORIENTOIL | J9: MDC | K9: 71246 | L9: 71946 | M9: =L9-K9 -> 700 | Q9: =M9*P9 -> 0 | R9: BASE ORIENTOIL | S9: Diesel | T9: 1.8 | U9: =Rutas[[#This Row],[Precio x Galón ($/gal)]]*Rutas[[#This Row],[Volumen de Combustible (gal)]] -> 203.328 | Y9: =U9+SUM(V9:X9) -> 203.328 | AA9: 112.96 | AB9: =IFERROR(M9/AA9,0) -> 6.1968839 | AC9: =IFERROR(Q9/M9,0) -> 0
C10: =ROW(A7) -> 7 | D10: 45628 | E10: 45635 | F10: QAA-2916 | G10: =IF(AND(E10<>"",E10<TODAY()),"Disponible",IFERROR(INDEX(Vehiculos[Estado Vehiculo],MATCH(F10,Vehiculos[Placa Vehiculo],0)),"")) -> Disponible | H10: PONCE RUIZ SIXTO LUBERNDI | I10: BASE ORIENTOIL | J10: MDC | K10: 53731 | L10: 54435 | M10: =L10-K10 -> 704 | Q10: =M10*P10 -> 0 | R10: BASE ORIENTOIL | S10: Diesel | T10: 1.8 | U10: =Rutas[[#This Row],[Precio x Galón ($/gal)]]*Rutas[[#This Row],[Volumen de Combustible (gal)]] -> 154.26 | Y10: =U10+SUM(V10:X10) -> 154.26 | AA10: 85.7 | AB10: =IFERROR(M10/AA10,0) -> 8.2147025 | AC10: =IFERROR(Q10/M10,0) -> 0
C11: =ROW(A8) -> 8 | D11: 45635 | E11: 45641 | F11: QAA-2916 | G11: =IF(AND(E11<>"",E11<TODAY()),"Disponible",IFERROR(INDEX(Vehiculos[Estado Vehiculo],MATCH(F11,Vehiculos[Placa Vehiculo],0)),"")) -> Disponible | H11: PONCE RUIZ SIXTO LUBERNDI | I11: BASE ORIENTOIL | J11: MDC | K11: 54435 | L11: 55268 | M11: =L11-K11 -> 833 | Q11: =M11*P11 -> 0 | R11: BASE ORIENTOIL | S11: Diesel | T11: 1.8 | U11: =Rutas[[#This Row],[Precio x Galón ($/gal)]]*Rutas[[#This Row],[Volumen de Combustible (gal)]] -> 197.748 | Y11: =U11+SUM(V11:X11) -> 197.748 | AA11: 109.86 | AB11: =IFERROR(M11/AA11,0) -> 7.5823776 | AC11: =IFERROR(Q11/M11,0) -> 0
C12: =ROW(A9) -> 9 | D12: 45641 | E12: 45647 | F12: QAA-2916 | G12: =IF(AND(E12<>"",E12<TODAY()),"Disponible",IFERROR(INDEX(Vehiculos[Estado Vehiculo],MATCH(F12,Vehiculos[Placa Vehiculo],0)),"")) -> Disponible | H12: BRIONES SOLORZANO LEONARDO FABIO | I12: BASE ORIENTOIL | J12: MDC | K12: 55268 | L12: 55943 | M12: =L12-K12 -> 675 | Q12: =M12*P12 -> 0 | R12: BASE ORIENTOIL | S12: Diesel | T12: 1.8 | U12: =Rutas[[#This Row],[Precio x Galón ($/gal)]]*Rutas[[#This Row],[Volumen de Combustible (gal)]] -> 211.482 | Y12: =U12+SUM(V12:X12) -> 211.482 | AA12: 117.49 | AB12: =IFERROR(M12/AA12,0) -> 5.7451698 | AC12: =IFERROR(Q12/M12,0) -> 0
C13: =ROW(A10) -> 10 | D13: 45647 | E13: 45652 | F13: QAA-2916 | G13: =IF(AND(E13<>"",E13<TODAY()),"Disponible",IFERROR(INDEX(Vehiculos[Estado Vehiculo],MATCH(F13,Vehiculos[Placa Vehiculo],0)),"")) -> Disponible | H13: BRIONES SOLORZANO LEONARDO FABIO | I13: BASE ORIENTOIL | J13: MDC | K13: 55943 | L13: 56624 | M13: =L13-K13 -> 681 | Q13: =M13*P13 -> 0 | R13: BASE ORIENTOIL | S13: Diesel | T13: 1.8 | U13: =Rutas[[#This Row],[Precio x Galón ($/gal)]]*Rutas[[#This Row],[Volumen de Combustible (gal)]] -> 293.706 | Y13: =U13+SUM(V13:X13) -> 293.706 | AA13: 163.17 | AB13: =IFERROR(M13/AA13,0) -> 4.1735613 | AC13: =IFERROR(Q13/M13,0) -> 0
C14: =ROW(A11) -> 11 | D14: 45652 | E14: 45656 | F14: QAA-2916 | G14: =IF(AND(E14<>"",E14<TODAY()),"Disponible",IFERROR(INDEX(Vehiculos[Estado Vehiculo],MATCH(F14,Vehiculos[Placa Vehiculo],0)),"")) -> Disponible | H14: PONCE RUIZ SIXTO LUBERNDI | I14: BASE ORIENTOIL | J14: MDC | K14: 56624 | L14: 57355 | M14: =L14-K14 -> 731 | Q14: =M14*P14 -> 0 | R14: BASE ORIENTOIL | S14: Diesel | T14: 1.8 | U14: =Rutas[[#This Row],[Precio x Galón ($/gal)]]*Rutas[[#This Row],[Volumen de Combustible (gal)]] -> 176.22 | Y14: =U14+SUM(V14:X14) -> 176.22 | AA14: 97.9 | AB14: =IFERROR(M14/AA14,0) -> 7.4668029 | AC14: =IFERROR(Q14/M14,0) -> 0
C15: =ROW(A12) -> 12 | D15: 45627 | E15: 45631 | F15: QAA-2915 | G15: =IF(AND(E15<>"",E15<TODAY()),"Disponible",IFERROR(INDEX(Vehiculos[Estado Vehiculo],MATCH(F15,Vehiculos[Placa Vehiculo],0)),"")) -> Disponible | H15: NAZARENO PALOMINO JORGE MANUEL | I15: BASE ORIENTOIL | J15: MDC | K15: 62880 | L15: 63639 | M15: =L15-K15 -> 759 | Q15: =M15*P15 -> 0 | R15: BASE ORIENTOIL | S15: Diesel | T15: 1.8 | U15: =Rutas[[#This Row],[Precio x Galón ($/gal)]]*Rutas[[#This Row],[Volumen de Combustible (gal)]] -> 223.848 | Y15: =U15+SUM(V15:X15) -> 223.848 | AA15: 124.36 | AB15: =IFERROR(M15/AA15,0) -> 6.1032486 | AC15: =IFERROR(Q15/M15,0) -> 0
C16: =ROW(A13) -> 13 | D16: 45631 | E16: 45634 | F16: QAA-2915 | G16: =IF(AND(E16<>"",E16<TODAY()),"Disponible",IFERROR(INDEX(Vehiculos[Estado Vehiculo],MATCH(F16,Vehiculos[Placa Vehiculo],0)),"")) -> Disponible | H16: LUNA HERNANDEZ LUIS ALBERTO | I16: BASE ORIENTOIL | J16: MDC | K16: 63639 | L16: 64228 | M16: =L16-K16 -> 589 | Q16: =M16*P16 -> 0 | R16: BASE ORIENTOIL | S16: Diesel | T16: 1.8 | U16: =Rutas[[#This Row],[Precio x Galón ($/gal)]]*Rutas[[#This Row],[Volumen de Combustible (gal)]] -> 218.214 | Y16: =U16+SUM(V16:X16) -> 218.214 | AA16: 121.23 | AB16: =IFERROR(M16/AA16,0) -> 4.8585334 | AC16: =IFERROR(Q16/M16,0) -> 0
... C47: =ROW(A44) -> 44 | D47: 45635 | E47: 45638 | F47: QAA-3166 | G47: =IF(AND(E47<>"",E47<TODAY()),"Disponible",IFERROR(INDEX(Vehiculos[Estado Vehiculo],MATCH(F47,Vehiculos[Placa Vehiculo],0)),"")) -> Disponible | H47: ORDOÑEZ CALLE JOSE SALVADOR | I47: BASE ORIENTOIL | J47: INCHI | K47: 22372 | L47: 23343 | M47: =L47-K47 -> 971 | Q47: =M47*P47 -> 0 | R47: BASE ORIENTOIL | S47: Diesel | T47: 1.8 | U47: =Rutas[[#This Row],[Precio x Galón ($/gal)]]*Rutas[[#This Row],[Volumen de Combustible (gal)]] -> 214.434 | Y47: =U47+SUM(V47:X47) -> 214.434 | AA47: 119.13 | AB47: =IFERROR(M47/AA47,0) -> 8.1507597 | AC47: =IFERROR(Q47/M47,0) -> 0
C48: =ROW(A45) -> 45 | D48: 45638 | E48: 45642 | F48: QAA-3166 | G48: =IF(AND(E48<>"",E48<TODAY()),"Disponible",IFERROR(INDEX(Vehiculos[Estado Vehiculo],MATCH(F48,Vehiculos[Placa Vehiculo],0)),"")) -> Disponible | H48: ORDOÑEZ CALLE JOSE SALVADOR | I48: BASE ORIENTOIL | J48: INCHI | K48: =L47 -> 23343 | L48: 24491 | M48: =L48-K48 -> 1148 | Q48: =M48*P48 -> 0 | R48: BASE ORIENTOIL | S48: Diesel | T48: 1.8 | U48: =Rutas[[#This Row],[Precio x Galón ($/gal)]]*Rutas[[#This Row],[Volumen de Combustible (gal)]] -> 268.2 | Y48: =U48+SUM(V48:X48) -> 268.2 | AA48: 149 | AB48: =IFERROR(M48/AA48,0) -> 7.704698 | AC48: =IFERROR(Q48/M48,0) -> 0
C49: =ROW(A46) -> 46 | D49: 45642 | E49: 45645 | F49: QAA-3166 | G49: =IF(AND(E49<>"",E49<TODAY()),"Disponible",IFERROR(INDEX(Vehiculos[Estado Vehiculo],MATCH(F49,Vehiculos[Placa Vehiculo],0)),"")) -> Disponible | H49: GALEAS AGUILA FREDY RODOLFO | I49: BASE ORIENTOIL | J49: INCHI | K49: =L48 -> 24491 | L49: 25568 | M49: =L49-K49 -> 1077 | Q49: =M49*P49 -> 0 | R49: BASE ORIENTOIL | S49: Diesel | T49: 1.8 | U49: =Rutas[[#This Row],[Precio x Galón ($/gal)]]*Rutas[[#This Row],[Volumen de Combustible (gal)]] -> 287.298 | Y49: =U49+SUM(V49:X49) -> 287.298 | AA49: 159.61 | AB49: =IFERROR(M49/AA49,0) -> 6.7476975 | AC49: =IFERROR(Q49/M49,0) -> 0
C50: =ROW(A47) -> 47 | D50: 45645 | E50: 45647 | F50: QAA-3166 | G50: =IF(AND(E50<>"",E50<TODAY()),"Disponible",IFERROR(INDEX(Vehiculos[Estado Vehiculo],MATCH(F50,Vehiculos[Placa Vehiculo],0)),"")) -> Disponible | H50: GALEAS AGUILA FREDY RODOLFO | I50: BASE ORIENTOIL | J50: INCHI | K50: =L49 -> 25568 | L50: 26327 | M50: =L50-K50 -> 759 | Q50: =M50*P50 -> 0 | R50: BASE ORIENTOIL | S50: Diesel | T50: 1.8 | U50: =Rutas[[#This Row],[Precio x Galón ($/gal)]]*Rutas[[#This Row],[Volumen de Combustible (gal)]] -> 267.84 | Y50: =U50+SUM(V50:X50) -> 267.84 | AA50: 148.8 | AB50: =IFERROR(M50/AA50,0) -> 5.1008065 | AC50: =IFERROR(Q50/M50,0) -> 0
C51: =ROW(A48) -> 48 | D51: 45647 | E51: 45649 | F51: QAA-3166 | G51: =IF(AND(E51<>"",E51<TODAY()),"Disponible",IFERROR(INDEX(Vehiculos[Estado Vehiculo],MATCH(F51,Vehiculos[Placa Vehiculo],0)),"")) -> Disponible | H51: GALEAS AGUILA FREDY RODOLFO | I51: BASE ORIENTOIL | J51: INCHI | K51: =L50 -> 26327 | L51: 27000 | M51: =L51-K51 -> 673 | Q51: =M51*P51 -> 0 | R51: BASE ORIENTOIL | S51: Diesel | T51: 1.8 | U51: =Rutas[[#This Row],[Precio x Galón ($/gal)]]*Rutas[[#This Row],[Volumen de Combustible (gal)]] -> 195.93 | Y51: =U51+SUM(V51:X51) -> 195.93 | AA51: 108.85 | AB51: =IFERROR(M51/AA51,0) -> 6.1828204 | AC51: =IFERROR(Q51/M51,0) -> 0
C52: =ROW(A49) -> 49 | D52: 45649 | E52: 45652 | F52: QAA-3166 | G52: =IF(AND(E52<>"",E52<TODAY()),"Disponible",IFERROR(INDEX(Vehiculos[Estado Vehiculo],MATCH(F52,Vehiculos[Placa Vehiculo],0)),"")) -> Disponible | H52: CORDOVA CELI ANDRES ALEXANDER | I52: BASE ORIENTOIL | J52: INCHI | K52: =L51 -> 27000 | L52: 27922 | M52: =L52-K52 -> 922 | Q52: =M52*P52 -> 0 | R52: BASE ORIENTOIL | S52: Diesel | T52: 1.8 | U52: =Rutas[[#This Row],[Precio x Galón ($/gal)]]*Rutas[[#This Row],[Volumen de Combustible (gal)]] -> 180.018 | Y52: =U52+SUM(V52:X52) -> 180.018 | AA52: 100.01 | AB52: =IFERROR(M52/AA52,0) -> 9.2190781 | AC52: =IFERROR(Q52/M52,0) -> 0
C53: =ROW(A50) -> 50 | D53: 45652 | E53: 45654 | F53: QAA-3166 | G53: =IF(AND(E53<>"",E53<TODAY()),"Disponible",IFERROR(INDEX(Vehiculos[Estado Vehiculo],MATCH(F53,Vehiculos[Placa Vehiculo],0)),"")) -> Disponible | H53: CORDOVA CELI ANDRES ALEXANDER | I53: BASE ORIENTOIL | J53: INCHI | K53: =L52 -> 27922 | L53: 28837 | M53: =L53-K53 -> 915 | Q53: =M53*P53 -> 0 | R53: BASE ORIENTOIL | S53: Diesel | T53: 1.8 | U53: =Rutas[[#This Row],[Precio x Galón ($/gal)]]*Rutas[[#This Row],[Volumen de Combustible (gal)]] -> 260.298 | Y53: =U53+SUM(V53:X53) -> 260.298 | AA53: 144.61 | AB53: =IFERROR(M53/AA53,0) -> 6.3273633 | AC53: =IFERROR(Q53/M53,0) -> 0
C54: =ROW(A51) -> 51 | D54: 45654 | E54: 45657 | F54: QAA-3166 | G54: =IF(AND(E54<>"",E54<TODAY()),"Disponible",IFERROR(INDEX(Vehiculos[Estado Vehiculo],MATCH(F54,Vehiculos[Placa Vehiculo],0)),"")) -> Disponible | H54: CORDOVA CELI ANDRES ALEXANDER | I54: BASE ORIENTOIL | J54: INCHI | K54: =L53 -> 28837 | L54: 29721 | M54: =L54-K54 -> 884 | Q54: =M54*P54 -> 0 | R54: BASE ORIENTOIL | S54: Diesel | T54: 1.8 | U54: =Rutas[[#This Row],[Precio x Galón ($/gal)]]*Rutas[[#This Row],[Volumen de Combustible (gal)]] -> 224.874 | Y54: =U54+SUM(V54:X54) -> 224.874 | AA54: 124.93 | AB54: =IFERROR(M54/AA54,0) -> 7.0759625 | AC54: =IFERROR(Q54/M54,0) -> 0
C55: =ROW(A52) -> 52 | D55: 45657 | E55: 45657 | F55: QAA-3166 | G55: =IF(AND(E55<>"",E55<TODAY()),"Disponible",IFERROR(INDEX(Vehiculos[Estado Vehiculo],MATCH(F55,Vehiculos[Placa Vehiculo],0)),"")) -> Disponible | H55: CORDOVA CELI ANDRES ALEXANDER | I55: BASE ORIENTOIL | J55: INCHI | K55: =L54 -> 29721 | L55: 30443 | M55: =L55-K55 -> 722 | Q55: =M55*P55 -> 0 | R55: BASE ORIENTOIL | S55: Diesel | T55: 1.8 | U55: =Rutas[[#This Row],[Precio x Galón ($/gal)]]*Rutas[[#This Row],[Volumen de Combustible (gal)]] -> 184.59 | Y55: =U55+SUM(V55:X55) -> 184.59 | AA55: 102.55 | AB55: =IFERROR(M55/AA55,0) -> 7.0404681 | AC55: =IFERROR(Q55/M55,0) -> 0
C56: =ROW(A53) -> 53 | D56: 45509 | E56: 45634 | F56: PFF-2857 | G56: =IF(AND(E56<>"",E56<TODAY()),"Disponible",IFERROR(INDEX(Vehiculos[Estado Vehiculo],MATCH(F56,Vehiculos[Placa Vehiculo],0)),"")) -> Disponible | H56: TACURI GUEVARA LUIS EDUARDO | I56: BASE ORIENTOIL | J56: SUPERVISOR | K56: 68869 | L56: 69453 | M56: =L56-K56 -> 584 | Q56: =M56*P56 -> 0 | R56: BASE ORIENTOIL | S56: Diesel | T56: 1.8 | U56: =Rutas[[#This Row],[Precio x Galón ($/gal)]]*Rutas[[#This Row],[Volumen de Combustible (gal)]] -> 27.45 | Y56: =U56+SUM(V56:X56) -> 27.45 | AA56: 15.25 | AB56: =IFERROR(M56/AA56,0) -> 38.295082 | AC56: =IFERROR(Q56/M56,0) -> 0
C57: =ROW(A54) -> 54 | D57: =E56 -> 45634 | E57: 45637 | F57: PFF-2857 | G57: =IF(AND(E57<>"",E57<TODAY()),"Disponible",IFERROR(INDEX(Vehiculos[Estado Vehiculo],MATCH(F57,Vehiculos[Placa Vehiculo],0)),"")) -> Disponible | H57: TACURI GUEVARA LUIS EDUARDO | I57: BASE ORIENTOIL | J57: SUPERVISOR | K57: =L56 -> 69453 | L57: 70164 | M57: =L57-K57 -> 711 | Q57: =M57*P57 -> 0 | R57: BASE ORIENTOIL | S57: Diesel | T57: 1.8 | U57: =Rutas[[#This Row],[Precio x Galón ($/gal)]]*Rutas[[#This Row],[Volumen de Combustible (gal)]] -> 25.002 | Y57: =U57+SUM(V57:X57) -> 25.002 | AA57: 13.89 | AB57: =IFERROR(M57/AA57,0) -> 51.187905 | AC57: =IFERROR(Q57/M57,0) -> 0
C58: =ROW(A55) -> 55 | D58: =E57 -> 45637 | E58: 45640 | F58: PFF-2857 | G58: =IF(AND(E58<>"",E58<TODAY()),"Disponible",IFERROR(INDEX(Vehiculos[Estado Vehiculo],MATCH(F58,Vehiculos[Placa Vehiculo],0)),"")) -> Disponible | H58: TACURI GUEVARA LUIS EDUARDO | I58: BASE ORIENTOIL | J58: SUPERVISOR | K58: =L57 -> 70164 | L58: 70755 | M58: =L58-K58 -> 591 | Q58: =M58*P58 -> 0 | R58: BASE ORIENTOIL | S58: Diesel | T58: 1.8 | U58: =Rutas[[#This Row],[Precio x Galón ($/gal)]]*Rutas[[#This Row],[Volumen de Combustible (gal)]] -> 28.944 | Y58: =U58+SUM(V58:X58) -> 28.944 | AA58: 16.08 | AB58: =IFERROR(M58/AA58,0) -> 36.753731 | AC58: =IFERROR(Q58/M58,0) -> 0
C59: =ROW(A56) -> 56 | D59: =E58 -> 45640 | E59: 45647 | F59: PFF-2857 | G59: =IF(AND(E59<>"",E59<TODAY()),"Disponible",IFERROR(INDEX(Vehiculos[Estado Vehiculo],MATCH(F59,Vehiculos[Placa Vehiculo],0)),"")) -> Disponible | H59: TACURI GUEVARA LUIS EDUARDO | I59: BASE ORIENTOIL | J59: SUPERVISOR | K59: =L58 -> 70755 | L59: 72398 | M59: =L59-K59 -> 1643 | Q59: =M59*P59 -> 0 | R59: BASE ORIENTOIL | S59: Diesel | T59: 1.8 | U59: =Rutas[[#This Row],[Precio x Galón ($/gal)]]*Rutas[[#This Row],[Volumen de Combustible (gal)]] -> 26.082 | Y59: =U59+SUM(V59:X59) -> 26.082 | AA59: 14.49 | AB59: =IFERROR(M59/AA59,0) -> 113.38854 | AC59: =IFERROR(Q59/M59,0) -> 0
C60: =ROW(A57) -> 57 | D60: =E59 -> 45647 | E60: 45653 | F60: PFF-2857 | G60: =IF(AND(E60<>"",E60<TODAY()),"Disponible",IFERROR(INDEX(Vehiculos[Estado Vehiculo],MATCH(F60,Vehiculos[Placa Vehiculo],0)),"")) -> Disponible | H60: SILVA FERNANDO | I60: BASE ORIENTOIL | J60: SUPERVISOR | K60: =L59 -> 72398 | L60: 73069 | M60: =L60-K60 -> 671 | Q60: =M60*P60 -> 0 | R60: BASE ORIENTOIL | S60: Diesel | T60: 1.8 | U60: =Rutas[[#This Row],[Precio x Galón ($/gal)]]*Rutas[[#This Row],[Volumen de Combustible (gal)]] -> 28.35 | Y60: =U60+SUM(V60:X60) -> 28.35 | AA60: 15.75 | AB60: =IFERROR(M60/AA60,0) -> 42.603175 | AC60: =IFERROR(Q60/M60,0) -> 0
C61: =ROW(A58) -> 58 | D61: =E60 -> 45653 | E61: 45654 | F61: PFF-2857 | G61: =IF(AND(E61<>"",E61<TODAY()),"Disponible",IFERROR(INDEX(Vehiculos[Estado Vehiculo],MATCH(F61,Vehiculos[Placa Vehiculo],0)),"")) -> Disponible | H61: SILVA FERNANDO | I61: BASE ORIENTOIL | J61: SUPERVISOR | K61: =L60 -> 73069 | L61: 73385 | M61: =L61-K61 -> 316 | Q61: =M61*P61 -> 0 | R61: BASE ORIENTOIL | S61: Diesel | T61: 1.8 | U61: =Rutas[[#This Row],[Precio x Galón ($/gal)]]*Rutas[[#This Row],[Volumen de Combustible (gal)]] -> 18.9 | Y61: =U61+SUM(V61:X61) -> 18.9 | AA61: 10.5 | AB61: =IFERROR(M61/AA61,0) -> 30.095238 | AC61: =IFERROR(Q61/M61,0) -> 0
C62: =ROW(A59) -> 59 | D62: 46019 | E62: 45656 | F62: PFF-2857 | G62: =IF(AND(E62<>"",E62<TODAY()),"Disponible",IFERROR(INDEX(Vehiculos[Estado Vehiculo],MATCH(F62,Vehiculos[Placa Vehiculo],0)),"")) -> Disponible | H62: SILVA FERNANDO | I62: BASE ORIENTOIL | J62: SUPERVISOR | K62: 73385 | L62: 74003 | M62: =L62-K62 -> 618 | Q62: =M62*P62 -> 0 | R62: BASE ORIENTOIL | S62: Diesel | T62: 1.8 | U62: =Rutas[[#This Row],[Precio x Galón ($/gal)]]*Rutas[[#This Row],[Volumen de Combustible (gal)]] -> 27.18 | Y62: =U62+SUM(V62:X62) -> 27.18 | AA62: 15.1 | AB62: =IFERROR(M62/AA62,0) -> 40.927152 | AC62: =IFERROR(Q62/M62,0) -> 0
C63: =ROW(A60) -> 60 | D63: 45627 | E63: 45633 | F63: PAB-3424 | G63: =IF(AND(E63<>"",E63<TODAY()),"Disponible",IFERROR(INDEX(Vehiculos[Estado Vehiculo],MATCH(F63,Vehiculos[Placa Vehiculo],0)),"")) -> Disponible | H63: CAMACHO MORENO GILSON ADALBERTO | I63: GASOLINERA | J63: PARAISO | M63: =L63-K63 -> 0 | Q63: =M63*P63 -> 0 | R63: GASOLINERA SAN JOSE | S63: Diesel | T63: 1.8 | U63: =Rutas[[#This Row],[Precio x Galón ($/gal)]]*Rutas[[#This Row],[Volumen de Combustible (gal)]] -> 99 | Y63: =U63+SUM(V63:X63) -> 99 | AA63: 55 | AB63: =IFERROR(M63/AA63,0) -> 0 | AC63: =IFERROR(Q63/M63,0) -> 0
C64: =ROW(A61) -> 61 | D64: 45633 | E64: 45641 | F64: PAB-3424 | G64: =IF(AND(E64<>"",E64<TODAY()),"Disponible",IFERROR(INDEX(Vehiculos[Estado Vehiculo],MATCH(F64,Vehiculos[Placa Vehiculo],0)),"")) -> Disponible | H64: CAMACHO MORENO GILSON ADALBERTO | I64: GASOLINERA | J64: PARAISO | M64: =L64-K64 -> 0 | Q64: =M64*P64 -> 0 | R64: GASOLINERA SAN JOSE | S64: Diesel | T64: 1.8 | U64: =Rutas[[#This Row],[Precio x Galón ($/gal)]]*Rutas[[#This Row],[Volumen de Combustible (gal)]] -> 108 | Y64: =U64+SUM(V64:X64) -> 108 | AA64: 60 | AB64: =IFERROR(M64/AA64,0) -> 0 | AC64: =IFERROR(Q64/M64,0) -> 0
C65: =ROW(A62) -> 62 | D65: 45641 | E65: 45646 | F65: PAB-3424 | G65: =IF(AND(E65<>"",E65<TODAY()),"Disponible",IFERROR(INDEX(Vehiculos[Estado Vehiculo],MATCH(F65,Vehiculos[Placa Vehiculo],0)),"")) -> Disponible | H65: CAMACHO MORENO GILSON ADALBERTO | I65: GASOLINERA | J65: PARAISO | M65: =L65-K65 -> 0 | Q65: =M65*P65 -> 0 | R65: GASOLINERA SAN JOSE | S65: Diesel | T65: 1.8 | U65: =Rutas[[#This Row],[Precio x Galón ($/gal)]]*Rutas[[#This Row],[Volumen de Combustible (gal)]] -> 99 | Y65: =U65+SUM(V65:X65) -> 99 | AA65: 55 | AB65: =IFERROR(M65/AA65,0) -> 0 | AC65: =IFERROR(Q65/M65,0) -> 0
C66: =ROW(A63) -> 63 | D66: 45646 | E66: 45654 | F66: PAB-3424 | G66: =IF(AND(E66<>"",E66<TODAY()),"Disponible",IFERROR(INDEX(Vehiculos[Estado Vehiculo],MATCH(F66,Vehiculos[Placa Vehiculo],0)),"")) -> Disponible | H66: CAMACHO MORENO GILSON ADALBERTO | I66: GASOLINERA | J66: PARAISO | M66: =L66-K66 -> 0 | Q66: =M66*P66 -> 0 | R66: GASOLINERA SAN JOSE | S66: Diesel | T66: 1.8 | U66: =Rutas[[#This Row],[Precio x Galón ($/gal)]]*Rutas[[#This Row],[Volumen de Combustible (gal)]] -> 108 | Y66: =U66+SUM(V66:X66) -> 108 | AA66: 60 | AB66: =IFERROR(M66/AA66,0) -> 0 | AC66: =IFERROR(Q66/M66,0) -> 0
C67: =ROW(A64) -> 64 | D67: 45654 | E67: 45657 | F67: PAB-3424 | G67: =IF(AND(E67<>"",E67<TODAY()),"Disponible",IFERROR(INDEX(Vehiculos[Estado Vehiculo],MATCH(F67,Vehiculos[Placa Vehiculo],0)),"")) -> Disponible | H67: CAMACHO MORENO GILSON ADALBERTO | I67: GASOLINERA | J67: PARAISO | M67: =L67-K67 -> 0 | Q67: =M67*P67 -> 0 | R67: GASOLINERA SAN JOSE | S67: Diesel | T67: 1.8 | U67: =Rutas[[#This Row],[Precio x Galón ($/gal)]]*Rutas[[#This Row],[Volumen de Combustible (gal)]] -> 126 | Y67: =U67+SUM(V67:X67) -> 126 | AA67: 70 | AB67: =IFERROR(M67/AA67,0) -> 0 | AC67: =IFERROR(Q67/M67,0) -> 0
C68: =ROW(A65) -> 65 | D68: 45627 | E68: 45633 | F68: IAA-2747 | G68: =IF(AND(E68<>"",E68<TODAY()),"Disponible",IFERROR(INDEX(Vehiculos[Estado Vehiculo],MATCH(F68,Vehiculos[Placa Vehiculo],0)),"")) -> Disponible | H68: BRAVO SONGOR MARCO HERNAN | I68: GASOLINERA | J68: PARAISO | M68: =L68-K68 -> 0 | Q68: =M68*P68 -> 0 | R68: GASOLINERA MIRAFLORES | S68: Diesel | T68: 1.8 | U68: =Rutas[[#This Row],[Precio x Galón ($/gal)]]*Rutas[[#This Row],[Volumen de Combustible (gal)]] -> 99 | Y68: =U68+SUM(V68:X68) -> 99 | AA68: 55 | AB68: =IFERROR(M68/AA68,0) -> 0 | AC68: =IFERROR(Q68/M68,0) -> 0
C69: =ROW(A66) -> 66 | D69: 45633 | E69: 45641 | F69: IAA-2747 | G69: =IF(AND(E69<>"",E69<TODAY()),"Disponible",IFERROR(INDEX(Vehiculos[Estado Vehiculo],MATCH(F69,Vehiculos[Placa Vehiculo],0)),"")) -> Disponible | H69: BRAVO SONGOR MARCO HERNAN | I69: GASOLINERA | J69: PARAISO | M69: =L69-K69 -> 0 | Q69: =M69*P69 -> 0 | R69: GASOLINERA MIRAFLORES | S69: Diesel | T69: 1.8 | U69: =Rutas[[#This Row],[Precio x Galón ($/gal)]]*Rutas[[#This Row],[Volumen de Combustible (gal)]] -> 108 | Y69: =U69+SUM(V69:X69) -> 108 | AA69: 60 | AB69: =IFERROR(M69/AA69,0) -> 0 | AC69: =IFERROR(Q69/M69,0) -> 0
C70: =ROW(A67) -> 67 | D70: 45641 | E70: 45646 | F70: IAA-2747 | G70: =IF(AND(E70<>"",E70<TODAY()),"Disponible",IFERROR(INDEX(Vehiculos[Estado Vehiculo],MATCH(F70,Vehiculos[Placa Vehiculo],0)),"")) -> Disponible | H70: BRAVO SONGOR MARCO HERNAN | I70: GASOLINERA | J70: PARAISO | M70: =L70-K70 -> 0 | Q70: =M70*P70 -> 0 | R70: GASOLINERA MIRAFLORES | S70: Diesel | T70: 1.8 | U70: =Rutas[[#This Row],[Precio x Galón ($/gal)]]*Rutas[[#This Row],[Volumen de Combustible (gal)]] -> 99 | Y70: =U70+SUM(V70:X70) -> 99 | AA70: 55 | AB70: =IFERROR(M70/AA70,0) -> 0 | AC70: =IFERROR(Q70/M70,0) -> 0
C71: =ROW(A68) -> 68 | D71: 45646 | E71: 45654 | F71: IAA-2747 | G71: =IF(AND(E71<>"",E71<TODAY()),"Disponible",IFERROR(INDEX(Vehiculos[Estado Vehiculo],MATCH(F71,Vehiculos[Placa Vehiculo],0)),"")) -> Disponible | H71: BRAVO SONGOR MARCO HERNAN | I71: GASOLINERA | J71: PARAISO | M71: =L71-K71 -> 0 | Q71: =M71*P71 -> 0 | R71: GASOLINERA MIRAFLORES | S71: Diesel | T71: 1.8 | U71: =Rutas[[#This Row],[Precio x Galón ($/gal)]]*Rutas[[#This Row],[Volumen de Combustible (gal)]] -> 108 | Y71: =U71+SUM(V71:X71) -> 108 | AA71: 60 | AB71: =IFERROR(M71/AA71,0) -> 0 | AC71: =IFERROR(Q71/M71,0) -> 0
C72: =ROW(A69) -> 69 | D72: 45654 | E72: 45657 | F72: IAA-2747 | G72: =IF(AND(E72<>"",E72<TODAY()),"Disponible",IFERROR(INDEX(Vehiculos[Estado Vehiculo],MATCH(F72,Vehiculos[Placa Vehiculo],0)),"")) -> Disponible | H72: BRAVO SONGOR MARCO HERNAN | I72: GASOLINERA | J72: PARAISO | M72: =L72-K72 -> 0 | Q72: =M72*P72 -> 0 | R72: GASOLINERA MIRAFLORES | S72: Diesel | T72: 1.8 | U72: =Rutas[[#This Row],[Precio x Galón ($/gal)]]*Rutas[[#This Row],[Volumen de Combustible (gal)]] -> 117 | Y72: =U72+SUM(V72:X72) -> 117 | AA72: 65 | AB72: =IFERROR(M72/AA72,0) -> 0 | AC72: =IFERROR(Q72/M72,0) -> 0
C73: =ROW(A70) -> 70 | G73: =IF(AND(E73<>"",E73<TODAY()),"Disponible",IFERROR(INDEX(Vehiculos[Estado Vehiculo],MATCH(F73,Vehiculos[Placa Vehiculo],0)),"")) | M73: =L73-K73 -> 0 | Q73: =M73*P73 -> 0 | Y73: =U73+SUM(V73:X73) -> 0 | AB73: =IFERROR(M73/AA73,0) -> 0 | AC73: =IFERROR(Q73/M73,0) -> 0
C74: =ROW(A71) -> 71 | G74: =IF(AND(E74<>"",E74<TODAY()),"Disponible",IFERROR(INDEX(Vehiculos[Estado Vehiculo],MATCH(F74,Vehiculos[Placa Vehiculo],0)),"")) | M74: =L74-K74 -> 0 | Q74: =M74*P74 -> 0 | Y74: =U74+SUM(V74:X74) -> 0 | AB74: =IFERROR(M74/AA74,0) -> 0 | AC74: =IFERROR(Q74/M74,0) -> 0
C75: =ROW(A72) -> 72 | D75: 45995 | E75: 45633 | F75: KR-1189/42416 | G75: =IF(AND(E75<>"",E75<TODAY()),"Disponible",IFERROR(INDEX(Vehiculos[Estado Vehiculo],MATCH(F75,Vehiculos[Placa Vehiculo],0)),"")) -> Disponible | H75: MOSCUY RAMIREZ MILVIO PAUL | I75: BASE ORIENTOIL | J75: MDC | K75: 1085 | L75: 1102 | M75: =L75-K75 -> 17 | Q75: =M75*P75 -> 0 | R75: BASE ORIENTOIL | S75: Diesel | T75: 1.8 | U75: =Rutas[[#This Row],[Precio x Galón ($/gal)]]*Rutas[[#This Row],[Volumen de Combustible (gal)]] -> 19.836 | Y75: =U75+SUM(V75:X75) -> 19.836 | AA75: 11.02 | AB75: =IFERROR(M75/AA75,0) -> 1.5426497 | AC75: =IFERROR(Q75/M75,0) -> 0
C76: =ROW(A73) -> 73 | D76: =E75 -> 45633 | E76: 45639 | F76: KR-1189/42416 | G76: =IF(AND(E76<>"",E76<TODAY()),"Disponible",IFERROR(INDEX(Vehiculos[Estado Vehiculo],MATCH(F76,Vehiculos[Placa Vehiculo],0)),"")) -> Disponible | H76: MOSCUY RAMIREZ MILVIO PAUL | I76: BASE ORIENTOIL | J76: MDC | K76: 1102 | L76: 1121 | M76: =L76-K76 -> 19 | Q76: =M76*P76 -> 0 | R76: BASE ORIENTOIL | S76: Diesel | T76: 1.8 | U76: =Rutas[[#This Row],[Precio x Galón ($/gal)]]*Rutas[[#This Row],[Volumen de Combustible (gal)]] -> 20.034 | Y76: =U76+SUM(V76:X76) -> 20.034 | AA76: 11.13 | AB76: =IFERROR(M76/AA76,0) -> 1.7070979 | AC76: =IFERROR(Q76/M76,0) -> 0
C77: =ROW(A74) -> 74 | D77: =E76 -> 45639 | E77: 45645 | F77: KR-1189/42416 | G77: =IF(AND(E77<>"",E77<TODAY()),"Disponible",IFERROR(INDEX(Vehiculos[Estado Vehiculo],MATCH(F77,Vehiculos[Placa Vehiculo],0)),"")) -> Disponible | H77: MOSCUY RAMIREZ MILVIO PAUL | I77: BASE ORIENTOIL | J77: MDC | K77: =L76 -> 1121 | L77: 1135 | M77: =L77-K77 -> 14 | Q77: =M77*P77 -> 0 | R77: BASE ORIENTOIL | S77: Diesel | T77: 1.8 | U77: =Rutas[[#This Row],[Precio x Galón ($/gal)]]*Rutas[[#This Row],[Volumen de Combustible (gal)]] -> 18.054 | Y77: =U77+SUM(V77:X77) -> 18.054 | AA77: 10.03 | AB77: =IFERROR(M77/AA77,0) -> 1.3958126 | AC77: =IFERROR(Q77/M77,0) -> 0
C78: =ROW(A75) -> 75 | D78: =E77 -> 45645 | E78: 45650 | F78: KR-1189/42416 | G78: =IF(AND(E78<>"",E78<TODAY()),"Disponible",IFERROR(INDEX(Vehiculos[Estado Vehiculo],MATCH(F78,Vehiculos[Placa Vehiculo],0)),"")) -> Disponible | H78: MOSCUY RAMIREZ MILVIO PAUL | I78: BASE ORIENTOIL | J78: MDC | K78: =L77 -> 1135 | L78: 1157 | M78: =L78-K78 -> 22 | Q78: =M78*P78 -> 0 | R78: BASE ORIENTOIL | S78: Diesel | T78: 1.8 | U78: =Rutas[[#This Row],[Precio x Galón ($/gal)]]*Rutas[[#This Row],[Volumen de Combustible (gal)]] -> 14.04 | Y78: =U78+SUM(V78:X78) -> 14.04 | AA78: 7.8 | AB78: =IFERROR(M78/AA78,0) -> 2.8205128 | AC78: =IFERROR(Q78/M78,0) -> 0
C79: =ROW(A76) -> 76 | D79: =E78 -> 45650 | E79: 45656 | F79: KR-1189/42416 | G79: =IF(AND(E79<>"",E79<TODAY()),"Disponible",IFERROR(INDEX(Vehiculos[Estado Vehiculo],MATCH(F79,Vehiculos[Placa Vehiculo],0)),"")) -> Disponible | H79: SAMANIEGO RICHARD | I79: BASE ORIENTOIL | J79: MDC | K79: =L78 -> 1157 | L79: 1173 | M79: =L79-K79 -> 16 | Q79: =M79*P79 -> 0 | R79: BASE ORIENTOIL | S79: Diesel | T79: 1.8 | U79: =Rutas[[#This Row],[Precio x Galón ($/gal)]]*Rutas[[#This Row],[Volumen de Combustible (gal)]] -> 16.974 | Y79: =U79+SUM(V79:X79) -> 16.974 | AA79: 9.43 | AB79: =IFERROR(M79/AA79,0) -> 1.6967126 | AC79: =IFERROR(Q79/M79,0) -> 0
C80: =ROW(A77) -> 77 | D80: =E79 -> 45656 | E80: 45657 | F80: KR-1189/42416 | G80: =IF(AND(E80<>"",E80<TODAY()),"Disponible",IFERROR(INDEX(Vehiculos[Estado Vehiculo],MATCH(F80,Vehiculos[Placa Vehiculo],0)),"")) -> Disponible | H80: SAMANIEGO RICHARD | I80: BASE ORIENTOIL | J80: MDC | K80: =L79 -> 1173 | L80: 1187 | M80: =L80-K80 -> 14 | Q80: =M80*P80 -> 0 | R80: BASE ORIENTOIL | S80: Diesel | T80: 1.8 | U80: =Rutas[[#This Row],[Precio x Galón ($/gal)]]*Rutas[[#This Row],[Volumen de Combustible (gal)]] -> 203.328 | Y80: =U80+SUM(V80:X80) -> 203.328 | AA80: 112.96 | AB80: =IFERROR(M80/AA80,0) -> 0.12393768 | AC80: =IFERROR(Q80/M80,0) -> 0
C81: =ROW(A78) -> 78 | D81: 45628 | E81: 45635 | F81: KR-1172/42409 | G81: =IF(AND(E81<>"",E81<TODAY()),"Disponible",IFERROR(INDEX(Vehiculos[Estado Vehiculo],MATCH(F81,Vehiculos[Placa Vehiculo],0)),"")) -> Disponible | H81: PONCE RUIZ SIXTO LUBERNDI | I81: BASE ORIENTOIL | J81: MDC | K81: 3861 | L81: 3884 | M81: =L81-K81 -> 23 | Q81: =M81*P81 -> 0 | R81: BASE ORIENTOIL | S81: Diesel | T81: 1.8 | U81: =Rutas[[#This Row],[Precio x Galón ($/gal)]]*Rutas[[#This Row],[Volumen de Combustible (gal)]] -> 30.726 | Y81: =U81+SUM(V81:X81) -> 30.726 | AA81: 17.07 | AB81: =IFERROR(M81/AA81,0) -> 1.3473931 | AC81: =IFERROR(Q81/M81,0) -> 0
C82: =ROW(A79) -> 79 | D82: 45635 | E82: 45652 | F82: KR-1172/42409 | G82: =IF(AND(E82<>"",E82<TODAY()),"Disponible",IFERROR(INDEX(Vehiculos[Estado Vehiculo],MATCH(F82,Vehiculos[Placa Vehiculo],0)),"")) -> Disponible | H82: PONCE RUIZ SIXTO LUBERNDI | I82: BASE ORIENTOIL | J82: MDC | K82: 3884 | L82: 3934 | M82: =L82-K82 -> 50 | Q82: =M82*P82 -> 0 | R82: BASE ORIENTOIL | S82: Diesel | T82: 1.8 | U82: =Rutas[[#This Row],[Precio x Galón ($/gal)]]*Rutas[[#This Row],[Volumen de Combustible (gal)]] -> 20.412 | Y82: =U82+SUM(V82:X82) -> 20.412 | AA82: 11.34 | AB82: =IFERROR(M82/AA82,0) -> 4.4091711 | AC82: =IFERROR(Q82/M82,0) -> 0
C83: =ROW(A80) -> 80 | D83: 45652 | E83: 45657 | F83: KR-1172/42409 | G83: =IF(AND(E83<>"",E83<TODAY()),"Disponible",IFERROR(INDEX(Vehiculos[Estado Vehiculo],MATCH(F83,Vehiculos[Placa Vehiculo],0)),"")) -> Disponible | H83: PONCE RUIZ SIXTO LUBERNDI | I83: BASE ORIENTOIL | J83: MDC | K83: 3934 | L83: 3957 | M83: =L83-K83 -> 23 | Q83: =M83*P83 -> 0 | R83: BASE ORIENTOIL | S83: Diesel | T83: 1.8 | U83: =Rutas[[#This Row],[Precio x Galón ($/gal)]]*Rutas[[#This Row],[Volumen de Combustible (gal)]] -> 19.8 | Y83: =U83+SUM(V83:X83) -> 19.8 | AA83: 11 | AB83: =IFERROR(M83/AA83,0) -> 2.0909091 | AC83: =IFERROR(Q83/M83,0) -> 0
C84: =ROW(A81) -> 81 | D84: 45628 | E84: 45631 | F84: KR-1344/42429 | G84: =IF(AND(E84<>"",E84<TODAY()),"Disponible",IFERROR(INDEX(Vehiculos[Estado Vehiculo],MATCH(F84,Vehiculos[Placa Vehiculo],0)),"")) -> Disponible | H84: ORDOÑEZ CALLE JOSE SALVADOR | I84: BASE ORIENTOIL | J84: MDC | K84: 15 | L84: 37 | M84: =L84-K84 -> 22 | Q84: =M84*P84 -> 0 | R84: BASE ORIENTOIL | S84: Diesel | T84: 1.8 | U84: =Rutas[[#This Row],[Precio x Galón ($/gal)]]*Rutas[[#This Row],[Volumen de Combustible (gal)]] -> 17.982 | Y84: =U84+SUM(V84:X84) -> 17.982 | AA84: 9.99 | AB84: =IFERROR(M84/AA84,0) -> 2.2022022 | AC84: =IFERROR(Q84/M84,0) -> 0
C85: =ROW(A82) -> 82 | D85: =E84 -> 45631 | E85: 45635 | F85: KR-1344/42429 | G85: =IF(AND(E85<>"",E85<TODAY()),"Disponible",IFERROR(INDEX(Vehiculos[Estado Vehiculo],MATCH(F85,Vehiculos[Placa Vehiculo],0)),"")) -> Disponible | H85: ORDOÑEZ CALLE JOSE SALVADOR | I85: BASE ORIENTOIL | J85: MDC | K85: =L84 -> 37 | L85: 61 | M85: =L85-K85 -> 24 | Q85: =M85*P85 -> 0 | R85: BASE ORIENTOIL | S85: Diesel | T85: 1.8 | U85: =Rutas[[#This Row],[Precio x Galón ($/gal)]]*Rutas[[#This Row],[Volumen de Combustible (gal)]] -> 20.214 | Y85: =U85+SUM(V85:X85) -> 20.214 | AA85: 11.23 | AB85: =IFERROR(M85/AA85,0) -> 2.1371327 | AC85: =IFERROR(Q85/M85,0) -> 0
C86: =ROW(A83) -> 83 | D86: =E85 -> 45635 | E86: 45638 | F86: KR-1344/42429 | G86: =IF(AND(E86<>"",E86<TODAY()),"Disponible",IFERROR(INDEX(Vehiculos[Estado Vehiculo],MATCH(F86,Vehiculos[Placa Vehiculo],0)),"")) -> Disponible | H86: ORDOÑEZ CALLE JOSE SALVADOR | I86: BASE ORIENTOIL | J86: MDC | K86: =L85 -> 61 | L86: 86 | M86: =L86-K86 -> 25 | Q86: =M86*P86 -> 0 | R86: BASE ORIENTOIL | S86: Diesel | T86: 1.8 | U86: =Rutas[[#This Row],[Precio x Galón ($/gal)]]*Rutas[[#This Row],[Volumen de Combustible (gal)]] -> 23.13 | Y86: =U86+SUM(V86:X86) -> 23.13 | AA86: 12.85 | AB86: =IFERROR(M86/AA86,0) -> 1.9455253 | AC86: =IFERROR(Q86/M86,0) -> 0
C87: =ROW(A84) -> 84 | D87: =E86 -> 45638 | E87: 45642 | F87: KR-1344/42429 | G87: =IF(AND(E87<>"",E87<TODAY()),"Disponible",IFERROR(INDEX(Vehiculos[Estado Vehiculo],MATCH(F87,Vehiculos[Placa Vehiculo],0)),"")) -> Disponible | H87: ORDOÑEZ CALLE JOSE SALVADOR | I87: BASE ORIENTOIL | J87: MDC | K87: =L86 -> 86 | L87: 111 | M87: =L87-K87 -> 25 | Q87: =M87*P87 -> 0 | R87: BASE ORIENTOIL | S87: Diesel | T87: 1.8 | U87: =Rutas[[#This Row],[Precio x Galón ($/gal)]]*Rutas[[#This Row],[Volumen de Combustible (gal)]] -> 23.76 | Y87: =U87+SUM(V87:X87) -> 23.76 | AA87: 13.2 | AB87: =IFERROR(M87/AA87,0) -> 1.8939394 | AC87: =IFERROR(Q87/M87,0) -> 0
C88: =ROW(A85) -> 85 | D88: =E87 -> 45642 | E88: 45645 | F88: KR-1344/42429 | G88: =IF(AND(E88<>"",E88<TODAY()),"Disponible",IFERROR(INDEX(Vehiculos[Estado Vehiculo],MATCH(F88,Vehiculos[Placa Vehiculo],0)),"")) -> Disponible | H88: GALEAS AGUILA FREDY RODOLFO | I88: BASE ORIENTOIL | J88: MDC | K88: =L87 -> 111 | L88: 127 | M88: =L88-K88 -> 16 | Q88: =M88*P88 -> 0 | R88: BASE ORIENTOIL | S88: Diesel | T88: 1.8 | U88: =Rutas[[#This Row],[Precio x Galón ($/gal)]]*Rutas[[#This Row],[Volumen de Combustible (gal)]] -> 25.668 | Y88: =U88+SUM(V88:X88) -> 25.668 | AA88: 14.26 | AB88: =IFERROR(M88/AA88,0) -> 1.1220196 | AC88: =IFERROR(Q88/M88,0) -> 0
C89: =ROW(A86) -> 86 | D89: =E88 -> 45645 | E89: 45649 | F89: KR-1344/42429 | G89: =IF(AND(E89<>"",E89<TODAY()),"Disponible",IFERROR(INDEX(Vehiculos[Estado Vehiculo],MATCH(F89,Vehiculos[Placa Vehiculo],0)),"")) -> Disponible | H89: GALEAS AGUILA FREDY RODOLFO | I89: BASE ORIENTOIL | J89: MDC | K89: =L88 -> 127 | L89: 152 | M89: =L89-K89 -> 25 | Q89: =M89*P89 -> 0 | R89: BASE ORIENTOIL | S89: Diesel | T89: 1.8 | U89: =Rutas[[#This Row],[Precio x Galón ($/gal)]]*Rutas[[#This Row],[Volumen de Combustible (gal)]] -> 12.618 | Y89: =U89+SUM(V89:X89) -> 12.618 | AA89: 7.01 | AB89: =IFERROR(M89/AA89,0) -> 3.5663338 | AC89: =IFERROR(Q89/M89,0) -> 0
C90: =ROW(A87) -> 87 | D90: =E89 -> 45649 | E90: 45652 | F90: KR-1344/42429 | G90: =IF(AND(E90<>"",E90<TODAY()),"Disponible",IFERROR(INDEX(Vehiculos[Estado Vehiculo],MATCH(F90,Vehiculos[Placa Vehiculo],0)),"")) -> Disponible | H90: CORDOVA CELI ANDRES ALEXANDER | I90: BASE ORIENTOIL | J90: MDC | K90: =L89 -> 152 | L90: 170 | M90: =L90-K90 -> 18 | Q90: =M90*P90 -> 0 | R90: BASE ORIENTOIL | S90: Diesel | T90: 1.8 | U90: =Rutas[[#This Row],[Precio x Galón ($/gal)]]*Rutas[[#This Row],[Volumen de Combustible (gal)]] -> 18.198 | Y90: =U90+SUM(V90:X90) -> 18.198 | AA90: 10.11 | AB90: =IFERROR(M90/AA90,0) -> 1.7804154 | AC90: =IFERROR(Q90/M90,0) -> 0
C91: =ROW(A88) -> 88 | D91: =E90 -> 45652 | E91: 45654 | F91: KR-1344/42429 | G91: =IF(AND(E91<>"",E91<TODAY()),"Disponible",IFERROR(INDEX(Vehiculos[Estado Vehiculo],MATCH(F91,Vehiculos[Placa Vehiculo],0)),"")) -> Disponible | H91: CORDOVA CELI ANDRES ALEXANDER | I91: BASE ORIENTOIL | J91: MDC | K91: =L90 -> 170 | L91: 184 | M91: =L91-K91 -> 14 | Q91: =M91*P91 -> 0 | R91: BASE ORIENTOIL | S91: Diesel | T91: 1.8 | U91: =Rutas[[#This Row],[Precio x Galón ($/gal)]]*Rutas[[#This Row],[Volumen de Combustible (gal)]] -> 18.072 | Y91: =U91+SUM(V91:X91) -> 18.072 | AA91: 10.04 | AB91: =IFERROR(M91/AA91,0) -> 1.3944223 | AC91: =IFERROR(Q91/M91,0) -> 0
C92: =ROW(A89) -> 89 | D92: =E91 -> 45654 | E92: 45657 | F92: KR-1344/42429 | G92: =IF(AND(E92<>"",E92<TODAY()),"Disponible",IFERROR(INDEX(Vehiculos[Estado Vehiculo],MATCH(F92,Vehiculos[Placa Vehiculo],0)),"")) -> Disponible | H92: CORDOVA CELI ANDRES ALEXANDER | I92: BASE ORIENTOIL | J92: MDC | K92: =L91 -> 184 | L92: 201 | M92: =L92-K92 -> 17 | Q92: =M92*P92 -> 0 | R92: BASE ORIENTOIL | S92: Diesel | T92: 1.8 | U92: =Rutas[[#This Row],[Precio x Galón ($/gal)]]*Rutas[[#This Row],[Volumen de Combustible (gal)]] -> 12.546 | Y92: =U92+SUM(V92:X92) -> 12.546 | AA92: 6.97 | AB92: =IFERROR(M92/AA92,0) -> 2.4390244 | AC92: =IFERROR(Q92/M92,0) -> 0
C93: =ROW(A90) -> 90 | D93: =E92 -> 45657 | E93: 45657 | F93: KR-1344/42429 | G93: =IF(AND(E93<>"",E93<TODAY()),"Disponible",IFERROR(INDEX(Vehiculos[Estado Vehiculo],MATCH(F93,Vehiculos[Placa Vehiculo],0)),"")) -> Disponible | H93: CORDOVA CELI ANDRES ALEXANDER | I93: BASE ORIENTOIL | J93: MDC | K93: =L92 -> 201 | L93: 213 | M93: =L93-K93 -> 12 | Q93: =M93*P93 -> 0 | R93: BASE ORIENTOIL | S93: Diesel | T93: 1.8 | U93: =Rutas[[#This Row],[Precio x Galón ($/gal)]]*Rutas[[#This Row],[Volumen de Combustible (gal)]] -> 384.3 | Y93: =U93+SUM(V93:X93) -> 384.3 | AA93: 213.5 | AB93: =IFERROR(M93/AA93,0) -> 0.056206089 | AC93: =IFERROR(Q93/M93,0) -> 0
C94: =ROW(A91) -> 91 | D94: 45630 | E94: 45633 | F94: KR-1090/42407 | G94: =IF(AND(E94<>"",E94<TODAY()),"Disponible",IFERROR(INDEX(Vehiculos[Estado Vehiculo],MATCH(F94,Vehiculos[Placa Vehiculo],0)),"")) -> Disponible | H94: CASTILLO VILLALVA EDGAR PATRICIO | I94: BASE ORIENTOIL | J94: MDC | K94: 2582 | L94: 2605 | M94: =L94-K94 -> 23 | Q94: =M94*P94 -> 0 | R94: BASE ORIENTOIL | S94: Diesel | T94: 1.8 | U94: =Rutas[[#This Row],[Precio x Galón ($/gal)]]*Rutas[[#This Row],[Volumen de Combustible (gal)]] -> 16.524 | Y94: =U94+SUM(V94:X94) -> 16.524 | AA94: 9.18 | AB94: =IFERROR(M94/AA94,0) -> 2.5054466 | AC94: =IFERROR(Q94/M94,0) -> 0
C95: =ROW(A92) -> 92 | D95: =E94 -> 45633 | E95: 45636 | F95: KR-1090/42407 | G95: =IF(AND(E95<>"",E95<TODAY()),"Disponible",IFERROR(INDEX(Vehiculos[Estado Vehiculo],MATCH(F95,Vehiculos[Placa Vehiculo],0)),"")) -> Disponible | H95: CASTILLO VILLALVA EDGAR PATRICIO | I95: BASE ORIENTOIL | J95: MDC | K95: =L94 -> 2605 | L95: 2629 | M95: =L95-K95 -> 24 | Q95: =M95*P95 -> 0 | R95: BASE ORIENTOIL | S95: Diesel | T95: 1.8 | U95: =Rutas[[#This Row],[Precio x Galón ($/gal)]]*Rutas[[#This Row],[Volumen de Combustible (gal)]] -> 16.884 | Y95: =U95+SUM(V95:X95) -> 16.884 | AA95: 9.38 | AB95: =IFERROR(M95/AA95,0) -> 2.5586354 | AC95: =IFERROR(Q95/M95,0) -> 0
C96: =ROW(A93) -> 93 | D96: =E95 -> 45636 | E96: 45638 | F96: KR-1090/42407 | G96: =IF(AND(E96<>"",E96<TODAY()),"Disponible",IFERROR(INDEX(Vehiculos[Estado Vehiculo],MATCH(F96,Vehiculos[Placa Vehiculo],0)),"")) -> Disponible | H96: CASTILLO VILLALVA EDGAR PATRICIO | I96: BASE ORIENTOIL | J96: MDC | K96: =L95 -> 2629 | L96: 2645 | M96: =L96-K96 -> 16 | Q96: =M96*P96 -> 0 | R96: BASE ORIENTOIL | S96: Diesel | T96: 1.8 | U96: =Rutas[[#This Row],[Precio x Galón ($/gal)]]*Rutas[[#This Row],[Volumen de Combustible (gal)]] -> 30.402 | Y96: =U96+SUM(V96:X96) -> 30.402 | AA96: 16.89 | AB96: =IFERROR(M96/AA96,0) -> 0.9473061 | AC96: =IFERROR(Q96/M96,0) -> 0
C97: =ROW(A94) -> 94 | D97: =E96 -> 45638 | E97: 45641 | F97: KR-1090/42407 | G97: =IF(AND(E97<>"",E97<TODAY()),"Disponible",IFERROR(INDEX(Vehiculos[Estado Vehiculo],MATCH(F97,Vehiculos[Placa Vehiculo],0)),"")) -> Disponible | H97: ORDOÑEZ MENENDEZ JOSUE ELISEO | I97: BASE ORIENTOIL | J97: MDC | K97: =L96 -> 2645 | L97: 2664 | M97: =L97-K97 -> 19 | Q97: =M97*P97 -> 0 | R97: BASE ORIENTOIL | S97: Diesel | T97: 1.8 | U97: =Rutas[[#This Row],[Precio x Galón ($/gal)]]*Rutas[[#This Row],[Volumen de Combustible (gal)]] -> 20.412 | Y97: =U97+SUM(V97:X97) -> 20.412 | AA97: 11.34 | AB97: =IFERROR(M97/AA97,0) -> 1.675485 | AC97: =IFERROR(Q97/M97,0) -> 0
C98: =ROW(A95) -> 95 | D98: =E97 -> 45641 | E98: 45644 | F98: KR-1090/42407 | G98: =IF(AND(E98<>"",E98<TODAY()),"Disponible",IFERROR(INDEX(Vehiculos[Estado Vehiculo],MATCH(F98,Vehiculos[Placa Vehiculo],0)),"")) -> Disponible | H98: ORDOÑEZ MENENDEZ JOSUE ELISEO | I98: BASE ORIENTOIL | J98: MDC | K98: =L97 -> 2664 | L98: 2687 | M98: =L98-K98 -> 23 | Q98: =M98*P98 -> 0 | R98: BASE ORIENTOIL | S98: Diesel | T98: 1.8 | U98: =Rutas[[#This Row],[Precio x Galón ($/gal)]]*Rutas[[#This Row],[Volumen de Combustible (gal)]] -> 28.89 | Y98: =U98+SUM(V98:X98) -> 28.89 | AA98: 16.05 | AB98: =IFERROR(M98/AA98,0) -> 1.4330218 | AC98: =IFERROR(Q98/M98,0) -> 0
C99: =ROW(A96) -> 96 | D99: =E98 -> 45644 | E99: 45648 | F99: KR-1090/42407 | G99: =IF(AND(E99<>"",E99<TODAY()),"Disponible",IFERROR(INDEX(Vehiculos[Estado Vehiculo],MATCH(F99,Vehiculos[Placa Vehiculo],0)),"")) -> Disponible | H99: ORDOÑEZ MENENDEZ JOSUE ELISEO | I99: BASE ORIENTOIL | J99: MDC | K99: =L98 -> 2687 | L99: 2714 | M99: =L99-K99 -> 27 | Q99: =M99*P99 -> 0 | R99: BASE ORIENTOIL | S99: Diesel | T99: 1.8 | U99: =Rutas[[#This Row],[Precio x Galón ($/gal)]]*Rutas[[#This Row],[Volumen de Combustible (gal)]] -> 18.792 | Y99: =U99+SUM(V99:X99) -> 18.792 | AA99: 10.44 | AB99: =IFERROR(M99/AA99,0) -> 2.5862069 | AC99: =IFERROR(Q99/M99,0) -> 0
A100: B | C100: =ROW(A97) -> 97 | D100: =E99 -> 45648 | E100: 45656 | F100: KR-1090/42407 | G100: =IF(AND(E100<>"",E100<TODAY()),"Disponible",IFERROR(INDEX(Vehiculos[Estado Vehiculo],MATCH(F100,Vehiculos[Placa Vehiculo],0)),"")) -> Disponible | H100: CASTILLO VILLALVA EDGAR PATRICIO | I100: BASE ORIENTOIL | J100: MDC | K100: =L99 -> 2714 | L100: 2748 | M100: =L100-K100 -> 34 | Q100: =M100*P100 -> 0 | R100: BASE ORIENTOIL | S100: Diesel | T100: 1.8 | U100: =Rutas[[#This Row],[Precio x Galón ($/gal)]]*Rutas[[#This Row],[Volumen de Combustible (gal)]] -> 11.25 | Y100: =U100+SUM(V100:X100) -> 11.25 | AA100: 6.25 | AB100: =IFERROR(M100/AA100,0) -> 5.44 | AC100: =IFERROR(Q100/M100,0) -> 0
C101: =ROW(A98) -> 98 | D101: 45639 | E101: 45641 | F101: KR-1188/42405 | G101: =IF(AND(E101<>"",E101<TODAY()),"Disponible",IFERROR(INDEX(Vehiculos[Estado Vehiculo],MATCH(F101,Vehiculos[Placa Vehiculo],0)),"")) -> Disponible | H101: TANDAZO ROSILLO VICTOR HUGO | I101: BASE ORIENTOIL | J101: MDC | K101: 941 | L101: 909 | M101: =L101-K101 -> -32 | Q101: =M101*P101 -> 0 | R101: BASE ORIENTOIL | S101: Diesel | T101: 1.8 | U101: =Rutas[[#This Row],[Precio x Galón ($/gal)]]*Rutas[[#This Row],[Volumen de Combustible (gal)]] -> 39.546 | Y101: =U101+SUM(V101:X101) -> 39.546 | AA101: 21.97 | AB101: =IFERROR(M101/AA101,0) -> -1.4565316 | AC101: =IFERROR(Q101/M101,0) -> 0
C102: =ROW(A99) -> 99 | D102: =E101 -> 45641 | E102: 45646 | F102: KR-1188/42405 | G102: =IF(AND(E102<>"",E102<TODAY()),"Disponible",IFERROR(INDEX(Vehiculos[Estado Vehiculo],MATCH(F102,Vehiculos[Placa Vehiculo],0)),"")) -> Disponible | H102: ESTACIO DAVILA EDWIN ALEXIS | I102: BASE ORIENTOIL | J102: MDC | K102: =L101 -> 909 | L102: 978 | M102: =L102-K102 -> 69 | Q102: =M102*P102 -> 0 | R102: BASE ORIENTOIL | S102: Diesel | T102: 1.8 | U102: =Rutas[[#This Row],[Precio x Galón ($/gal)]]*Rutas[[#This Row],[Volumen de Combustible (gal)]] -> 23.652 | Y102: =U102+SUM(V102:X102) -> 23.652 | AA102: 13.14 | AB102: =IFERROR(M102/AA102,0) -> 5.2511416 | AC102: =IFERROR(Q102/M102,0) -> 0
C103: =ROW(A100) -> 100 | D103: =E102 -> 45646 | E103: 45653 | F103: KR-1188/42405 | G103: =IF(AND(E103<>"",E103<TODAY()),"Disponible",IFERROR(INDEX(Vehiculos[Estado Vehiculo],MATCH(F103,Vehiculos[Placa Vehiculo],0)),"")) -> Disponible | H103: TANDAZO ROSILLO VICTOR HUGO | I103: BASE ORIENTOIL | J103: MDC | K103: =L102 -> 978 | L103: 1007 | M103: =L103-K103 -> 29 | Q103: =M103*P103 -> 0 | R103: BASE ORIENTOIL | S103: Diesel | T103: 1.8 | U103: =Rutas[[#This Row],[Precio x Galón ($/gal)]]*Rutas[[#This Row],[Volumen de Combustible (gal)]] -> 23.562 | Y103: =U103+SUM(V103:X103) -> 23.562 | AA103: 13.09 | AB103: =IFERROR(M103/AA103,0) -> 2.2154316 | AC103: =IFERROR(Q103/M103,0) -> 0
C104: =ROW(A101) -> 101 | D104: =E103 -> 45653 | E104: 45656 | F104: KR-1188/42405 | G104: =IF(AND(E104<>"",E104<TODAY()),"Disponible",IFERROR(INDEX(Vehiculos[Estado Vehiculo],MATCH(F104,Vehiculos[Placa Vehiculo],0)),"")) -> Disponible | H104: BRIONES SOLORZANO LEONARDO FABIO | I104: BASE ORIENTOIL | J104: MDC | K104: =L103 -> 1007 | L104: 1063 | M104: =L104-K104 -> 56 | Q104: =M104*P104 -> 0 | R104: BASE ORIENTOIL | S104: Diesel | T104: 1.8 | U104: =Rutas[[#This Row],[Precio x Galón ($/gal)]]*Rutas[[#This Row],[Volumen de Combustible (gal)]] -> 15.372 | Y104: =U104+SUM(V104:X104) -> 15.372 | AA104: 8.54 | AB104: =IFERROR(M104/AA104,0) -> 6.557377 | AC104: =IFERROR(Q104/M104,0) -> 0
C105: =ROW(A102) -> 102 | D105: 45628 | E105: 45634 | F105: KR-1088/42406 | G105: =IF(AND(E105<>"",E105<TODAY()),"Disponible",IFERROR(INDEX(Vehiculos[Estado Vehiculo],MATCH(F105,Vehiculos[Placa Vehiculo],0)),"")) -> Disponible | H105: VARGAS CARAVAJAL ROMEL LEONEL | I105: BASE ORIENTOIL | J105: MDC | K105: 3007 | L105: 3051 | M105: =L105-K105 -> 44 | Q105: =M105*P105 -> 0 | R105: BASE ORIENTOIL | S105: Diesel | T105: 1.8 | U105: =Rutas[[#This Row],[Precio x Galón ($/gal)]]*Rutas[[#This Row],[Volumen de Combustible (gal)]] -> 19.8 | Y105: =U105+SUM(V105:X105) -> 19.8 | AA105: 11 | AB105: =IFERROR(M105/AA105,0) -> 4 | AC105: =IFERROR(Q105/M105,0) -> 0
C106: =ROW(A103) -> 103 | D106: =E105 -> 45634 | E106: 45638 | F106: KR-1088/42406 | G106: =IF(AND(E106<>"",E106<TODAY()),"Disponible",IFERROR(INDEX(Vehiculos[Estado Vehiculo],MATCH(F106,Vehiculos[Placa Vehiculo],0)),"")) -> Disponible | H106: ARGUELLO PAUCAR JOHN FRANKLIN | I106: BASE ORIENTOIL | J106: MDC | K106: 3051 | L106: 3077 | M106: =L106-K106 -> 26 | Q106: =M106*P106 -> 0 | R106: BASE ORIENTOIL | S106: Diesel | T106: 1.8 | U106: =Rutas[[#This Row],[Precio x Galón ($/gal)]]*Rutas[[#This Row],[Volumen de Combustible (gal)]] -> 30.636 | Y106: =U106+SUM(V106:X106) -> 30.636 | AA106: 17.02 | AB106: =IFERROR(M106/AA106,0) -> 1.5276146 | AC106: =IFERROR(Q106/M106,0) -> 0
C107: =ROW(A104) -> 104 | D107: =E106 -> 45638 | E107: 45656 | F107: KR-1088/42406 | G107: =IF(AND(E107<>"",E107<TODAY()),"Disponible",IFERROR(INDEX(Vehiculos[Estado Vehiculo],MATCH(F107,Vehiculos[Placa Vehiculo],0)),"")) -> Disponible | H107: ESTACIO DAVILA EDWIN ALEXIS | I107: BASE ORIENTOIL | J107: MDC | K107: 3077 | L107: 3142 | M107: =L107-K107 -> 65 | Q107: =M107*P107 -> 0 | R107: BASE ORIENTOIL | S107: Diesel | T107: 1.8 | U107: =Rutas[[#This Row],[Precio x Galón ($/gal)]]*Rutas[[#This Row],[Volumen de Combustible (gal)]] -> 27.396 | Y107: =U107+SUM(V107:X107) -> 27.396 | AA107: 15.22 | AB107: =IFERROR(M107/AA107,0) -> 4.2706965 | AC107: =IFERROR(Q107/M107,0) -> 0
C108: =ROW(A105) -> 105 | D108: 45647 | E108: 45649 | F108: KR-1185/42408 | G108: =IF(AND(E108<>"",E108<TODAY()),"Disponible",IFERROR(INDEX(Vehiculos[Estado Vehiculo],MATCH(F108,Vehiculos[Placa Vehiculo],0)),"")) -> Disponible | H108: ESTACIO DAVILA EDWIN ALEXIS | I108: BASE ORIENTOIL | J108: MDC | K108: 2398 | L108: 2419 | M108: =L108-K108 -> 21 | Q108: =M108*P108 -> 0 | R108: BASE ORIENTOIL | S108: Diesel | T108: 1.8 | U108: =Rutas[[#This Row],[Precio x Galón ($/gal)]]*Rutas[[#This Row],[Volumen de Combustible (gal)]] -> 34.38 | Y108: =U108+SUM(V108:X108) -> 34.38 | AA108: 19.1 | AB108: =IFERROR(M108/AA108,0) -> 1.0994764 | AC108: =IFERROR(Q108/M108,0) -> 0
C109: =ROW(A106) -> 106 | D109: =E108 -> 45649 | E109: 45653 | F109: KR-1185/42408 | G109: =IF(AND(E109<>"",E109<TODAY()),"Disponible",IFERROR(INDEX(Vehiculos[Estado Vehiculo],MATCH(F109,Vehiculos[Placa Vehiculo],0)),"")) -> Disponible | H109: CASTILLO VILLALVA EDGAR PATRICIO | I109: BASE ORIENTOIL | J109: MDC | K109: =L108 -> 2419 | L109: 2452 | M109: =L109-K109 -> 33 | Q109: =M109*P109 -> 0 | R109: BASE ORIENTOIL | S109: Diesel | T109: 1.8 | U109: =Rutas[[#This Row],[Precio x Galón ($/gal)]]*Rutas[[#This Row],[Volumen de Combustible (gal)]] -> 19.26 | Y109: =U109+SUM(V109:X109) -> 19.26 | AA109: 10.7 | AB109: =IFERROR(M109/AA109,0) -> 3.0841121 | AC109: =IFERROR(Q109/M109,0) -> 0
C110: =ROW(A107) -> 107 | D110: =E109 -> 45653 | E110: 45655 | F110: KR-1185/42408 | G110: =IF(AND(E110<>"",E110<TODAY()),"Disponible",IFERROR(INDEX(Vehiculos[Estado Vehiculo],MATCH(F110,Vehiculos[Placa Vehiculo],0)),"")) -> Disponible | H110: VARGAS CARAVAJAL ROMEL LEONEL | I110: BASE ORIENTOIL | J110: MDC | K110: 2452 | L110: 2474 | M110: =L110-K110 -> 22 | Q110: =M110*P110 -> 0 | R110: BASE ORIENTOIL | S110: Diesel | T110: 1.8 | U110: =Rutas[[#This Row],[Precio x Galón ($/gal)]]*Rutas[[#This Row],[Volumen de Combustible (gal)]] -> 18.774 | Y110: =U110+SUM(V110:X110) -> 18.774 | AA110: 10.43 | AB110: =IFERROR(M110/AA110,0) -> 2.1093001 | AC110: =IFERROR(Q110/M110,0) -> 0
C111: =ROW(A108) -> 108 | D111: =E110 -> 45655 | E111: 45656 | F111: KR-1185/42408 | G111: =IF(AND(E111<>"",E111<TODAY()),"Disponible",IFERROR(INDEX(Vehiculos[Estado Vehiculo],MATCH(F111,Vehiculos[Placa Vehiculo],0)),"")) -> Disponible | H111: VARGAS CARAVAJAL ROMEL LEONEL | I111: BASE ORIENTOIL | J111: MDC | K111: 2474 | L111: 2505 | M111: =L111-K111 -> 31 | Q111: =M111*P111 -> 0 | R111: BASE ORIENTOIL | S111: Diesel | T111: 1.8 | U111: =Rutas[[#This Row],[Precio x Galón ($/gal)]]*Rutas[[#This Row],[Volumen de Combustible (gal)]] -> 19.008 | Y111: =U111+SUM(V111:X111) -> 19.008 | AA111: 10.56 | AB111: =IFERROR(M111/AA111,0) -> 2.9356061 | AC111: =IFERROR(Q111/M111,0) -> 0
C112: =ROW(A109) -> 109 | G112: =IF(AND(E112<>"",E112<TODAY()),"Disponible",IFERROR(INDEX(Vehiculos[Estado Vehiculo],MATCH(F112,Vehiculos[Placa Vehiculo],0)),"")) | M112: =L112-K112 -> 0 | Q112: =M112*P112 -> 0 | Y112: =U112+SUM(V112:X112) -> 0 | AB112: =IFERROR(M112/AA112,0) -> 0 | AC112: =IFERROR(Q112/M112,0) -> 0
C113: =ROW(A110) -> 110 | G113: =IF(AND(E113<>"",E113<TODAY()),"Disponible",IFERROR(INDEX(Vehiculos[Estado Vehiculo],MATCH(F113,Vehiculos[Placa Vehiculo],0)),"")) | M113: =L113-K113 -> 0 | Q113: =M113*P113 -> 0 | U113: =Rutas[[#This Row],[Precio x Galón ($/gal)]]*Rutas[[#This Row],[Volumen de Combustible (gal)]] -> 0 | Y113: =U113+SUM(V113:X113) -> 0 | AB113: =IFERROR(M113/AA113,0) -> 0 | AC113: =IFERROR(Q113/M113,0) -> 0
C114: =ROW(A111) -> 111 | D114: 45661 | E114: 45664 | F114: QAA-2912 | G114: =IF(AND(E114<>"",E114<TODAY()),"Disponible",IFERROR(INDEX(Vehiculos[Estado Vehiculo],MATCH(F114,Vehiculos[Placa Vehiculo],0)),"")) -> Disponible | H114: MOSCUY RAMIREZ MILVIO PAUL | I114: BASE ORIENTOIL | J114: INCHI | K114: 71946 | L114: 72535 | M114: =L114-K114 -> 589 | Q114: =M114*P114 -> 0 | R114: BASE ORIENTOIL | S114: Diesel | T114: 1.8 | U114: =Rutas[[#This Row],[Precio x Galón ($/gal)]]*Rutas[[#This Row],[Volumen de Combustible (gal)]] -> 179.694 | Y114: =U114+SUM(V114:X114) -> 179.694 | AA114: 99.83 | AB114: =IFERROR(M114/AA114,0) -> 5.9000301 | AC114: =IFERROR(Q114/M114,0) -> 0
C115: =ROW(A112) -> 112 | D115: =E114 -> 45664 | E115: 45669 | F115: QAA-2912 | G115: =IF(AND(E115<>"",E115<TODAY()),"Disponible",IFERROR(INDEX(Vehiculos[Estado Vehiculo],MATCH(F115,Vehiculos[Placa Vehiculo],0)),"")) -> Disponible | H115: MOSCUY RAMIREZ MILVIO PAUL | I115: BASE ORIENTOIL | J115: INCHI | K115: =L114 -> 72535 | L115: 73239 | M115: =L115-K115 -> 704 | Q115: =M115*P115 -> 0 | R115: BASE ORIENTOIL | S115: Diesel | T115: 1.8 | U115: =Rutas[[#This Row],[Precio x Galón ($/gal)]]*Rutas[[#This Row],[Volumen de Combustible (gal)]] -> 148.968 | Y115: =U115+SUM(V115:X115) -> 148.968 | AA115: 82.76 | AB115: =IFERROR(M115/AA115,0) -> 8.5065249 | AC115: =IFERROR(Q115/M115,0) -> 0
C116: =ROW(A113) -> 113 | D116: =E115 -> 45669 | E116: 45673 | F116: QAA-2912 | G116: =IF(AND(E116<>"",E116<TODAY()),"Disponible",IFERROR(INDEX(Vehiculos[Estado Vehiculo],MATCH(F116,Vehiculos[Placa Vehiculo],0)),"")) -> Disponible | H116: MOSCUY RAMIREZ MILVIO PAUL | I116: BASE ORIENTOIL | J116: INCHI | K116: =L115 -> 73239 | L116: 73801 | M116: =L116-K116 -> 562 | Q116: =M116*P116 -> 0 | R116: BASE ORIENTOIL | S116: Diesel | T116: 1.8 | U116: =Rutas[[#This Row],[Precio x Galón ($/gal)]]*Rutas[[#This Row],[Volumen de Combustible (gal)]] -> 178.254 | Y116: =U116+SUM(V116:X116) -> 178.254 | AA116: 99.03 | AB116: =IFERROR(M116/AA116,0) -> 5.675048 | AC116: =IFERROR(Q116/M116,0) -> 0
C117: =ROW(A114) -> 114 | D117: =E116 -> 45673 | E117: 45679 | F117: QAA-2912 | G117: =IF(AND(E117<>"",E117<TODAY()),"Disponible",IFERROR(INDEX(Vehiculos[Estado Vehiculo],MATCH(F117,Vehiculos[Placa Vehiculo],0)),"")) -> Disponible | H117: MOSCUY RAMIREZ MILVIO PAUL | I117: BASE ORIENTOIL | J117: INCHI | K117: =L116 -> 73801 | L117: 74643 | M117: =L117-K117 -> 842 | Q117: =M117*P117 -> 0 | R117: BASE ORIENTOIL | S117: Diesel | T117: 1.8 | U117: =Rutas[[#This Row],[Precio x Galón ($/gal)]]*Rutas[[#This Row],[Volumen de Combustible (gal)]] -> 146.736 | Y117: =U117+SUM(V117:X117) -> 146.736 | AA117: 81.52 | AB117: =IFERROR(M117/AA117,0) -> 10.328754 | AC117: =IFERROR(Q117/M117,0) -> 0
C118: =ROW(A115) -> 115 | D118: =E117 -> 45679 | E118: 45686 | F118: QAA-2912 | G118: =IF(AND(E118<>"",E118<TODAY()),"Disponible",IFERROR(INDEX(Vehiculos[Estado Vehiculo],MATCH(F118,Vehiculos[Placa Vehiculo],0)),"")) -> Disponible | H118: BRIONES SOLORZANO LEONARDO FABIO | I118: BASE ORIENTOIL | J118: INCHI | K118: =L117 -> 74643 | L118: 75415 | M118: =L118-K118 -> 772 | Q118: =M118*P118 -> 0 | R118: BASE ORIENTOIL | S118: Diesel | T118: 1.8 | U118: =Rutas[[#This Row],[Precio x Galón ($/gal)]]*Rutas[[#This Row],[Volumen de Combustible (gal)]] -> 201.744 | Y118: =U118+SUM(V118:X118) -> 201.744 | AA118: 112.08 | AB118: =IFERROR(M118/AA118,0) -> 6.8879372 | AC118: =IFERROR(Q118/M118,0) -> 0
C119: =ROW(A116) -> 116 | D119: =E118 -> 45686 | E119: 45687 | F119: QAA-2912 | G119: =IF(AND(E119<>"",E119<TODAY()),"Disponible",IFERROR(INDEX(Vehiculos[Estado Vehiculo],MATCH(F119,Vehiculos[Placa Vehiculo],0)),"")) -> Disponible | H119: BRIONES SOLORZANO LEONARDO FABIO | I119: BASE ORIENTOIL | J119: INCHI | K119: =L118 -> 75415 | L119: 75573 | M119: =L119-K119 -> 158 | N119: 311 | Q119: =M119*P119 -> 0 | R119: BASE ORIENTOIL | S119: Diesel | T119: 1.8 | U119: =Rutas[[#This Row],[Precio x Galón ($/gal)]]*Rutas[[#This Row],[Volumen de Combustible (gal)]] -> 206.28 | Y119: =U119+SUM(V119:X119) -> 206.28 | AA119: 114.6 | AB119: =IFERROR(M119/AA119,0) -> 1.3787086 | AC119: =IFERROR(Q119/M119,0) -> 0
C120: =ROW(A117) -> 117 | D120: 45659 | E120: 45666 | F120: QAA-2916 | G120: =IF(AND(E120<>"",E120<TODAY()),"Disponible",IFERROR(INDEX(Vehiculos[Estado Vehiculo],MATCH(F120,Vehiculos[Placa Vehiculo],0)),"")) -> Disponible | H120: PONCE RUIZ SIXTO LUBERNDI | I120: BASE ORIENTOIL | J120: MDC | K120: 57264 | L120: 57355 | M120: =L120-K120 -> 91 | Q120: =M120*P120 -> 0 | R120: BASE ORIENTOIL | S120: Diesel | T120: 1.8 | U120: =Rutas[[#This Row],[Precio x Galón ($/gal)]]*Rutas[[#This Row],[Volumen de Combustible (gal)]] -> 204.354 | Y120: =U120+SUM(V120:X120) -> 204.354 | AA120: 113.53 | AB120: =IFERROR(M120/AA120,0) -> 0.80155025 | AC120: =IFERROR(Q120/M120,0) -> 0
C121: =ROW(A118) -> 118 | D121: =E120 -> 45666 | E121: 45682 | F121: QAA-2916 | G121: =IF(AND(E121<>"",E121<TODAY()),"Disponible",IFERROR(INDEX(Vehiculos[Estado Vehiculo],MATCH(F121,Vehiculos[Placa Vehiculo],0)),"")) -> Disponible | H121: PONCE RUIZ SIXTO LUBERNDI | I121: BASE ORIENTOIL | J121: MDC | K121: 57938 | L121: 58034 | M121: =L121-K121 -> 96 | Q121: =M121*P121 -> 0 | R121: BASE ORIENTOIL | S121: Diesel | T121: 1.8 | U121: =Rutas[[#This Row],[Precio x Galón ($/gal)]]*Rutas[[#This Row],[Volumen de Combustible (gal)]] -> 185.256 | Y121: =U121+SUM(V121:X121) -> 185.256 | AA121: 102.92 | AB121: =IFERROR(M121/AA121,0) -> 0.93276331 | AC121: =IFERROR(Q121/M121,0) -> 0
C122: =ROW(A119) -> 119 | D122: =E121 -> 45682 | E122: 45687 | F122: QAA-2916 | G122: =IF(AND(E122<>"",E122<TODAY()),"Disponible",IFERROR(INDEX(Vehiculos[Estado Vehiculo],MATCH(F122,Vehiculos[Placa Vehiculo],0)),"")) -> Disponible | H122: PONCE RUIZ SIXTO LUBERNDI | I122: BASE ORIENTOIL | J122: MDC | K122: 59544 | L122: 59655 | M122: =L122-K122 -> 111 | N122: 280 | Q122: =M122*P122 -> 0 | R122: BASE ORIENTOIL | S122: Diesel | T122: 1.8 | U122: =Rutas[[#This Row],[Precio x Galón ($/gal)]]*Rutas[[#This Row],[Volumen de Combustible (gal)]] -> 219.33 | Y122: =U122+SUM(V122:X122) -> 219.33 | AA122: 121.85 | AB122: =IFERROR(M122/AA122,0) -> 0.91095609 | AC122: =IFERROR(Q122/M122,0) -> 0
C123: =ROW(A120) -> 120 | D123: 45659 | E123: 45663 | F123: QAA-2915 | G123: =IF(AND(E123<>"",E123<TODAY()),"Disponible",IFERROR(INDEX(Vehiculos[Estado Vehiculo],MATCH(F123,Vehiculos[Placa Vehiculo],0)),"")) -> Disponible | H123: LUNA HERNANDEZ LUIS ALBERTO | I123: BASE ORIENTOIL | J123: MDC | K123: 69090 | L123: 69282 | M123: =L123-K123 -> 192 | Q123: =M123*P123 -> 0 | R123: BASE ORIENTOIL | S123: Diesel | T123: 1.8 | U123: =Rutas[[#This Row],[Precio x Galón ($/gal)]]*Rutas[[#This Row],[Volumen de Combustible (gal)]] -> 181.098 | Y123: =U123+SUM(V123:X123) -> 181.098 | AA123: 100.61 | AB123: =IFERROR(M123/AA123,0) -> 1.908359 | AC123: =IFERROR(Q123/M123,0) -> 0
C124: =ROW(A121) -> 121 | D124: =E123 -> 45663 | E124: 45666 | F124: QAA-2915 | G124: =IF(AND(E124<>"",E124<TODAY()),"Disponible",IFERROR(INDEX(Vehiculos[Estado Vehiculo],MATCH(F124,Vehiculos[Placa Vehiculo],0)),"")) -> Disponible | H124: LUNA HERNANDEZ LUIS ALBERTO | I124: BASE ORIENTOIL | J124: MDC | K124: 69857 | L124: 69969 | M124: =L124-K124 -> 112 | Q124: =M124*P124 -> 0 | R124: BASE ORIENTOIL | S124: Diesel | T124: 1.8 | U124: =Rutas[[#This Row],[Precio x Galón ($/gal)]]*Rutas[[#This Row],[Volumen de Combustible (gal)]] -> 239.688 | Y124: =U124+SUM(V124:X124) -> 239.688 | AA124: 133.16 | AB124: =IFERROR(M124/AA124,0) -> 0.84109342 | AC124: =IFERROR(Q124/M124,0) -> 0
C125: =ROW(A122) -> 122 | D125: =E124 -> 45666 | E125: 45670 | F125: QAA-2915 | G125: =IF(AND(E125<>"",E125<TODAY()),"Disponible",IFERROR(INDEX(Vehiculos[Estado Vehiculo],MATCH(F125,Vehiculos[Placa Vehiculo],0)),"")) -> Disponible | H125: LUNA HERNANDEZ LUIS ALBERTO | I125: BASE ORIENTOIL | J125: MDC | K125: 70389 | L125: 70485 | M125: =L125-K125 -> 96 | Q125: =M125*P125 -> 0 | R125: BASE ORIENTOIL | S125: Diesel | T125: 1.8 | U125: =Rutas[[#This Row],[Precio x Galón ($/gal)]]*Rutas[[#This Row],[Volumen de Combustible (gal)]] -> 190.242 | Y125: =U125+SUM(V125:X125) -> 190.242 | AA125: 105.69 | AB125: =IFERROR(M125/AA125,0) -> 0.90831678 | AC125: =IFERROR(Q125/M125,0) -> 0
C126: =ROW(A123) -> 123 | D126: =E125 -> 45670 | E126: 45675 | F126: QAA-2915 | G126: =IF(AND(E126<>"",E126<TODAY()),"Disponible",IFERROR(INDEX(Vehiculos[Estado Vehiculo],MATCH(F126,Vehiculos[Placa Vehiculo],0)),"")) -> Disponible | H126: CAMACHO NARANJO CARLOS ANDRES | I126: BASE ORIENTOIL | J126: MDC | K126: 71359 | L126: 71467 | M126: =L126-K126 -> 108 | Q126: =M126*P126 -> 0 | R126: BASE ORIENTOIL | S126: Diesel | T126: 1.8 | U126: =Rutas[[#This Row],[Precio x Galón ($/gal)]]*Rutas[[#This Row],[Volumen de Combustible (gal)]] -> 239.382 | Y126: =U126+SUM(V126:X126) -> 239.382 | AA126: 132.99 | AB126: =IFERROR(M126/AA126,0) -> 0.81209113 | AC126: =IFERROR(Q126/M126,0) -> 0
C127: =ROW(A124) -> 124 | D127: =E126 -> 45675 | E127: 45678 | F127: QAA-2915 | G127: =IF(AND(E127<>"",E127<TODAY()),"Disponible",IFERROR(INDEX(Vehiculos[Estado Vehiculo],MATCH(F127,Vehiculos[Placa Vehiculo],0)),"")) -> Disponible | H127: CAMACHO NARANJO CARLOS ANDRES | I127: BASE ORIENTOIL | J127: MDC | K127: 72100 | L127: 72316 | M127: =L127-K127 -> 216 | Q127: =M127*P127 -> 0 | R127: BASE ORIENTOIL | S127: Diesel | T127: 1.8 | U127: =Rutas[[#This Row],[Precio x Galón ($/gal)]]*Rutas[[#This Row],[Volumen de Combustible (gal)]] -> 239.256 | Y127: =U127+SUM(V127:X127) -> 239.256 | AA127: 132.92 | AB127: =IFERROR(M127/AA127,0) -> 1.6250376 | AC127: =IFERROR(Q127/M127,0) -> 0
C128: =ROW(A125) -> 125 | D128: =E127 -> 45678 | E128: 45682 | F128: QAA-2915 | G128: =IF(AND(E128<>"",E128<TODAY()),"Disponible",IFERROR(INDEX(Vehiculos[Estado Vehiculo],MATCH(F128,Vehiculos[Placa Vehiculo],0)),"")) -> Disponible | H128: CAMACHO NARANJO CARLOS ANDRES | I128: BASE ORIENTOIL | J128: MDC | K128: 72752 | L128: 72852 | M128: =L128-K128 -> 100 | Q128: =M128*P128 -> 0 | R128: BASE ORIENTOIL | S128: Diesel | T128: 1.8 | U128: =Rutas[[#This Row],[Precio x Galón ($/gal)]]*Rutas[[#This Row],[Volumen de Combustible (gal)]] -> 184.284 | Y128: =U128+SUM(V128:X128) -> 184.284 | AA128: 102.38 | AB128: =IFERROR(M128/AA128,0) -> 0.97675327 | AC128: =IFERROR(Q128/M128,0) -> 0
C129: =ROW(A126) -> 126 | D129: =E128 -> 45682 | E129: 45685 | F129: QAA-2915 | G129: =IF(AND(E129<>"",E129<TODAY()),"Disponible",IFERROR(INDEX(Vehiculos[Estado Vehiculo],MATCH(F129,Vehiculos[Placa Vehiculo],0)),"")) -> Disponible | H129: CAMACHO NARANJO CARLOS ANDRES | I129: BASE ORIENTOIL | J129: MDC | K129: 73608 | L129: 73710 | M129: =L129-K129 -> 102 | Q129: =M129*P129 -> 0 | R129: BASE ORIENTOIL | S129: Diesel | T129: 1.8 | U129: =Rutas[[#This Row],[Precio x Galón ($/gal)]]*Rutas[[#This Row],[Volumen de Combustible (gal)]] -> 209.988 | Y129: =U129+SUM(V129:X129) -> 209.988 | AA129: 116.66 | AB129: =IFERROR(M129/AA129,0) -> 0.87433568 | AC129: =IFERROR(Q129/M129,0) -> 0
C130: =ROW(A127) -> 127 | D130: =E129 -> 45685 | E130: 45687 | F130: QAA-2915 | G130: =IF(AND(E130<>"",E130<TODAY()),"Disponible",IFERROR(INDEX(Vehiculos[Estado Vehiculo],MATCH(F130,Vehiculos[Placa Vehiculo],0)),"")) -> Disponible | H130: CAMACHO NARANJO CARLOS ANDRES | I130: BASE ORIENTOIL | J130: MDC | K130: 74355 | L130: 74448 | M130: =L130-K130 -> 93 | N130: 611 | Q130: =M130*P130 -> 0 | R130: BASE ORIENTOIL | S130: Diesel | T130: 1.8 | U130: =Rutas[[#This Row],[Precio x Galón ($/gal)]]*Rutas[[#This Row],[Volumen de Combustible (gal)]] -> 228.132 | Y130: =U130+SUM(V130:X130) -> 228.132 | AA130: 126.74 | AB130: =IFERROR(M130/AA130,0) -> 0.7337857 | AC130: =IFERROR(Q130/M130,0) -> 0
C131: =ROW(A128) -> 128 | D131: 45659 | E131: 45663 | F131: QAA-3165 | G131: =IF(AND(E131<>"",E131<TODAY()),"Disponible",IFERROR(INDEX(Vehiculos[Estado Vehiculo],MATCH(F131,Vehiculos[Placa Vehiculo],0)),"")) -> Disponible | H131: CASTILLO VILLALVA EDGAR PATRICIO | I131: BASE ORIENTOIL | J131: MDC | K131: 20438 | L131: 20639 | M131: =L131-K131 -> 201 | Q131: =M131*P131 -> 0 | R131: BASE ORIENTOIL | S131: Diesel | T131: 1.8 | U131: =Rutas[[#This Row],[Precio x Galón ($/gal)]]*Rutas[[#This Row],[Volumen de Combustible (gal)]] -> 112.158 | Y131: =U131+SUM(V131:X131) -> 112.158 | AA131: 62.31 | AB131: =IFERROR(M131/AA131,0) -> 3.2258065 | AC131: =IFERROR(Q131/M131,0) -> 0
...

Sheet Enapitos
B1: CONTROL DE ENAPITOS
C3: Nro | D3: Fecha | E3: Nro Viaje | F3: Placa Vehículo | G3: Conductor | H3: Infracción | I3: Importe multa ($) | J3: Importe pagado ($) | K3: Debe ($) | L3: Estado Pago | M3: Observaciones
C4: =ROW(A1) -> 1 | F4: =IFERROR(VLOOKUP($E4,Rutas[],4,FALSE),"") | G4: =IFERROR(VLOOKUP($E4,Rutas[],6,FALSE),"") | K4: =I4-J4 -> 0 | L4: =IF(I4=0,"",IF(K4=0,"Abierto","Cerrado"))
C5: =ROW(A2) -> 2 | F5: =IFERROR(VLOOKUP($E5,Rutas[],4,FALSE),"") | G5: =IFERROR(VLOOKUP($E5,Rutas[],6,FALSE),"") | K5: =I5-J5 -> 0 | L5: =IF(I5=0,"",IF(K5=0,"Abierto","Cerrado"))
C6: =ROW(A3) -> 3 | F6: =IFERROR(VLOOKUP($E6,Rutas[],4,FALSE),"") | G6: =IFERROR(VLOOKUP($E6,Rutas[],6,FALSE),"") | K6: =I6-J6 -> 0 | L6: =IF(I6=0,"",IF(K6=0,"Abierto","Cerrado"))
C7: =ROW(A4) -> 4 | F7: =IFERROR(VLOOKUP($E7,Rutas[],4,FALSE),"") | G7: =IFERROR(VLOOKUP($E7,Rutas[],6,FALSE),"") | K7: =I7-J7 -> 0 | L7: =IF(I7=0,"",IF(K7=0,"Abierto","Cerrado"))
C8: =ROW(A5) -> 5 | F8: =IFERROR(VLOOKUP($E8,Rutas[],4,FALSE),"") | G8: =IFERROR(VLOOKUP($E8,Rutas[],6,FALSE),"") | K8: =I8-J8 -> 0 | L8: =IF(I8=0,"",IF(K8=0,"Abierto","Cerrado"))
C9: =ROW(A6) -> 6 | F9: =IFERROR(VLOOKUP($E9,Rutas[],4,FALSE),"") | G9: =IFERROR(VLOOKUP($E9,Rutas[],6,FALSE),"") | K9: =I9-J9 -> 0 | L9: =IF(I9=0,"",IF(K9=0,"Abierto","Cerrado"))
C10: =ROW(A7) -> 7 | F10: =IFERROR(VLOOKUP($E10,Rutas[],4,FALSE),"") | G10: =IFERROR(VLOOKUP($E10,Rutas[],6,FALSE),"") | K10: =I10-J10 -> 0 | L10: =IF(I10=0,"",IF(K10=0,"Abierto","Cerrado"))
C11: =ROW(A8) -> 8 | F11: =IFERROR(VLOOKUP($E11,Rutas[],4,FALSE),"") | G11: =IFERROR(VLOOKUP($E11,Rutas[],6,FALSE),"") | K11: =I11-J11 -> 0 | L11: =IF(I11=0,"",IF(K11=0,"Abierto","Cerrado"))
C12: =ROW(A9) -> 9 | F12: =IFERROR(VLOOKUP($E12,Rutas[],4,FALSE),"") | G12: =IFERROR(VLOOKUP($E12,Rutas[],6,FALSE),"") | K12: =I12-J12 -> 0 | L12: =IF(I12=0,"",IF(K12=0,"Abierto","Cerrado"))
C13: =ROW(A10) -> 10 | F13: =IFERROR(VLOOKUP($E13,Rutas[],4,FALSE),"") | G13: =IFERROR(VLOOKUP($E13,Rutas[],6,FALSE),"") | K13: =I13-J13 -> 0 | L13: =IF(I13=0,"",IF(K13=0,"Abierto","Cerrado"))
C14: =ROW(A11) -> 11 | F14: =IFERROR(VLOOKUP($E14,Rutas[],4,FALSE),"") | G14: =IFERROR(VLOOKUP($E14,Rutas[],6,FALSE),"") | K14: =I14-J14 -> 0 | L14: =IF(I14=0,"",IF(K14=0,"Abierto","Cerrado"))
C15: =ROW(A12) -> 12 | F15: =IFERROR(VLOOKUP($E15,Rutas[],4,FALSE),"") | G15: =IFERROR(VLOOKUP($E15,Rutas[],6,FALSE),"") | K15: =I15-J15 -> 0 | L15: =IF(I15=0,"",IF(K15=0,"Abierto","Cerrado"))
... C23: =ROW(A20) -> 20 | F23: =IFERROR(VLOOKUP($E23,Rutas[],4,FALSE),"") | G23: =IFERROR(VLOOKUP($E23,Rutas[],6,FALSE),"") | K23: =I23-J23 -> 0 | L23: =IF(I23=0,"",IF(K23=0,"Abierto","Cerrado"))

Sheet Mantenimiento
C1: MANTENIMIENTO DE CABEZALES Y VACUUM
C3: Nro | D3: Placa Vehiculo | E3: Taller | F3: Fecha Entrada | G3: Fecha Salida | H3: Tipo | I3: Kilometraje del Odómetro | J3: KM Entre MTO | K3: Tiempo MTO CRTVO | L3: Tiempo MTO PTVO | M3: Paquete de Mantenimiento | N3: N° de Orden | O3: Causas del Mantenimiento | P3: Costo Total ($) | Q3: Fecha de Pago | R3: Observaciones
C4: =ROW(A1) -> 1 | D4: QAA-3164 | E4: MECÁNICA ORIENTOIL | F4: 45592 | G4: 45592 | H4: Preventivo | I4: 6507 | M4: Preventivo 01 | O4: Mantenimiento Preventivo 8000 kms
C5: =ROW(A2) -> 2 | D5: QAA-3164 | E5: MECÁNICA ORIENTOIL | F5: 45669 | G5: 45669 | H5: Preventivo | I5: 14546 | J5: =Mantenimiento[[#This Row],[Kilometraje del Odómetro]]-I4 -> 8039 | L5: 2 | M5: Preventivo 01 | O5: Mantenimiento Preventivo 8000 kms
C6: =ROW(A3) -> 3 | D6: QAA-3164 | E6: MECÁNICA ORIENTOIL | F6: 45707 | G6: 45707 | H6: Preventivo | I6: 22382 | J6: =Mantenimiento[[#This Row],[Kilometraje del Odómetro]]-I5 -> 7836 | L6: 2 | M6: Preventivo 01 | O6: Mantenimiento Preventivo 8000 kms
C7: =ROW(A4) -> 4 | D7: QAA-3164 | E7: MECÁNICA ORIENTOIL | F7: 45821 | G7: 45821 | H7: Preventivo | I7: 30382 | J7: =Mantenimiento[[#This Row],[Kilometraje del Odómetro]]-I6 -> 8000 | L7: 2 | M7: Preventivo 01 | N7: 2025060020 | O7: Mantenimiento Preventivo 8000 kms
C8: =ROW(A5) -> 5 | D8: QAA-3164 | E8: MECÁNICA ORIENTOIL | F8: 45925 | G8: 45925 | H8: Preventivo | I8: 38310 | J8: =Mantenimiento[[#This Row],[Kilometraje del Odómetro]]-I7 -> 7928 | L8: 2 | M8: Preventivo 01 | N8: 2025090041 | O8: Mantenimiento Preventivo 8000 kms
C9: =ROW(A6) -> 6 | D9: QAA-3164 | E9: MECÁNICA ORIENTOIL | F9: 46008 | G9: 46008 | H9: Correctivo | I9: 43982 | K9: 2 | M9: Correctivo 02 | N9: 2025121328 | O9: Arreglo del motor de subida del vidrio y cambio de radio
C10: =ROW(A6) -> 6 | D10: QAA-3164 | E10: MECÁNICA ORIENTOIL | F10: 46008 | G10: 46008 | H10: Correctivo | I10: 43982 | K10: 3 | M10: Correctivo 01 | N10: 2025121328 | O10: Cambio de retrovisor, Ajuste de Quinta rueda y arreglo de Tubo de escape
C11: =ROW(A6) -> 6 | D11: QAA-3164 | E11: MECÁNICA ORIENTOIL | F11: 46009 | G11: 46009 | H11: Correctivo | I11: 43982 | K11: 2 | M11: Correctivo 01 | N11: 2025121329 | O11: Chequeo de fuga de aire
C12: =ROW(A6) -> 6
C13: =ROW(A6) -> 6
C14: =ROW(A7) -> 7
C15: =ROW(A8) -> 8 | J15: =Mantenimiento[[#This Row],[Kilometraje del Odómetro]]-I14 -> 0
C16: =ROW(A13) -> 13 | D16: QAA-3166 | E16: MECÁNICA ORIENTOIL | F16: 45573 | G16: 45573 | H16: Preventivo | I16: 9993 | J16: =Mantenimiento[[#This Row],[Kilometraje del Odómetro]]-I15 -> 9993 | M16: Preventivo 01 | O16: Mantenimiento Preventivo 8000 kms
C17: =ROW(A14) -> 14 | D17: QAA-3166 | E17: MECÁNICA ORIENTOIL | F17: 45621 | G17: 45621 | H17: Preventivo | I17: 18280 | J17: =Mantenimiento[[#This Row],[Kilometraje del Odómetro]]-I16 -> 8287 | M17: Preventivo 01 | O17: Mantenimiento Preventivo 8000 kms
C18: =ROW(A15) -> 15 | D18: QAA-3166 | E18: MECÁNICA ORIENTOIL | F18: 45651 | G18: 45651 | H18: Preventivo | I18: 27744 | J18: =Mantenimiento[[#This Row],[Kilometraje del Odómetro]]-I17 -> 9464 | M18: Preventivo 01 | O18: Mantenimiento Preventivo 8000 kms
C19: =ROW(A16) -> 16 | D19: QAA-3166 | E19: MECÁNICA ORIENTOIL | F19: 45679 | G19: 45679 | H19: Preventivo | I19: 36300 | J19: =Mantenimiento[[#This Row],[Kilometraje del Odómetro]]-I18 -> 8556 | M19: Preventivo 01 | O19: Mantenimiento Preventivo 8000 kms
C20: =ROW(A17) -> 17 | D20: QAA-3166 | E20: MECÁNICA ORIENTOIL | F20: 45758 | G20: 45758 | H20: Preventivo | I20: 44200 | J20: =Mantenimiento[[#This Row],[Kilometraje del Odómetro]]-I19 -> 7900 | L20: 2 | M20: Preventivo 02 | N20: 2025040015 | O20: Mantenimiento Preventivo 8000 kms
C21: =ROW(A18) -> 18 | D21: QAA-3166 | E21: MECÁNICA ORIENTOIL | F21: 45817 | G21: 45817 | H21: Preventivo | I21: 52969 | J21: =Mantenimiento[[#This Row],[Kilometraje del Odómetro]]-I20 -> 8769 | L21: 2 | M21: Preventivo 02 | N21: 2025060021 | O21: Mantenimiento Preventivo 8000 kms
C22: =ROW(A19) -> 19
C23: =ROW(A20) -> 20
C24: =ROW(A21) -> 21
C25: =ROW(A22) -> 22
C26: =ROW(A23) -> 23
C27: =ROW(A24) -> 24 | J27: =Mantenimiento[[#This Row],[Kilometraje del Odómetro]]-I26 -> 0
C28: =ROW(A25) -> 25 | D28: QAA-2912 | E28: MECÁNICA ORIENTOIL | F28: 45123 | G28: 45123 | H28: Preventivo | I28: 5708 | J28: =Mantenimiento[[#This Row],[Kilometraje del Odómetro]]-I27 -> 5708 | M28: Preventivo 01 | O28: Mantenimiento Preventivo 8000 kms
C29: =ROW(A26) -> 26 | D29: QAA-2912 | E29: MECÁNICA ORIENTOIL | F29: 45227 | G29: 45227 | H29: Preventivo | I29: 11715 | J29: =Mantenimiento[[#This Row],[Kilometraje del Odómetro]]-I28 -> 6007 | M29: Preventivo 01 | O29: Mantenimiento Preventivo 8000 kms
C30: =ROW(A27) -> 27 | D30: QAA-2912 | E30: MECÁNICA ORIENTOIL | F30: 45321 | G30: 45321 | H30: Preventivo | I30: 18827 | J30: =Mantenimiento[[#This Row],[Kilometraje del Odómetro]]-I29 -> 7112 | M30: Preventivo 01 | O30: Mantenimiento Preventivo 8000 kms
C31: =ROW(A28) -> 28 | D31: QAA-2912 | E31: MECÁNICA ORIENTOIL | F31: 45407 | G31: 45407 | H31: Preventivo | I31: 25265 | J31: =Mantenimiento[[#This Row],[Kilometraje del Odómetro]]-I30 -> 6438 | M31: Preventivo 01 | O31: Mantenimiento Preventivo 8000 kms
C32: =ROW(A29) -> 29 | D32: QAA-2912 | E32: MECÁNICA ORIENTOIL | F32: 45452 | G32: =Mantenimiento[[#This Row],[Fecha Entrada]] -> 45452 | H32: Preventivo | I32: 34449 | J32: =Mantenimiento[[#This Row],[Kilometraje del Odómetro]]-I31 -> 9184 | M32: Preventivo 02 | O32: Mantenimiento Preventivo 8000 kms
C33: =ROW(A30) -> 30 | D33: QAA-2912 | E33: MECÁNICA ORIENTOIL | F33: 45490 | G33: =Mantenimiento[[#This Row],[Fecha Entrada]] -> 45490 | H33: Preventivo | I33: 43951 | J33: =Mantenimiento[[#This Row],[Kilometraje del Odómetro]]-I32 -> 9502 | M33: Preventivo 02 | O33: Mantenimiento Preventivo 8000 kms
C34: =ROW(A31) -> 31 | D34: QAA-2912 | E34: MECÁNICA ORIENTOIL | F34: 45536 | G34: =Mantenimiento[[#This Row],[Fecha Entrada]] -> 45536 | H34: Preventivo | I34: 51987 | J34: =Mantenimiento[[#This Row],[Kilometraje del Odómetro]]-I33 -> 8036 | M34: Preventivo 02 | O34: Mantenimiento Preventivo 8000 kms
C35: =ROW(A32) -> 32 | D35: QAA-2912 | E35: MECÁNICA ORIENTOIL | F35: 45572 | G35: =Mantenimiento[[#This Row],[Fecha Entrada]] -> 45572 | H35: Preventivo | I35: 59918 | J35: =Mantenimiento[[#This Row],[Kilometraje del Odómetro]]-I34 -> 7931 | M35: Preventivo 02 | O35: Mantenimiento Preventivo 8000 kms
C36: =ROW(A33) -> 33 | D36: QAA-2912 | E36: MECÁNICA ORIENTOIL | F36: 45634 | G36: =Mantenimiento[[#This Row],[Fecha Entrada]] -> 45634 | H36: Preventivo | I36: 68206 | J36: =Mantenimiento[[#This Row],[Kilometraje del Odómetro]]-I35 -> 8288 | M36: Preventivo 03 | O36: Mantenimiento Preventivo 8000 kms
C37: =ROW(A34) -> 34 | D37: QAA-2912 | E37: MECÁNICA ORIENTOIL | F37: 45693 | G37: =Mantenimiento[[#This Row],[Fecha Entrada]] -> 45693 | H37: Preventivo | I37: 76604 | J37: =Mantenimiento[[#This Row],[Kilometraje del Odómetro]]-I36 -> 8398 | L37: 2 | M37: Preventivo 03 | O37: Mantenimiento Preventivo 8000 kms
C38: =ROW(A35) -> 35 | D38: QAA-2912 | E38: MECÁNICA ORIENTOIL | F38: 45749 | G38: 45749 | H38: Preventivo | I38: 84825 | J38: =Mantenimiento[[#This Row],[Kilometraje del Odómetro]]-I37 -> 8221 | L38: 2 | M38: Preventivo 03 | N38: 2025030025 | O38: Mantenimiento Preventivo 8000 kms
C39: =ROW(A36) -> 36 | D39: QAA-2912 | E39: MECÁNICA ORIENTOIL | F39: 45732 | G39: 45732 | H39: Prev Caja y Corona | I39: 82764 | M39: Caja y Corona 01 | O39: Mantenimiento Preventivo 60000 Kms
C40: =ROW(A37) -> 37 | D40: QAA-2912 | E40: MECÁNICA ORIENTOIL | F40: 45780 | G40: 45780 | H40: Preventivo | I40: 91515 | J40: =Mantenimiento[[#This Row],[Kilometraje del Odómetro]]-I38 -> 6690 | L40: 2 | M40: Preventivo 03 | N40: 2025050012 | O40: Mantenimiento Preventivo 8000 kms
C41: =ROW(A38) -> 38 | D41: QAA-2912 | E41: MECÁNICA ORIENTOIL | F41: 45811 | G41: 45811 | H41: Preventivo | I41: 99982 | J41: =Mantenimiento[[#This Row],[Kilometraje del Odómetro]]-I40 -> 8467 | L41: 2 | M41: Preventivo 04 | N41: 2025060012 | O41: Mantenimiento Preventivo 8000 kms
C42: =ROW(A39) -> 39 | D42: QAA-2912 | E42: MECÁNICA ORIENTOIL | F42: 45885 | G42: 45885 | H42: Preventivo | I42: 108492 | J42: =Mantenimiento[[#This Row],[Kilometraje del Odómetro]]-I41 -> 8510 | L42: 2 | M42: Preventivo 04 | N42: 2025080026 | O42: Mantenimiento Preventivo 8000 kms
C43: =ROW(A40) -> 40 | D43: QAA-2912 | E43: MECÁNICA ORIENTOIL | F43: 45928 | G43: 45928 | H43: Correctivo | I43: 115400 | K43: 1 | M43: Correctivo 02 | N43: 2025091211 | O43: Cambio de luces guias posteriores
C44: =ROW(A41) -> 41 | D44: QAA-2912 | E44: MECÁNICA ORIENTOIL | F44: 45933 | G44: 45933 | H44: Preventivo | I44: 116582 | J44: =Mantenimiento[[#This Row],[Kilometraje del Odómetro]]-I42 -> 8090 | L44: 2 | M44: Preventivo 01 | N44: 2025100006 | O44: Mantenimiento Preventivo 8000 kms
C45: =ROW(A42) -> 42 | D45: QAA-2912 | E45: MECÁNICA ORIENTOIL | F45: 45979 | G45: 45979 | H45: Preventivo | I45: 124870 | J45: =Mantenimiento[[#This Row],[Kilometraje del Odómetro]]-I44 -> 8288 | L45: 2 | M45: Preventivo 01 | N45: 2025110024 | O45: Mantenimiento Preventivo 8000 kms
C46: =ROW(A43) -> 43 | D46: QAA-2912 | E46: MECÁNICA ORIENTOIL | F46: 46000 | G46: 46000 | H46: Correctivo | I46: 127361 | K46: 3 | M46: Correctivo 02 | N46: 2025121325 | O46: Chequeo de alarmas encendidas en el tablero
C47: =ROW(A44) -> 44
C48: =ROW(A45) -> 45
C49: =ROW(A46) -> 46
C50: =ROW(A47) -> 47 | J50: =Mantenimiento[[#This Row],[Kilometraje del Odómetro]]-I49 -> 0
C51: =ROW(A48) -> 48 | D51: QAA-2915 | E51: MECÁNICA ORIENTOIL | F51: 45113 | G51: =Mantenimiento[[#This Row],[Fecha Entrada]] -> 45113 | H51: Preventivo | I51: 5974 | J51: =Mantenimiento[[#This Row],[Kilometraje del Odómetro]]-I50 -> 5974 | M51: Preventivo 01 | O51: Mantenimiento Preventivo 8000 kms
C52: =ROW(A49) -> 49 | D52: QAA-2915 | E52: MECÁNICA ORIENTOIL | F52: 45224 | G52: =Mantenimiento[[#This Row],[Fecha Entrada]] -> 45224 | H52: Preventivo | I52: 11798 | J52: =Mantenimiento[[#This Row],[Kilometraje del Odómetro]]-I51 -> 5824 | M52: Preventivo 01 | O52: Mantenimiento Preventivo 8000 kms
C53: =ROW(A50) -> 50 | D53: QAA-2915 | E53: MECÁNICA ORIENTOIL | F53: 45321 | G53: =Mantenimiento[[#This Row],[Fecha Entrada]] -> 45321 | H53: Preventivo | I53: 19271 | J53: =Mantenimiento[[#This Row],[Kilometraje del Odómetro]]-I52 -> 7473 | M53: Preventivo 01 | O53: Mantenimiento Preventivo 8000 kms
C54: =ROW(A51) -> 51 | D54: QAA-2915 | E54: MECÁNICA ORIENTOIL | F54: 45406 | G54: =Mantenimiento[[#This Row],[Fecha Entrada]] -> 45406 | H54: Preventivo | I54: 25353 | J54: =Mantenimiento[[#This Row],[Kilometraje del Odómetro]]-I53 -> 6082 | M54: Preventivo 01 | O54: Mantenimiento Preventivo 8000 kms
C55: =ROW(A52) -> 52 | D55: QAA-2915 | E55: MECÁNICA ORIENTOIL | F55: 45493 | G55: =Mantenimiento[[#This Row],[Fecha Entrada]] -> 45493 | H55: Preventivo | I55: 33506 | J55: =Mantenimiento[[#This Row],[Kilometraje del Odómetro]]-I54 -> 8153 | M55: Preventivo 02 | O55: Mantenimiento Preventivo 8000 kms
C56: =ROW(A53) -> 53 | D56: QAA-2915 | E56: MECÁNICA ORIENTOIL | F56: 45547 | G56: =Mantenimiento[[#This Row],[Fecha Entrada]] -> 45547 | H56: Preventivo | I56: 42830 | J56: =Mantenimiento[[#This Row],[Kilometraje del Odómetro]]-I55 -> 9324 | M56: Preventivo 02 | O56: Mantenimiento Preventivo 8000 kms
C57: =ROW(A54) -> 54 | D57: QAA-2915 | E57: MECÁNICA ORIENTOIL | F57: 45612 | G57: =Mantenimiento[[#This Row],[Fecha Entrada]] -> 45612 | H57: Preventivo | I57: 60051 | J57: =Mantenimiento[[#This Row],[Kilometraje del Odómetro]]-I56 -> 17221 | M57: Preventivo 02 | O57: Mantenimiento Preventivo 8000 kms
C58: =ROW(A55) -> 55 | D58: QAA-2915 | E58: MECÁNICA ORIENTOIL | F58: 45656 | G58: =Mantenimiento[[#This Row],[Fecha Entrada]] -> 45656 | H58: Preventivo | I58: 68467 | J58: =Mantenimiento[[#This Row],[Kilometraje del Odómetro]]-I57 -> 8416 | M58: Preventivo 02 | O58: Mantenimiento Preventivo 8000 kms
C59: =ROW(A56) -> 56 | D59: QAA-2915 | E59: MECÁNICA ORIENTOIL | F59: 45697 | G59: =Mantenimiento[[#This Row],[Fecha Entrada]] -> 45697 | H59: Preventivo | I59: 76712 | J59: =Mantenimiento[[#This Row],[Kilometraje del Odómetro]]-I58 -> 8245 | L59: 2 | M59: Preventivo 03 | O59: Mantenimiento Preventivo 8000 kms
C60: =ROW(A57) -> 57 | D60: QAA-2915 | E60: MECÁNICA ORIENTOIL | F60: 45749 | G60: 45749 | H60: Preventivo | I60: 85206 | J60: =Mantenimiento[[#This Row],[Kilometraje del Odómetro]]-I59 -> 8494 | L60: 2 | M60: Preventivo 03 | N60: 2025030026 | O60: Mantenimiento Preventivo 8000 kms
C61: =ROW(A58) -> 58 | D61: QAA-2915 | E61: MECÁNICA ORIENTOIL | F61: 45730 | G61: 45730 | H61: Prev Caja y Corona | I61: 82494 | M61: Caja y Corona 01 | O61: Mantenimiento Preventivo 60000 Kms
C62: =ROW(A59) -> 59 | D62: QAA-2915 | E62: MECÁNICA ORIENTOIL | F62: 45789 | G62: 45789 | H62: Preventivo | I62: 94887 | J62: =Mantenimiento[[#This Row],[Kilometraje del Odómetro]]-I60 -> 9681 | L62: 2 | M62: Preventivo 03 | N62: 2025050011 | O62: Mantenimiento Preventivo 8000 kms
C63: =ROW(A60) -> 60 | D63: QAA-2915 | E63: MECÁNICA ORIENTOIL | F63: 45814 | G63: 45814 | H63: Preventivo | I63: 102761 | J63: =Mantenimiento[[#This Row],[Kilometraje del Odómetro]]-I62 -> 7874 | L63: 2 | M63: Preventivo 03 | N63: 2025060014 | O63: Mantenimiento Preventivo 8000 kms
C64: =ROW(A61) -> 61 | D64: QAA-2915 | E64: MECÁNICA ORIENTOIL | F64: 45891 | G64: 45891 | H64: Preventivo | I64: 110916 | J64: =Mantenimiento[[#This Row],[Kilometraje del Odómetro]]-I63 -> 8155 | L64: 2 | M64: Preventivo 04 | N64: 2025080034 | O64: Mantenimiento Preventivo 8000 kms
C65: =ROW(A62) -> 62 | D65: QAA-2915 | E65: MECÁNICA ORIENTOIL | F65: 45920 | G65: 45920 | H65: Correctivo | I65: 115915 | K65: 0.5 | M65: Correctivo 02 | N65: 2025091187 | O65: Cambio de foco Neblinero
C66: =ROW(A63) -> 63 | D66: QAA-2915 | E66: MECÁNICA ORIENTOIL | F66: 45925 | G66: 45925 | H66: Correctivo | I66: 116432 | K66: 0.75 | M66: Correctivo 02 | N66: 2025091200 | O66: Cambio de luces guias posteriores
C67: =ROW(A64) -> 64 | D67: QAA-2915 | E67: MECÁNICA ORIENTOIL | F67: 45941 | G67: 45941 | H67: Preventivo | I67: 119430 | J67: =Mantenimiento[[#This Row],[Kilometraje del Odómetro]]-I64 -> 8514 | L67: 2 | M67: Preventivo 01 | N67: 2025101230 | O67: Mantenimiento Preventivo 8000 kms
C68: =ROW(A65) -> 65 | D68: QAA-2915 | E68: MECÁNICA ORIENTOIL | F68: 45948 | G68: 45948 | H68: Correctivo | I68: 120390 | K68: 0.75 | M68: Correctivo 02 | N68: 2025101256 | O68: Cambio de 2 baterias NS 150
C69: =ROW(A66) -> 66 | D69: QAA-2915 | E69: MECÁNICA ORIENTOIL | F69: 45954 | G69: 45954 | H69: Correctivo | I69: 121490 | K69: 2 | M69: Correctivo 03 | N69: 2025101250 | O69: Cambio de 8 Llantas nuevas para el cabezal
C70: =ROW(A67) -> 67 | D70: QAA-2915 | E70: MECÁNICA ORIENTOIL | F70: 45956 | G70: 45956 | H70: Correctivo | I70: 121512 | K70: 1 | M70: Correctivo 01 | N70: 2025101253 | O70: Cambio de manguera de pulmon de freno / y tanque de aire (sistema de frenado)
C71: =ROW(A68) -> 68 | D71: QAA-2915 | E71: MECÁNICA ORIENTOIL | F71: 45991 | G71: 45991 | H71: Preventivo | I71: 127486 | J71: =Mantenimiento[[#This Row],[Kilometraje del Odómetro]]-I67 -> 8056 | L71: 2 | M71: Preventivo 01 | N71: 2025110042 | O71: Mantenimiento Preventivo de los 8000 Kmss
C72: =ROW(A69) -> 69
C73: =ROW(A70) -> 70
C74: =ROW(A71) -> 71
C75: =ROW(A72) -> 72
C76: =ROW(A73) -> 73 | J76: =Mantenimiento[[#This Row],[Kilometraje del Odómetro]]-I75 -> 0
C77: =ROW(A74) -> 74 | D77: QAA-2916 | E77: MECÁNICA ORIENTOIL | F77: 45113 | G77: =Mantenimiento[[#This Row],[Fecha Entrada]] -> 45113 | H77: Preventivo | I77: 5663 | J77: =Mantenimiento[[#This Row],[Kilometraje del Odómetro]]-I76 -> 5663 | M77: Preventivo 01 | O77: Mantenimiento Preventivo 8000 kms
C78: =ROW(A75) -> 75 | D78: QAA-2916 | E78: MECÁNICA ORIENTOIL | F78: 45227 | G78: =Mantenimiento[[#This Row],[Fecha Entrada]] -> 45227 | H78: Preventivo | I78: 12046 | J78: =Mantenimiento[[#This Row],[Kilometraje del Odómetro]]-I77 -> 6383 | M78: Preventivo 01 | O78: Mantenimiento Preventivo 8000 kms
C79: =ROW(A76) -> 76 | D79: QAA-2916 | E79: MECÁNICA ORIENTOIL | F79: 45311 | G79: =Mantenimiento[[#This Row],[Fecha Entrada]] -> 45311 | H79: Preventivo | I79: 18216 | J79: =Mantenimiento[[#This Row],[Kilometraje del Odómetro]]-I78 -> 6170 | M79: Preventivo 01 | O79: Mantenimiento Preventivo 8000 kms
C80: =ROW(A77) -> 77 | D80: QAA-2916 | E80: MECÁNICA ORIENTOIL | F80: 45424 | G80: =Mantenimiento[[#This Row],[Fecha Entrada]] -> 45424 | H80: Preventivo | I80: 29886 | J80: =Mantenimiento[[#This Row],[Kilometraje del Odómetro]]-I79 -> 11670 | M80: Preventivo 01 | O80: Mantenimiento Preventivo 8000 kms
C81: =ROW(A78) -> 78 | D81: QAA-2916 | E81: MECÁNICA ORIENTOIL | F81: 45471 | G81: =Mantenimiento[[#This Row],[Fecha Entrada]] -> 45471 | H81: Preventivo | I81: 38240 | J81: =Mantenimiento[[#This Row],[Kilometraje del Odómetro]]-I80 -> 8354 | M81: Preventivo 02 | O81: Mantenimiento Preventivo 8000 kms
C82: =ROW(A79) -> 79 | D82: QAA-2916 | E82: MECÁNICA ORIENTOIL | F82: 45554 | G82: =Mantenimiento[[#This Row],[Fecha Entrada]] -> 45554 | H82: Preventivo | I82: 46743 | J82: =Mantenimiento[[#This Row],[Kilometraje del Odómetro]]-I81 -> 8503 | M82: Preventivo 02 | O82: Mantenimiento Preventivo 8000 kms
C83: =ROW(A80) -> 80 | D83: QAA-2916 | E83: MECÁNICA ORIENTOIL | F83: 45638 | G83: =Mantenimiento[[#This Row],[Fecha Entrada]] -> 45638 | H83: Preventivo | I83: 54704 | J83: =Mantenimiento[[#This Row],[Kilometraje del Odómetro]]-I82 -> 7961 | M83: Preventivo 02 | O83: Mantenimiento Preventivo 8000 kms
C84: =ROW(A81) -> 81 | D84: QAA-2916 | E84: MECÁNICA ORIENTOIL | F84: 45702 | G84: =Mantenimiento[[#This Row],[Fecha Entrada]] -> 45702 | H84: Preventivo | I84: 62417 | J84: =Mantenimiento[[#This Row],[Kilometraje del Odómetro]]-I83 -> 7713 | L84: 2 | M84: Preventivo 03 | O84: Mantenimiento Preventivo 8000 kms
C85: =ROW(A82) -> 82 | D85: QAA-2916 | E85: MECÁNICA ORIENTOIL | F85: 45754 | G85: 45754 | H85: Preventivo | I85: 71131 | J85: =Mantenimiento[[#This Row],[Kilometraje del Odómetro]]-I84 -> 8714 | L85: 2 | M85: Preventivo 03 | N85: 2025040009 | O85: Mantenimiento Preventivo 8000 kms
C86: =ROW(A83) -> 83 | D86: QAA-2916 | E86: MECÁNICA ORIENTOIL | F86: 45791 | G86: 45791 | H86: Preventivo | I86: 79638 | J86: =Mantenimiento[[#This Row],[Kilometraje del Odómetro]]-I85 -> 8507 | L86: 2 | M86: Preventivo 03 | N86: 2025050014 | O86: Mantenimiento Preventivo 8000 kms
C87: =ROW(A84) -> 84 | D87: QAA-2916 | E87: MECÁNICA ORIENTOIL | F87: 45820 | G87: 45820 | H87: Preventivo | I87: 88310 | J87: =Mantenimiento[[#This Row],[Kilometraje del Odómetro]]-I86 -> 8672 | L87: 2 | M87: Preventivo 03 | N87: 2025060030 | O87: Mantenimiento Preventivo 8000 kms
C88: =ROW(A85) -> 85 | D88: QAA-2916 | E88: MECÁNICA ORIENTOIL | F88: 45842 | G88: 45842 | H88: Prev Caja y Corona | I88: 91080 | L88: 2 | M88: Caja y Corona 01 | O88: Mantenimiento Preventivo 60000 Kms
C89: =ROW(A86) -> 86 | D89: QAA-2916 | E89: MECÁNICA ORIENTOIL | F89: 45891 | G89: 45891 | H89: Preventivo | I89: 96460 | J89: =Mantenimiento[[#This Row],[Kilometraje del Odómetro]]-I87 -> 8150 | L89: 2 | M89: Preventivo 04 | N89: 2025080035 | O89: Mantenimiento Preventivo 8000 kms
C90: =ROW(A87) -> 87 | D90: QAA-2916 | E90: MECÁNICA ORIENTOIL | F90: 45922 | G90: 45922 | H90: Correctivo | I90: 101393 | K90: 1 | M90: Correctivo 01 | N90: 2025091195 | O90: Revisión y ajuste de muelas de Quinta Rueda
C91: =ROW(A88) -> 88 | D91: QAA-2916 | E91: MECÁNICA ORIENTOIL | F91: 45938 | G91: 45938 | H91: Preventivo | I91: 104335 | J91: =Mantenimiento[[#This Row],[Kilometraje del Odómetro]]-I89 -> 7875 | L91: 2 | M91: Preventivo 02 | N91: 2025101222 | O91: Mantenimiento Preventivo 8000 kms
C92: =ROW(A89) -> 89 | D92: QAA-2916 | E92: MECÁNICA ORIENTOIL | F92: 45940 | G92: 45940 | H92: Correctivo | I92: 104897 | K92: 2 | M92: Correctivo 03 | N92: 2025101227 | O92: Cambio de 8 Llantas Nuevas
C93: =ROW(A90) -> 90 | D93: QAA-2916 | E93: MECÁNICA ORIENTOIL | F93: 45985 | G93: 45985 | H93: Preventivo | I93: 112441 | J93: =Mantenimiento[[#This Row],[Kilometraje del Odómetro]]-I91 -> 8106 | L93: 2 | M93: Preventivo 02 | N93: 2025110034 | O93: Mantenimiento Preventivo 8000 kms
C94: =ROW(A91) -> 91 | D94: QAA-2916 | E94: MECÁNICA ORIENTOIL | F94: 46001 | G94: 46001 | H94: Correctivo | I94: 115206 | K94: 5 | M94: Correctivo 02 | N94: 2025121326 | O94: Cambio de cinturones, Revision de alarmas en el tablero y chequeo de fuga de aire.
C95: =ROW(A91) -> 91
C96: =ROW(A91) -> 91
C97: =ROW(A92) -> 92
C98: =ROW(A93) -> 93 | J98: =Mantenimiento[[#This Row],[Kilometraje del Odómetro]]-I97 -> 0
C99: =ROW(A96) -> 96 | D99: QAA-3165 | E99: MECÁNICA ORIENTOIL | F99: 45594 | G99: =Mantenimiento[[#This Row],[Fecha Entrada]] -> 45594 | H99: Preventivo | I99: 5943 | J99: =Mantenimiento[[#This Row],[Kilometraje del Odómetro]]-I98 -> 5943 | M99: Preventivo 01 | O99: Mantenimiento Preventivo 8000 kms
C100: =ROW(A97) -> 97 | D100: QAA-3165 | E100: MECÁNICA ORIENTOIL | F100: 45623 | G100: =Mantenimiento[[#This Row],[Fecha Entrada]] -> 45623 | H100: Preventivo | I100: 15273 | J100: =Mantenimiento[[#This Row],[Kilometraje del Odómetro]]-I99 -> 9330 | M100: Preventivo 01 | O100: Mantenimiento Preventivo 8000 kms
C101: =ROW(A98) -> 98 | D101: QAA-3165 | E101: MECÁNICA ORIENTOIL | F101: 45673 | G101: =Mantenimiento[[#This Row],[Fecha Entrada]] -> 45673 | H101: Preventivo | I101: 23308 | J101: =Mantenimiento[[#This Row],[Kilometraje del Odómetro]]-I100 -> 8035 | L101: 2 | M101: Preventivo 01 | O101: Mantenimiento Preventivo 8000 kms
...

Sheet DAÑOS
A1: Equipo | B1: Fecha_Fallo | C1: Kilometraje_Horas_Fallo | D1: Fecha_Inicio_Reparacion | E1: Fecha_Fin_Reparacion | F1: Tiempo_Reparacion_horas | G1: Tipo_Fallo | H1: Estado_Reparacion | I1: Intervalo_Entre_Fallos | J1: Causas de la falla | K1: criterio de busqueda
A2: KR-1094/42424 | B2: 45905 | C2: 2270 | D2: 45967 | F2: 40 | G2: Primer Fallo | H2: Completado | I2: =IF(COUNTIF(A$2:A2,A2)=1,0,IFERROR(C2-_xlfn.MAXIFS(C$2:C$47,A$2:A$52,A2,B$2:B$47,"<"&B2),0)) -> 0 | J2: Cambio de radiador, Cambio de Empaques, cambio de bola en la bota | K2: 385 | M2: =VLOOKUP(W2,Mantenimiento!$C4:$L602,2,0) -> #N/A | N2: =VLOOKUP($K2,Mantenimiento!$C4:$L602,5,0) -> 45950 | O2: =VLOOKUP($K2,Mantenimiento!$C4:$L602,7,0) -> 1130 | P2: 45928 | R2: 1 | S2: Primer Fallo | T2: =IF(R2>0,"Completado","0") -> Completado | U2: =IF(COUNTIF(M$2:M2,M2)=1,0,IFERROR(O2-_xlfn.MAXIFS(O$2:O$52,M$2:M$52,M2,N$2:N$52,"<"&N2),0)) -> 0 | V2: =VLOOKUP($K2,Mantenimiento!$C4:$O602,13,0) -> Cambio de Manometro de -10 a +10
A3: KR-1184/42418 | B3: 45910 | C3: 860 | D3: 45960 | F3: 33 | G3: Primer Fallo | H3: Completado | I3: =IF(COUNTIF(A$2:A3,A3)=1,0,IFERROR(C3-_xlfn.MAXIFS(C$2:C$47,A$2:A$52,A3,B$2:B$47,"<"&B3),0)) -> 0 | J3: Cambio de cable de energia que conecta el cabezal con el vacuum y cambio de tanque de combustible | K3: 366
A4: KR-1344/42429 | B4: 45911 | C4: 1129 | D4: 45945 | F4: 18 | G4: Primer Fallo | H4: Completado | I4: =IF(COUNTIF(A$2:A4,A4)=1,0,IFERROR(C4-_xlfn.MAXIFS(C$2:C$47,A$2:A$52,A4,B$2:B$47,"<"&B4),0)) -> 0 | J4: Cambio de valvula prinicpal de vacuum | K4: 259
A5: QAA-3165 | B5: 45916 | C5: 51699 | D5: 45936 | F5: 9 | G5: Primer Fallo | H5: Completado | I5: =IF(COUNTIF(A$2:A5,A5)=1,0,IFERROR(C5-_xlfn.MAXIFS(C$2:C$47,A$2:A$52,A5,B$2:B$47,"<"&B5),0)) -> 0 | J5: Cambio de Faro derecho frontal | K5: 94
A6: KR-1344/42429 | B6: 45916 | C6: 1180 | D6: 45946 | F6: 19 | G6: Correctivo | H6: Completado | I6: =IF(COUNTIF(A$2:A6,A6)=1,0,IFERROR(C6-_xlfn.MAXIFS(C$2:C$47,A$2:A$52,A6,B$2:B$47,"<"&B6),0)) -> 0 | J6: Cambio de bandas | K6: 260
A7: KR-1344/42429 | B7: 45918 | C7: 1200 | D7: 45947 | F7: 20 | G7: Correctivo | H7: Completado | I7: =IF(COUNTIF(A$2:A7,A7)=1,0,IFERROR(C7-_xlfn.MAXIFS(C$2:C$47,A$2:A$52,A7,B$2:B$47,"<"&B7),0)) -> 0 | J7: Cambio de luces guia traseras | K7: 261
A8: QAA-2915 | B8: 45920 | C8: 115915 | D8: 45929 | F8: 2 | G8: Primer Fallo | H8: Completado | I8: =IF(COUNTIF(A$2:A8,A8)=1,0,IFERROR(C8-_xlfn.MAXIFS(C$2:C$47,A$2:A$52,A8,B$2:B$47,"<"&B8),0)) -> 0 | J8: Cambio de foco Neblinero | K8: 56
A9: QAA-3165 | B9: 45921 | C9: 52865 | D9: 45937 | F9: 10 | G9: Correctivo | H9: Completado | I9: =IF(COUNTIF(A$2:A9,A9)=1,0,IFERROR(C9-_xlfn.MAXIFS(C$2:C$47,A$2:A$52,A9,B$2:B$47,"<"&B9),0)) -> 0 | J9: Cambio de Faro zquierdo frontal y Revisión de baterias | K9: 95
A10: KR-1108/42403 | B10: 45921 | C10: 3345 | D10: 45958 | F10: 31 | G10: Primer Fallo | H10: Completado | I10: =IF(COUNTIF(A$2:A10,A10)=1,0,IFERROR(C10-_xlfn.MAXIFS(C$2:C$47,A$2:A$52,A10,B$2:B$47,"<"&B10),0)) -> 0 | J10: Cambio de 8 Llantas Reencauchadas de Vacuum | K10: 354
A11: KR-1184/42418 | B11: 45921 | C11: 951 | D11: 45961 | F11: 34 | G11: Correctivo | H11: Completado | I11: =IF(COUNTIF(A$2:A11,A11)=1,0,IFERROR(C11-_xlfn.MAXIFS(C$2:C$47,A$2:A$52,A11,B$2:B$47,"<"&B11),0)) -> 0 | J11: Cambio de un switch de 1 tiempo de Vacuum | K11: 367
A12: QAA-2916 | B12: 45922 | C12: 101393 | D12: 45934 | F12: 7 | G12: Primer Fallo | H12: Completado | I12: =IF(COUNTIF(A$2:A12,A12)=1,0,IFERROR(C12-_xlfn.MAXIFS(C$2:C$47,A$2:A$52,A12,B$2:B$47,"<"&B12),0)) -> 0 | J12: Revisión y ajuste de muelas de Quinta Rueda | K12: 81
A13: KR-1344/42429 | B13: 45922 | C13: 1218 | D13: 45948 | F13: 21 | G13: Correctivo | H13: Completado | I13: =IF(COUNTIF(A$2:A13,A13)=1,0,IFERROR(C13-_xlfn.MAXIFS(C$2:C$47,A$2:A$52,A13,B$2:B$47,"<"&B13),0)) -> 0 | J13: Cambio de 2 Bandas de compresor de Vacuum | K13: 262
A14: KR-1184/42418 | B14: 45922 | C14: 961 | D14: 45962 | F14: 35 | G14: Correctivo | H14: Completado | I14: =IF(COUNTIF(A$2:A14,A14)=1,0,IFERROR(C14-_xlfn.MAXIFS(C$2:C$47,A$2:A$52,A14,B$2:B$47,"<"&B14),0)) -> 0 | J14: Revisión de tapas de combustible y revisión de tomacorriente de vacuum | K14: 368
A15: KR-1094/42424 | B15: 45922 | C15: 1 | D15: 45968 | F15: 41 | G15: Correctivo | H15: Completado | I15: =IF(COUNTIF(A$2:A15,A15)=1,0,IFERROR(C15-_xlfn.MAXIFS(C$2:C$47,A$2:A$52,A15,B$2:B$47,"<"&B15),0))+C2 -> 2270 | J15: Cambio de Hormetro dañado de Vacuum | K15: 386
A16: KR-1088/42406 | B16: 45923 | C16: 401 | D16: 45953 | F16: 26 | G16: Primer Fallo | H16: Completado | I16: =IF(COUNTIF(A$2:A16,A16)=1,0,IFERROR(C16-_xlfn.MAXIFS(C$2:C$47,A$2:A$52,A16,B$2:B$47,"<"&B16),0)) -> 0 | J16: Cambio de kinping y regulación de frenos | K16: 317
A17: QAA-3165 | B17: 45924 | C17: 53519 | D17: 45938 | F17: 11 | G17: Correctivo | H17: Completado | I17: =IF(COUNTIF(A$2:A17,A17)=1,0,IFERROR(C17-_xlfn.MAXIFS(C$2:C$47,A$2:A$52,A17,B$2:B$47,"<"&B17),0)) -> 0 | J17: Cambio de 2 baterias | K17: 96
A18: QAA-2915 | B18: 45925 | C18: 116432 | D18: 45930 | F18: 3 | G18: Correctivo | H18: Completado | I18: =IF(COUNTIF(A$2:A18,A18)=1,0,IFERROR(C18-_xlfn.MAXIFS(C$2:C$47,A$2:A$52,A18,B$2:B$47,"<"&B18),0)) -> 0 | J18: Cambio de luces guias posteriores | K18: 57
A19: QAA-2912 | B19: 45928 | C19: 115400 | D19: 45928 | F19: 1 | G19: Primer Fallo | H19: Completado | I19: =IF(COUNTIF(A$2:A19,A19)=1,0,IFERROR(C19-_xlfn.MAXIFS(C$2:C$47,A$2:A$52,A19,B$2:B$47,"<"&B19),0)) -> 0 | J19: Cambio de luces guias posteriores | K19: 36
A20: KR-1094/42424 | B20: 45928 | C20: 30 | D20: 45969 | F20: 42 | G20: Correctivo | H20: Completado | I20: =IF(COUNTIF(A$2:A20,A20)=1,0,IFERROR(C20-_xlfn.MAXIFS(C$2:C$47,A$2:A$52,A20,B$2:B$47,"<"&B20),0))+C2 -> 2270 | J20: Cambio de Valvula Check, Valvula de alivio y Valvula repartidora. | K20: 387
A21: KR-1344/42429 | B21: 45929 | C21: 1250 | D21: 45949 | F21: 22 | G21: Correctivo | H21: Completado | I21: =IF(COUNTIF(A$2:A21,A21)=1,0,IFERROR(C21-_xlfn.MAXIFS(C$2:C$47,A$2:A$52,A21,B$2:B$47,"<"&B21),0)) -> 0 | J21: Cambio de 2 Bandas de compresor de Vacuum | K21: 264
A22: KR-1088/42406 | B22: 45929 | C22: 452 | D22: 45954 | F22: 27 | G22: Correctivo | H22: Completado | I22: =IF(COUNTIF(A$2:A22,A22)=1,0,IFERROR(C22-_xlfn.MAXIFS(C$2:C$47,A$2:A$52,A22,B$2:B$47,"<"&B22),0)) -> 0 | J22: Cambio de tetenedor de valvula de 4 Vías | K22: 319
A23: KR-1184/42418 | B23: 45929 | C23: 982 | D23: 45963 | F23: 36 | G23: Correctivo | H23: Completado | I23: =IF(COUNTIF(A$2:A23,A23)=1,0,IFERROR(C23-_xlfn.MAXIFS(C$2:C$47,A$2:A$52,A23,B$2:B$47,"<"&B23),0)) -> 0 | J23: Arreglo de fuga de aire en manguera principal | K23: 369
A24: KR-1184/42418 | B24: 45931 | C24: 1012 | D24: 45964 | F24: 37 | G24: Primer Fallo | H24: Completado | I24: =IF(COUNTIF(A$2:A24,A24)=1,0,IFERROR(C24-_xlfn.MAXIFS(C$2:C$47,A$2:A$52,A24,B$2:B$47,"<"&B24),0)) -> 0 | J24: Cambio de Válvula repatidora del vacuum y manguera de aire | K24: 370
A25: KR-1088/42406 | B25: 45932 | C25: 463 | D25: 45955 | F25: 28 | G25: Primer Fallo | H25: Completado | I25: =IF(COUNTIF(A$2:A25,A25)=1,0,IFERROR(C25-_xlfn.MAXIFS(C$2:C$47,A$2:A$52,A25,B$2:B$47,"<"&B25),0)) -> 0 | J25: Soldado de tanquere de aire de vacuum | K25: 320
A26: KR-1094/42424 | B26: 45932 | C26: 64 | D26: 45970 | F26: 43 | G26: Primer Fallo | H26: Completado | I26: =IF(COUNTIF(A$2:A26,A26)=1,0,IFERROR(C26-_xlfn.MAXIFS(C$2:C$47,A$2:A$52,A26,B$2:B$47,"<"&B26),0))+C2 -> 2270 | J26: Cambio de manguera de aire por taponamiento | K26: 388
A27: QAA-3074 | B27: 45937 | C27: 19130 | D27: 45942 | F27: 15 | G27: Primer Fallo | H27: Completado | I27: =IF(COUNTIF(A$2:A27,A27)=1,0,IFERROR(C27-_xlfn.MAXIFS(C$2:C$47,A$2:A$52,A27,B$2:B$47,"<"&B27),0)) -> 0 | J27: Cambio de manguera de aire de cabezal vacuum | K27: 191
A28: QAA-2916 | B28: 45940 | C28: 104897 | D28: 45935 | F28: 8 | G28: Primer Fallo | H28: Completado | I28: =IF(COUNTIF(A$2:A28,A28)=1,0,IFERROR(C28-_xlfn.MAXIFS(C$2:C$47,A$2:A$52,A28,B$2:B$47,"<"&B28),0)) -> 0 | J28: Cambio de 8 Llantas Nuevas | K28: 83
A29: KR-1188/42405 | B29: 45947 | C29: 2442 | D29: 45952 | F29: 25 | G29: Primer Fallo | H29: Completado | I29: =IF(COUNTIF(A$2:A29,A29)=1,0,IFERROR(C29-_xlfn.MAXIFS(C$2:C$47,A$2:A$52,A29,B$2:B$47,"<"&B29),0)) -> 0 | J29: Cambio de faro led cuadrado | K29: 297
A30: QAA-2915 | B30: 45948 | C30: 120390 | D30: 45931 | F30: 4 | G30: Primer Fallo | H30: Completado | I30: =IF(COUNTIF(A$2:A30,A30)=1,0,IFERROR(C30-_xlfn.MAXIFS(C$2:C$47,A$2:A$52,A30,B$2:B$47,"<"&B30),0)) -> 0 | J30: Cambio de 2 baterias NS 150 | K30: 59
A31: QAA-2915 | B31: 45948 | C31: 120390 | D31: 45933 | F31: 6 | G31: Correctivo | H31: Completado | I31: =IF(COUNTIF(A$2:A31,A31)=1,0,IFERROR(C31-_xlfn.MAXIFS(C$2:C$47,A$2:A$52,A31,B$2:B$47,"<"&B31),0)) -> 0 | J31: Cambio de 2 baterias NS 150 | K31: 59
A32: KR-1184/42418 | B32: 45950 | C32: 1130 | D32: 45965 | F32: 38 | G32: Correctivo | H32: Completado | I32: =IF(COUNTIF(A$2:A32,A32)=1,0,IFERROR(C32-_xlfn.MAXIFS(C$2:C$47,A$2:A$52,A32,B$2:B$47,"<"&B32),0)) -> 0 | J32: Cambio de Manometro de -10 a +10 | K32: 372
A33: KR-1184/42418 | B33: 45950 | C33: 1130 | D33: 45966 | F33: 39 | G33: Correctivo | H33: Completado | I33: =IF(COUNTIF(A$2:A33,A33)=1,0,IFERROR(C33-_xlfn.MAXIFS(C$2:C$47,A$2:A$52,A33,B$2:B$47,"<"&B33),0)) -> 0 | J33: Cambio de Manometro de -10 a +10 | K33: 372
A34: KR-1094/42424 | B34: 45951 | C34: 223 | D34: 45971 | F34: 44 | G34: Correctivo | H34: Completado | I34: =IF(COUNTIF(A$2:A34,A34)=1,0,IFERROR(C34-_xlfn.MAXIFS(C$2:C$60,A$2:A$60,A34,B$2:B$60,"<"&B34),0))+C2 -> 223 | J34: Cambio de 2 Llantas reencauchadas 12 R 22.5 | K34: 390
A35: KR-1088/42406 | B35: 45952 | C35: 506 | D35: 45956 | F35: 29 | G35: Correctivo | H35: Completado | I35: =IF(COUNTIF(A$2:A35,A35)=1,0,IFERROR(C35-_xlfn.MAXIFS(C$2:C$47,A$2:A$52,A35,B$2:B$47,"<"&B35),0)) -> 0 | J35: Cambio de las 2 Patas de Apoyo del vacuum | K35: 321
A36: QAA-2915 | B36: 45954 | C36: 121490 | D36: 45932 | F36: 5 | G36: Correctivo | H36: Completado | I36: =IF(COUNTIF(A$2:A36,A36)=1,0,IFERROR(C36-_xlfn.MAXIFS(C$2:C$47,A$2:A$52,A36,B$2:B$47,"<"&B36),0)) -> 0 | J36: Cambio de 8 Llantas nuevas para el cabezal | K36: 60
A37: QAA-3165 | B37: 45957 | C37: 57606 | D37: 45939 | F37: 12 | G37: Primer Fallo | H37: Completado | I37: =IF(COUNTIF(A$2:A37,A37)=1,0,IFERROR(C37-_xlfn.MAXIFS(C$2:C$47,A$2:A$52,A37,B$2:B$47,"<"&B37),0)) -> 0 | J37: Soldado de radiador por liqueo de refrigerante | K37: 98
A38: QAA-3220 | B38: 45963 | C38: 49213 | D38: 45963 | F38: 1 | G38: Primer Fallo | H38: Completado | I38: =IF(COUNTIF(A$2:A38,A38)=1,0,IFERROR(C38-_xlfn.MAXIFS(C$2:C$47,A$2:A$52,A38,B$2:B$47,"<"&B38),0)) -> 0 | J38: Cambio de foco de retroceso | K38: 162
A39: QAA-3220 | B39: 45970 | C39: 49817 | D39: 45970 | F39: 0.75 | G39: Correctivo | H39: Completado | I39: =IF(COUNTIF(A$2:A39,A39)=1,0,IFERROR(C39-_xlfn.MAXIFS(C$2:C$47,A$2:A$52,A39,B$2:B$47,"<"&B39),0)) -> 0 | J39: Cambio de 2 baterias N 150 | K39: 163
A40: QAA-3074 | B40: 45965 | C40: 26474 | D40: 45965 | F40: 2 | G40: Primer Fallo | H40: Completado | I40: =IF(COUNTIF(A$2:A40,A40)=1,0,IFERROR(C40-_xlfn.MAXIFS(C$2:C$47,A$2:A$52,A40,B$2:B$47,"<"&B40),0)) -> 0 | J40: Cambio de 8 llantas nuevas 12R 22.5 | K40: 196
A41: KR-1344/42429 | B41: 45963 | C41: 1588 | D41: 45963 | F41: 0.5 | G41: Primer Fallo | H41: Completado | I41: =IF(COUNTIF(A$2:A41,A41)=1,0,IFERROR(C41-_xlfn.MAXIFS(C$2:C$47,A$2:A$52,A41,B$2:B$47,"<"&B41),0)) -> 0 | J41: Cambio de foco faro Led cuadrado | K41: 268
A42: KR-1344/42429 | B42: 45973 | C42: 1667 | D42: 45973 | F42: 1 | G42: Correctivo | H42: Completado | I42: =IF(COUNTIF(A$2:A42,A42)=1,0,IFERROR(C42-_xlfn.MAXIFS(C$2:C$47,A$2:A$52,A42,B$2:B$47,"<"&B42),0)) -> 0 | J42: Cambio de tanque de combustible | K42: 269
A43: KR-1088/42406 | B43: 45971 | C43: 532 | D43: 45971 | F43: 0.75 | G43: Primer Fallo | H43: Completado | I43: =IF(COUNTIF(A$2:A43,A43)=1,0,IFERROR(C43-_xlfn.MAXIFS(C$2:C$47,A$2:A$52,A43,B$2:B$47,"<"&B43),0)) -> 0 | J43: Cambio de Batería NS 78 | K43: 324
A44: KR-1108/42403 | B44: 45962 | C44: 3630 | D44: 45962 | F44: 1 | G44: Primer Fallo | H44: Completado | I44: =IF(COUNTIF(A$2:A44,A44)=1,0,IFERROR(C44-_xlfn.MAXIFS(C$2:C$47,A$2:A$52,A44,B$2:B$47,"<"&B44),0)) -> 0 | J44: Cambio de bateria y alternador | K44: 358
A45: KR-1108/42403 | B45: 45987 | C45: 3819 | D45: 45987 | F45: 1 | G45: Correctivo | H45: Completado | I45: =IF(COUNTIF(A$2:A45,A45)=1,0,IFERROR(C45-_xlfn.MAXIFS(C$2:C$47,A$2:A$52,A45,B$2:B$47,"<"&B45),0)) -> 0 | J45: Mantenimiento correctivo con el cambio de las dos bandas del compresor | K45: 360
A46: KR-1184/42418 | B46: 45973 | C46: 1208 | D46: 45973 | F46: 0.5 | G46: Primer Fallo | H46: Completado | I46: =IF(COUNTIF(A$2:A46,A46)=1,0,IFERROR(C46-_xlfn.MAXIFS(C$2:C$47,A$2:A$52,A46,B$2:B$47,"<"&B46),0)) -> 0 | J46: Cambio de acople hembra de valvula de alivio | K46: 377
A47: KR-1184/42418 | B47: 45986 | C47: 1263 | D47: 45986 | F47: 1 | G47: Correctivo | H47: Completado | I47: =IF(COUNTIF(A$2:A47,A47)=1,0,IFERROR(C47-_xlfn.MAXIFS(C$2:C$47,A$2:A$52,A47,B$2:B$47,"<"&B47),0)) -> 0 | J47: Cambio de v{alvula principal repartidora del vacuum | K47: 378
A48: QAA-3164 | B48: 46008 | C48: 43982 | D48: 46008 | F48: 2 | G48: Primer Fallo | H48: Completado | I48: =IF(COUNTIF(A$2:A48,A48)=1,0,IFERROR(C48-_xlfn.MAXIFS(C$2:C$57,A$2:A$57,A48,B$2:B$57,"<"&B48),0)) -> 0 | J48: Arreglo del motor de subida del vidrio y cambio de radio
A49: QAA-3164 | B49: 46008 | C49: 43983 | D49: 46008 | F49: 3 | G49: Correctivo | H49: Completado | I49: =IF(COUNTIF(A$2:A49,A49)=1,0,IFERROR(C49-_xlfn.MAXIFS(C$2:C$57,A$2:A$57,A49,B$2:B$57,"<"&B49),0)) -> 43983 | J49: Cambio de retrovisor, Ajuste de Quinta rueda y arreglo de Tubo de escape
A50: QAA-3164 | B50: 46009 | C50: 43984 | D50: 46009 | F50: 2 | G50: Correctivo | H50: Completado | I50: =IF(COUNTIF(A$2:A50,A50)=1,0,IFERROR(C50-_xlfn.MAXIFS(C$2:C$57,A$2:A$57,A50,B$2:B$57,"<"&B50),0)) -> 1 | J50: Chequeo de fuga de aire
A51: QAA-2912 | B51: 46000 | C51: 127361 | D51: 46000 | F51: 3 | G51: Primer Fallo | H51: Completado | I51: =IF(COUNTIF(A$2:A51,A51)=1,0,IFERROR(C51-_xlfn.MAXIFS(C$2:C$57,A$2:A$57,A51,B$2:B$57,"<"&B51),0)) -> 11961 | J51: Chequeo de alarmas encendidas en el tablero
A52: QAA-2916 | B52: 46001 | C52: 115206 | D52: 46001 | F52: 5 | G52: Primer Fallo | H52: Completado | I52: =IF(COUNTIF(A$2:A52,A52)=1,0,IFERROR(C52-_xlfn.MAXIFS(C$2:C$57,A$2:A$57,A52,B$2:B$57,"<"&B52),0)) -> 10309 | J52: Cambio de cinturones, Revision de alarmas en el tablero y chequeo de fuga de aire.
A53: PFF-2857 | B53: 45999 | C53: 113075 | D53: 45999 | F53: 30 | G53: Primer Fallo | H53: Completado | I53: =IF(COUNTIF(A$2:A53,A53)=1,0,IFERROR(C53-_xlfn.MAXIFS(C$2:C$57,A$2:A$57,A53,B$2:B$57,"<"&B53),0)) -> 0 | J53: Revision y correccion de Inyectores
A54: KR-1344/42429 | B54: 46008 | C54: 2022 | D54: 46008 | F54: 1 | G54: Primer Fallo | H54: Completado | I54: =IF(COUNTIF(A$2:A54,A54)=1,0,IFERROR(C54-_xlfn.MAXIFS(C$2:C$57,A$2:A$57,A54,B$2:B$57,"<"&B54),0)) -> 355 | J54: Cambio de valvula de 2 pulgadas
A55: KR-1088/42406 | B55: 46015 | C55: 900 | D55: 46015 | F55: 1 | G55: Primer Fallo | H55: Completado | I55: =IF(COUNTIF(A$2:A55,A55)=1,0,IFERROR(C55-_xlfn.MAXIFS(C$2:C$57,A$2:A$57,A55,B$2:B$57,"<"&B55),0)) -> 368 | J55: Cambio de collarin del embargue de motor de vacuum
A56: KR-1108/42403 | B56: 46002 | C56: 3973 | D56: 46002 | F56: 2 | G56: Primer Fallo | H56: Completado | I56: =IF(COUNTIF(A$2:A56,A56)=1,0,IFERROR(C56-_xlfn.MAXIFS(C$2:C$57,A$2:A$57,A56,B$2:B$57,"<"&B56),0)) -> 154 | J56: Cambio de un pulmon sencilloy valvula de bola del carter

Sheet Flujo de Caja
B1: UTILIDAD DEL PROYECTO
D3: =DATE($D$6,MATCH(D8,$D$8:$O$8,0),1) -> 45658 | E3: =DATE($D$6,MATCH(E8,$D$8:$O$8,0),1) -> 45689 | F3: =DATE($D$6,MATCH(F8,$D$8:$O$8,0),1) -> 45717 | G3: =DATE($D$6,MATCH(G8,$D$8:$O$8,0),1) -> 45748 | H3: =DATE($D$6,MATCH(H8,$D$8:$O$8,0),1) -> 45778 | I3: =DATE($D$6,MATCH(I8,$D$8:$O$8,0),1) -> 45809 | J3: =DATE($D$6,MATCH(J8,$D$8:$O$8,0),1) -> 45839 | K3: =DATE($D$6,MATCH(K8,$D$8:$O$8,0),1) -> 45870 | ... O3: =DATE($D$6,MATCH(O8,$D$8:$O$8,0),1) -> 45992
D4: =EOMONTH(D3,0) -> 45688 | E4: =EOMONTH(E3,0) -> 45716 | F4: =EOMONTH(F3,0) -> 45747 | G4: =EOMONTH(G3,0) -> 45777 | H4: =EOMONTH(H3,0) -> 45808 | I4: =EOMONTH(I3,0) -> 45838 | J4: =EOMONTH(J3,0) -> 45869 | K4: =EOMONTH(K3,0) -> 45900 | ... O4: =EOMONTH(O3,0) -> 46022
C6: Año | D6: 2025 | R6: EGRESOS VARIOS
C8: Concepto | D8: Enero | E8: Febrero | F8: Marzo | G8: Abril | H8: Mayo | I8: Junio | J8: Julio | K8: Agosto | L8: Setiembre | M8: Octubre | N8: Noviembre | O8: Diciembre | P8: Total | R8: Año | S8: Mes | T8: Gastos Personal | U8: Otros Egresos
C9: Ingresos ($) | D9: =SUMIFS(Rutas[Ingreso Total ($)],Rutas[Fecha de Llegada],">="&D$3,Rutas[Fecha de Llegada],"<="&D$4) -> 1374.45 | E9: =SUMIFS(Rutas[Ingreso Total ($)],Rutas[Fecha de Llegada],">="&E$3,Rutas[Fecha de Llegada],"<="&E$4) -> 0 | F9: =SUMIFS(Rutas[Ingreso Total ($)],Rutas[Fecha de Llegada],">="&F$3,Rutas[Fecha de Llegada],"<="&F$4) -> 0 | G9: =SUMIFS(Rutas[Ingreso Total ($)],Rutas[Fecha de Llegada],">="&G$3,Rutas[Fecha de Llegada],"<="&G$4) -> 0 | H9: =SUMIFS(Rutas[Ingreso Total ($)],Rutas[Fecha de Llegada],">="&H$3,Rutas[Fecha de Llegada],"<="&H$4) -> 0 | I9: =SUMIFS(Rutas[Ingreso Total ($)],Rutas[Fecha de Llegada],">="&I$3,Rutas[Fecha de Llegada],"<="&I$4) -> 0 | J9: =SUMIFS(Rutas[Ingreso Total ($)],Rutas[Fecha de Llegada],">="&J$3,Rutas[Fecha de Llegada],"<="&J$4) -> 0 | K9: =SUMIFS(Rutas[Ingreso Total ($)],Rutas[Fecha de Llegada],">="&K$3,Rutas[Fecha de Llegada],"<="&K$4) -> 0 | ... O9: =SUMIFS(Rutas[Ingreso Total ($)],Rutas[Fecha de Llegada],">="&O$3,Rutas[Fecha de Llegada],"<="&O$4) -> 30605.1 | P9: =SUM(D9:O9) -> 94079.93 | R9: 2024 | S9: Enero
C10: Egresos ($) | D10: =SUM(D11:D19) -> 10987.194 | E10: =SUM(E11:E19) -> 9058.158 | F10: =SUM(F11:F19) -> 9461.214 | G10: =SUM(G11:G19) -> 11635.2 | H10: =SUM(H11:H19) -> 19949.706 | I10: =SUM(I11:I19) -> 13746.029 | J10: =SUM(J11:J19) -> 6677.352 | K10: =SUM(K11:K19) -> 13294.836 | ... P10: =SUM(P11:P19) -> 172802.76 | R10: 2024 | S10: Febrero
C11: Personal | D11: =SUMIFS(Egresos_varios[Gastos Personal],Egresos_varios[Año],$D$6,Egresos_varios[Mes],D$8) -> 0 | E11: =SUMIFS(Egresos_varios[Gastos Personal],Egresos_varios[Año],$D$6,Egresos_varios[Mes],E$8) -> 0 | F11: =SUMIFS(Egresos_varios[Gastos Personal],Egresos_varios[Año],$D$6,Egresos_varios[Mes],F$8) -> 0 | G11: =SUMIFS(Egresos_varios[Gastos Personal],Egresos_varios[Año],$D$6,Egresos_varios[Mes],G$8) -> 0 | H11: =SUMIFS(Egresos_varios[Gastos Personal],Egresos_varios[Año],$D$6,Egresos_varios[Mes],H$8) -> 0 | I11: =SUMIFS(Egresos_varios[Gastos Personal],Egresos_varios[Año],$D$6,Egresos_varios[Mes],I$8) -> 0 | J11: =SUMIFS(Egresos_varios[Gastos Personal],Egresos_varios[Año],$D$6,Egresos_varios[Mes],J$8) -> 0 | K11: =SUMIFS(Egresos_varios[Gastos Personal],Egresos_varios[Año],$D$6,Egresos_varios[Mes],K$8) -> 0 | ... O11: =SUMIFS(Egresos_varios[Gastos Personal],Egresos_varios[Año],$D$6,Egresos_varios[Mes],O$8) -> 0 | P11: =SUM(D11:O11) -> 0 | R11: 2024 | S11: Marzo
C12: Seguros | D12: =SUMIFS(Seguros[Importe Pagado ($)],Seguros[Fecha de Pago],">="&D$3,Seguros[Fecha de Pago],"<="&D$4) -> 0 | E12: =SUMIFS(Seguros[Importe Pagado ($)],Seguros[Fecha de Pago],">="&E$3,Seguros[Fecha de Pago],"<="&E$4) -> 0 | F12: =SUMIFS(Seguros[Importe Pagado ($)],Seguros[Fecha de Pago],">="&F$3,Seguros[Fecha de Pago],"<="&F$4) -> 0 | G12: =SUMIFS(Seguros[Importe Pagado ($)],Seguros[Fecha de Pago],">="&G$3,Seguros[Fecha de Pago],"<="&G$4) -> 0 | H12: =SUMIFS(Seguros[Importe Pagado ($)],Seguros[Fecha de Pago],">="&H$3,Seguros[Fecha de Pago],"<="&H$4) -> 0 | I12: =SUMIFS(Seguros[Importe Pagado ($)],Seguros[Fecha de Pago],">="&I$3,Seguros[Fecha de Pago],"<="&I$4) -> 0 | J12: =SUMIFS(Seguros[Importe Pagado ($)],Seguros[Fecha de Pago],">="&J$3,Seguros[Fecha de Pago],"<="&J$4) -> 0 | K12: =SUMIFS(Seguros[Importe Pagado ($)],Seguros[Fecha de Pago],">="&K$3,Seguros[Fecha de Pago],"<="&K$4) -> 0 | ... O12: =SUMIFS(Seguros[Importe Pagado ($)],Seguros[Fecha de Pago],">="&O$3,Seguros[Fecha de Pago],"<="&O$4) -> 0 | P12: =SUM(D12:O12) -> 0 | R12: 2024 | S12: Abril
C13: Impuestos | D13: =SUMIFS(Impuestos[Impuesto ($)],Impuestos[Fecha de pago],">="&D$3,Impuestos[Fecha de pago],"<="&D$4) -> 0 | E13: =SUMIFS(Impuestos[Impuesto ($)],Impuestos[Fecha de pago],">="&E$3,Impuestos[Fecha de pago],"<="&E$4) -> 0 | F13: =SUMIFS(Impuestos[Impuesto ($)],Impuestos[Fecha de pago],">="&F$3,Impuestos[Fecha de pago],"<="&F$4) -> 0 | G13: =SUMIFS(Impuestos[Impuesto ($)],Impuestos[Fecha de pago],">="&G$3,Impuestos[Fecha de pago],"<="&G$4) -> 0 | H13: =SUMIFS(Impuestos[Impuesto ($)],Impuestos[Fecha de pago],">="&H$3,Impuestos[Fecha de pago],"<="&H$4) -> 0 | I13: =SUMIFS(Impuestos[Impuesto ($)],Impuestos[Fecha de pago],">="&I$3,Impuestos[Fecha de pago],"<="&I$4) -> 0 | J13: =SUMIFS(Impuestos[Impuesto ($)],Impuestos[Fecha de pago],">="&J$3,Impuestos[Fecha de pago],"<="&J$4) -> 0 | K13: =SUMIFS(Impuestos[Impuesto ($)],Impuestos[Fecha de pago],">="&K$3,Impuestos[Fecha de pago],"<="&K$4) -> 0 | ... O13: =SUMIFS(Impuestos[Impuesto ($)],Impuestos[Fecha de pago],">="&O$3,Impuestos[Fecha de pago],"<="&O$4) -> 0 | P13: =SUM(D13:O13) -> 0 | R13: 2024 | S13: Mayo
C14: Multas | D14: =SUMIFS(Multas[Importe multa ($)],Multas[Fecha],">="&D$3,Multas[Fecha],"<="&D$4) -> 0 | E14: =SUMIFS(Multas[Importe multa ($)],Multas[Fecha],">="&E$3,Multas[Fecha],"<="&E$4) -> 0 | F14: =SUMIFS(Multas[Importe multa ($)],Multas[Fecha],">="&F$3,Multas[Fecha],"<="&F$4) -> 0 | G14: =SUMIFS(Multas[Importe multa ($)],Multas[Fecha],">="&G$3,Multas[Fecha],"<="&G$4) -> 0 | H14: =SUMIFS(Multas[Importe multa ($)],Multas[Fecha],">="&H$3,Multas[Fecha],"<="&H$4) -> 0 | I14: =SUMIFS(Multas[Importe multa ($)],Multas[Fecha],">="&I$3,Multas[Fecha],"<="&I$4) -> 0 | J14: =SUMIFS(Multas[Importe multa ($)],Multas[Fecha],">="&J$3,Multas[Fecha],"<="&J$4) -> 0 | K14: =SUMIFS(Multas[Importe multa ($)],Multas[Fecha],">="&K$3,Multas[Fecha],"<="&K$4) -> 0 | ... O14: =SUMIFS(Multas[Importe multa ($)],Multas[Fecha],">="&O$3,Multas[Fecha],"<="&O$4) -> 0 | P14: =SUM(D14:O14) -> 0 | R14: 2024 | S14: Junio
C15: Mantenimiento | D15: =SUMIFS(Mantenimiento[Costo Total ($)],Mantenimiento[Fecha de Pago],">="&D$3,Mantenimiento[Fecha de Pago],"<="&D$4) -> 0 | E15: =SUMIFS(Mantenimiento[Costo Total ($)],Mantenimiento[Fecha de Pago],">="&E$3,Mantenimiento[Fecha de Pago],"<="&E$4) -> 0 | F15: =SUMIFS(Mantenimiento[Costo Total ($)],Mantenimiento[Fecha de Pago],">="&F$3,Mantenimiento[Fecha de Pago],"<="&F$4) -> 0 | G15: =SUMIFS(Mantenimiento[Costo Total ($)],Mantenimiento[Fecha de Pago],">="&G$3,Mantenimiento[Fecha de Pago],"<="&G$4) -> 0 | H15: =SUMIFS(Mantenimiento[Costo Total ($)],Mantenimiento[Fecha de Pago],">="&H$3,Mantenimiento[Fecha de Pago],"<="&H$4) -> 0 | I15: =SUMIFS(Mantenimiento[Costo Total ($)],Mantenimiento[Fecha de Pago],">="&I$3,Mantenimiento[Fecha de Pago],"<="&I$4) -> 0 | J15: =SUMIFS(Mantenimiento[Costo Total ($)],Mantenimiento[Fecha de Pago],">="&J$3,Mantenimiento[Fecha de Pago],"<="&J$4) -> 0 | K15: =SUMIFS(Mantenimiento[Costo Total ($)],Mantenimiento[Fecha de Pago],">="&K$3,Mantenimiento[Fecha de Pago],"<="&K$4) -> 0 | ... O15: =SUMIFS(Mantenimiento[Costo Total ($)],Mantenimiento[Fecha de Pago],">="&O$3,Mantenimiento[Fecha de Pago],"<="&O$4) -> 0 | P15: =SUM(D15:O15) -> 0 | R15: 2024 | S15: Julio
C16: Combustible | D16: =SUMIFS(Rutas[Total Combustible ($)],Rutas[Fecha de Llegada],">="&D$3,Rutas[Fecha de Llegada],"<="&D$4) -> 10987.194 | E16: =SUMIFS(Rutas[Total Combustible ($)],Rutas[Fecha de Llegada],">="&E$3,Rutas[Fecha de Llegada],"<="&E$4) -> 9058.158 | F16: =SUMIFS(Rutas[Total Combustible ($)],Rutas[Fecha de Llegada],">="&F$3,Rutas[Fecha de Llegada],"<="&F$4) -> 9461.214 | G16: =SUMIFS(Rutas[Total Combustible ($)],Rutas[Fecha de Llegada],">="&G$3,Rutas[Fecha de Llegada],"<="&G$4) -> 11635.2 | H16: =SUMIFS(Rutas[Total Combustible ($)],Rutas[Fecha de Llegada],">="&H$3,Rutas[Fecha de Llegada],"<="&H$4) -> 19949.706 | I16: =SUMIFS(Rutas[Total Combustible ($)],Rutas[Fecha de Llegada],">="&I$3,Rutas[Fecha de Llegada],"<="&I$4) -> 13746.029 | J16: =SUMIFS(Rutas[Total Combustible ($)],Rutas[Fecha de Llegada],">="&J$3,Rutas[Fecha de Llegada],"<="&J$4) -> 6677.352 | K16: =SUMIFS(Rutas[Total Combustible ($)],Rutas[Fecha de Llegada],">="&K$3,Rutas[Fecha de Llegada],"<="&K$4) -> 13294.836 | ... O16: =SUMIFS(Rutas[Total Combustible ($)],Rutas[Fecha de Llegada],">="&O$3,Rutas[Fecha de Llegada],"<="&O$4) -> 21275.66 | P16: =SUM(D16:O16) -> 172802.76 | R16: 2024 | S16: Agosto
C17: Peaje | D17: =SUMIFS(Rutas[Gasto peajes ($)],Rutas[Fecha de Llegada],">="&D$3,Rutas[Fecha de Llegada],"<="&D$4) -> 0 | E17: =SUMIFS(Rutas[Gasto peajes ($)],Rutas[Fecha de Llegada],">="&E$3,Rutas[Fecha de Llegada],"<="&E$4) -> 0 | F17: =SUMIFS(Rutas[Gasto peajes ($)],Rutas[Fecha de Llegada],">="&F$3,Rutas[Fecha de Llegada],"<="&F$4) -> 0 | G17: =SUMIFS(Rutas[Gasto peajes ($)],Rutas[Fecha de Llegada],">="&G$3,Rutas[Fecha de Llegada],"<="&G$4) -> 0 | H17: =SUMIFS(Rutas[Gasto peajes ($)],Rutas[Fecha de Llegada],">="&H$3,Rutas[Fecha de Llegada],"<="&H$4) -> 0 | I17: =SUMIFS(Rutas[Gasto peajes ($)],Rutas[Fecha de Llegada],">="&I$3,Rutas[Fecha de Llegada],"<="&I$4) -> 0 | J17: =SUMIFS(Rutas[Gasto peajes ($)],Rutas[Fecha de Llegada],">="&J$3,Rutas[Fecha de Llegada],"<="&J$4) -> 0 | K17: =SUMIFS(Rutas[Gasto peajes ($)],Rutas[Fecha de Llegada],">="&K$3,Rutas[Fecha de Llegada],"<="&K$4) -> 0 | ... O17: =SUMIFS(Rutas[Gasto peajes ($)],Rutas[Fecha de Llegada],">="&O$3,Rutas[Fecha de Llegada],"<="&O$4) -> 0 | P17: =SUM(D17:O17) -> 0 | R17: 2024 | S17: Setiembre
C18: Comidas | D18: =SUMIFS(Rutas[Gasto comidas ($)],Rutas[Fecha de Llegada],">="&D$3,Rutas[Fecha de Llegada],"<="&D$4) -> 0 | E18: =SUMIFS(Rutas[Gasto comidas ($)],Rutas[Fecha de Llegada],">="&E$3,Rutas[Fecha de Llegada],"<="&E$4) -> 0 | F18: =SUMIFS(Rutas[Gasto comidas ($)],Rutas[Fecha de Llegada],">="&F$3,Rutas[Fecha de Llegada],"<="&F$4) -> 0 | G18: =SUMIFS(Rutas[Gasto comidas ($)],Rutas[Fecha de Llegada],">="&G$3,Rutas[Fecha de Llegada],"<="&G$4) -> 0 | H18: =SUMIFS(Rutas[Gasto comidas ($)],Rutas[Fecha de Llegada],">="&H$3,Rutas[Fecha de Llegada],"<="&H$4) -> 0 | I18: =SUMIFS(Rutas[Gasto comidas ($)],Rutas[Fecha de Llegada],">="&I$3,Rutas[Fecha de Llegada],"<="&I$4) -> 0 | J18: =SUMIFS(Rutas[Gasto comidas ($)],Rutas[Fecha de Llegada],">="&J$3,Rutas[Fecha de Llegada],"<="&J$4) -> 0 | K18: =SUMIFS(Rutas[Gasto comidas ($)],Rutas[Fecha de Llegada],">="&K$3,Rutas[Fecha de Llegada],"<="&K$4) -> 0 | ... O18: =SUMIFS(Rutas[Gasto comidas ($)],Rutas[Fecha de Llegada],">="&O$3,Rutas[Fecha de Llegada],"<="&O$4) -> 0 | P18: =SUM(D18:O18) -> 0 | R18: 2024 | S18: Octubre
C19: Otros Egresos | D19: =SUMIFS(Egresos_varios[Otros Egresos],Egresos_varios[Año],$D$6,Egresos_varios[Mes],D$8) -> 0 | E19: =SUMIFS(Egresos_varios[Otros Egresos],Egresos_varios[Año],$D$6,Egresos_varios[Mes],E$8) -> 0 | F19: =SUMIFS(Egresos_varios[Otros Egresos],Egresos_varios[Año],$D$6,Egresos_varios[Mes],F$8) -> 0 | G19: =SUMIFS(Egresos_varios[Otros Egresos],Egresos_varios[Año],$D$6,Egresos_varios[Mes],G$8) -> 0 | H19: =SUMIFS(Egresos_varios[Otros Egresos],Egresos_varios[Año],$D$6,Egresos_varios[Mes],H$8) -> 0 | I19: =SUMIFS(Egresos_varios[Otros Egresos],Egresos_varios[Año],$D$6,Egresos_varios[Mes],I$8) -> 0 | J19: =SUMIFS(Egresos_varios[Otros Egresos],Egresos_varios[Año],$D$6,Egresos_varios[Mes],J$8) -> 0 | K19: =SUMIFS(Egresos_varios[Otros Egresos],Egresos_varios[Año],$D$6,Egresos_varios[Mes],K$8) -> 0 | ... O19: =SUMIFS(Egresos_varios[Otros Egresos],Egresos_varios[Año],$D$6,Egresos_varios[Mes],O$8) -> 0 | P19: =SUM(D19:O19) -> 0 | R19: 2024 | S19: Noviembre
C20: Utilidad ($) | D20: =D9-D10 -> -9612.744 | E20: =E9-E10 -> -9058.158 | F20: =F9-F10 -> -9461.214 | G20: =G9-G10 -> -11635.2 | H20: =H9-H10 -> -19949.706 | I20: =I9-I10 -> -13746.029 | J20: =J9-J10 -> -6677.352 | K20: =K9-K10 -> -13294.836 | ... P20: =P9-P10 -> -78722.827 | R20: 2024 | S20: Diciembre
C21: Margen (%) | D21: =IFERROR(D20/D9,"") -> -6.9938841 | E21: =IFERROR(E20/E9,"") | F21: =IFERROR(F20/F9,"") | G21: =IFERROR(G20/G9,"") | H21: =IFERROR(H20/H9,"") | I21: =IFERROR(I20/I9,"") | J21: =IFERROR(J20/J9,"") | K21: =IFERROR(K20/K9,"") | ... P21: =IFERROR(P20/P9,"") -> -0.83676536 | R21: 2025 | S21: Enero
R22: 2025 | S22: Febrero
R23: 2025 | S23: Marzo
R24: 2025 | S24: Abril
R25: 2025 | S25: Mayo
R26: 2025 | S26: Junio
R27: 2025 | S27: Julio
R28: 2025 | S28: Agosto
R29: 2025 | S29: Setiembre
R30: 2025 | S30: Octubre
R31: 2025 | S31: Noviembre
R32: 2025 | S32: Diciembre

Sheet Reporte General
B1: REPORTE GENERAL DE INDICADORES POR VEHICULO
F3: =DATE($G$7,MATCH(F9,$F$9:$Q$9,0),1) -> 45658 | G3: =DATE($G$7,MATCH(G9,$F$9:$Q$9,0),1) -> 45689 | H3: =DATE($G$7,MATCH(H9,$F$9:$Q$9,0),1) -> 45717 | I3: =DATE($G$7,MATCH(I9,$F$9:$Q$9,0),1) -> 45748 | J3: =DATE($G$7,MATCH(J9,$F$9:$Q$9,0),1) -> 45778 | K3: =DATE($G$7,MATCH(K9,$F$9:$Q$9,0),1) -> 45809 | L3: =DATE($G$7,MATCH(L9,$F$9:$Q$9,0),1) -> 45839 | M3: =DATE($G$7,MATCH(M9,$F$9:$Q$9,0),1) -> 45870 | ... Q3: =DATE($G$7,MATCH(Q9,$F$9:$Q$9,0),1) -> 45992
F4: =EOMONTH(F3,0) -> 45688 | G4: =EOMONTH(G3,0) -> 45716 | H4: =EOMONTH(H3,0) -> 45747 | I4: =EOMONTH(I3,0) -> 45777 | J4: =EOMONTH(J3,0) -> 45808 | K4: =EOMONTH(K3,0) -> 45838 | L4: =EOMONTH(L3,0) -> 45869 | M4: =EOMONTH(M3,0) -> 45900 | ... Q4: =EOMONTH(Q3,0) -> 46022
C7: Placa de Vehículo | D7: ='KPI Individual'!D2 -> QAA-3164 | E7: =VLOOKUP(D7,Vehiculos[[PLACA]:[MARCA]],3,FALSE) -> SHACMAN | F7: Año | G7: ='Flujo de Caja'!D6 -> 2025
C9: Totales | D9: Unidad | E9: Gráfica | F9: Enero | G9: Febrero | H9: Marzo | I9: Abril | J9: Mayo | K9: Junio | L9: Julio | M9: Agosto | N9: Septiembre | O9: Octubre | P9: Noviembre | Q9: Diciembre | R9: Total
C10: Nro de tanqueos | D10: Und | F10: =COUNTIFS(Rutas[Placa Vehiculo],IF($D$7="","*",$D$7),Rutas[Fecha de Llegada],">="&F$3,Rutas[Fecha de Llegada],"<="&F$4) -> 4 | G10: =COUNTIFS(Rutas[Placa Vehiculo],IF($D$7="","*",$D$7),Rutas[Fecha de Llegada],">="&G$3,Rutas[Fecha de Llegada],"<="&G$4) -> 6 | H10: =COUNTIFS(Rutas[Placa Vehiculo],IF($D$7="","*",$D$7),Rutas[Fecha de Llegada],">="&H$3,Rutas[Fecha de Llegada],"<="&H$4) -> 6 | I10: =COUNTIFS(Rutas[Placa Vehiculo],IF($D$7="","*",$D$7),Rutas[Fecha de Llegada],">="&I$3,Rutas[Fecha de Llegada],"<="&I$4) -> 4 | J10: =COUNTIFS(Rutas[Placa Vehiculo],IF($D$7="","*",$D$7),Rutas[Fecha de Llegada],">="&J$3,Rutas[Fecha de Llegada],"<="&J$4) -> 6 | K10: =COUNTIFS(Rutas[Placa Vehiculo],IF($D$7="","*",$D$7),Rutas[Fecha de Llegada],">="&K$3,Rutas[Fecha de Llegada],"<="&K$4) -> 4 | L10: =COUNTIFS(Rutas[Placa Vehiculo],IF($D$7="","*",$D$7),Rutas[Fecha de Llegada],">="&L$3,Rutas[Fecha de Llegada],"<="&L$4) -> 4 | M10: =COUNTIFS(Rutas[Placa Vehiculo],IF($D$7="","*",$D$7),Rutas[Fecha de Llegada],">="&M$3,Rutas[Fecha de Llegada],"<="&M$4) -> 6 | ... Q10: =COUNTIFS(Rutas[Placa Vehiculo],IF($D$7="","*",$D$7),Rutas[Fecha de Llegada],">="&Q$3,Rutas[Fecha de Llegada],"<="&Q$4) -> 3 | R10: =SUM(F10:Q10) -> 53
C11: Kms Recorridos | D11: Km | F11: =SUMIFS(Rutas[Kms Recorridos],Rutas[Placa Vehiculo],IF($D$7="","*",$D$7),Rutas[Fecha de Llegada],">="&F$3,Rutas[Fecha de Llegada],"<="&F$4) -> 774 | G11: =SUMIFS(Rutas[Kms Recorridos],Rutas[Placa Vehiculo],IF($D$7="","*",$D$7),Rutas[Fecha de Llegada],">="&G$3,Rutas[Fecha de Llegada],"<="&G$4) -> 453 | H11: =SUMIFS(Rutas[Kms Recorridos],Rutas[Placa Vehiculo],IF($D$7="","*",$D$7),Rutas[Fecha de Llegada],">="&H$3,Rutas[Fecha de Llegada],"<="&H$4) -> 1637 | I11: =SUMIFS(Rutas[Kms Recorridos],Rutas[Placa Vehiculo],IF($D$7="","*",$D$7),Rutas[Fecha de Llegada],">="&I$3,Rutas[Fecha de Llegada],"<="&I$4) -> 1811 | J11: =SUMIFS(Rutas[Kms Recorridos],Rutas[Placa Vehiculo],IF($D$7="","*",$D$7),Rutas[Fecha de Llegada],">="&J$3,Rutas[Fecha de Llegada],"<="&J$4) -> 3263 | K11: =SUMIFS(Rutas[Kms Recorridos],Rutas[Placa Vehiculo],IF($D$7="","*",$D$7),Rutas[Fecha de Llegada],">="&K$3,Rutas[Fecha de Llegada],"<="&K$4) -> 1789 | L11: =SUMIFS(Rutas[Kms Recorridos],Rutas[Placa Vehiculo],IF($D$7="","*",$D$7),Rutas[Fecha de Llegada],">="&L$3,Rutas[Fecha de Llegada],"<="&L$4) -> 2334 | M11: =SUMIFS(Rutas[Kms Recorridos],Rutas[Placa Vehiculo],IF($D$7="","*",$D$7),Rutas[Fecha de Llegada],">="&M$3,Rutas[Fecha de Llegada],"<="&M$4) -> 2333 | ... Q11: =SUMIFS(Rutas[Kms Recorridos],Rutas[Placa Vehiculo],IF($D$7="","*",$D$7),Rutas[Fecha de Llegada],">="&Q$3,Rutas[Fecha de Llegada],"<="&Q$4) -> 2112 | R11: =SUM(F11:Q11) -> 22844
C12: Ingresos | D12: $ | F12: =SUMIFS(Rutas[Ingreso Total ($)],Rutas[Placa Vehiculo],IF($D$7="","*",$D$7),Rutas[Fecha de Llegada],">="&F$3,Rutas[Fecha de Llegada],"<="&F$4) -> 0 | G12: =SUMIFS(Rutas[Ingreso Total ($)],Rutas[Placa Vehiculo],IF($D$7="","*",$D$7),Rutas[Fecha de Llegada],">="&G$3,Rutas[Fecha de Llegada],"<="&G$4) -> 0 | H12: =SUMIFS(Rutas[Ingreso Total ($)],Rutas[Placa Vehiculo],IF($D$7="","*",$D$7),Rutas[Fecha de Llegada],">="&H$3,Rutas[Fecha de Llegada],"<="&H$4) -> 0 | I12: =SUMIFS(Rutas[Ingreso Total ($)],Rutas[Placa Vehiculo],IF($D$7="","*",$D$7),Rutas[Fecha de Llegada],">="&I$3,Rutas[Fecha de Llegada],"<="&I$4) -> 0 | J12: =SUMIFS(Rutas[Ingreso Total ($)],Rutas[Placa Vehiculo],IF($D$7="","*",$D$7),Rutas[Fecha de Llegada],">="&J$3,Rutas[Fecha de Llegada],"<="&J$4) -> 0 | K12: =SUMIFS(Rutas[Ingreso Total ($)],Rutas[Placa Vehiculo],IF($D$7="","*",$D$7),Rutas[Fecha de Llegada],">="&K$3,Rutas[Fecha de Llegada],"<="&K$4) -> 0 | L12: =SUMIFS(Rutas[Ingreso Total ($)],Rutas[Placa Vehiculo],IF($D$7="","*",$D$7),Rutas[Fecha de Llegada],">="&L$3,Rutas[Fecha de Llegada],"<="&L$4) -> 0 | M12: =SUMIFS(Rutas[Ingreso Total ($)],Rutas[Placa Vehiculo],IF($D$7="","*",$D$7),Rutas[Fecha de Llegada],">="&M$3,Rutas[Fecha de Llegada],"<="&M$4) -> 0 | ... Q12: =SUMIFS(Rutas[Ingreso Total ($)],Rutas[Placa Vehiculo],IF($D$7="","*",$D$7),Rutas[Fecha de Llegada],">="&Q$3,Rutas[Fecha de Llegada],"<="&Q$4) -> 1605.12 | R12: =SUM(F12:Q12) -> 4857.16
C13: Gastos | D13: $ | F13: =SUMIFS(Rutas[Gasto Total ($)],Rutas[Placa Vehiculo],IF($D$7="","*",$D$7),Rutas[Fecha de Llegada],">="&F$3,Rutas[Fecha de Llegada],"<="&F$4) -> 597.402 | G13: =SUMIFS(Rutas[Gasto Total ($)],Rutas[Placa Vehiculo],IF($D$7="","*",$D$7),Rutas[Fecha de Llegada],">="&G$3,Rutas[Fecha de Llegada],"<="&G$4) -> 1156.662 | H13: =SUMIFS(Rutas[Gasto Total ($)],Rutas[Placa Vehiculo],IF($D$7="","*",$D$7),Rutas[Fecha de Llegada],">="&H$3,Rutas[Fecha de Llegada],"<="&H$4) -> 1204.308 | I13: =SUMIFS(Rutas[Gasto Total ($)],Rutas[Placa Vehiculo],IF($D$7="","*",$D$7),Rutas[Fecha de Llegada],">="&I$3,Rutas[Fecha de Llegada],"<="&I$4) -> 652.14 | J13: =SUMIFS(Rutas[Gasto Total ($)],Rutas[Placa Vehiculo],IF($D$7="","*",$D$7),Rutas[Fecha de Llegada],">="&J$3,Rutas[Fecha de Llegada],"<="&J$4) -> 833.04 | K13: =SUMIFS(Rutas[Gasto Total ($)],Rutas[Placa Vehiculo],IF($D$7="","*",$D$7),Rutas[Fecha de Llegada],">="&K$3,Rutas[Fecha de Llegada],"<="&K$4) -> 602.874 | L13: =SUMIFS(Rutas[Gasto Total ($)],Rutas[Placa Vehiculo],IF($D$7="","*",$D$7),Rutas[Fecha de Llegada],">="&L$3,Rutas[Fecha de Llegada],"<="&L$4) -> 612.504 | M13: =SUMIFS(Rutas[Gasto Total ($)],Rutas[Placa Vehiculo],IF($D$7="","*",$D$7),Rutas[Fecha de Llegada],">="&M$3,Rutas[Fecha de Llegada],"<="&M$4) -> 853.11 | ... Q13: =SUMIFS(Rutas[Gasto Total ($)],Rutas[Placa Vehiculo],IF($D$7="","*",$D$7),Rutas[Fecha de Llegada],">="&Q$3,Rutas[Fecha de Llegada],"<="&Q$4) -> 879.9 | R13: =SUM(F13:Q13) -> 9963.14
C14: Cantidad de galones cargados | D14: gal | F14: =SUMIFS(Rutas[Volumen de Combustible (gal)],Rutas[Placa Vehiculo],IF($D$7="","*",$D$7),Rutas[Fecha de Llegada],">="&F$3,Rutas[Fecha de Llegada],"<="&F$4) -> 331.89 | G14: =SUMIFS(Rutas[Volumen de Combustible (gal)],Rutas[Placa Vehiculo],IF($D$7="","*",$D$7),Rutas[Fecha de Llegada],">="&G$3,Rutas[Fecha de Llegada],"<="&G$4) -> 642.59 | H14: =SUMIFS(Rutas[Volumen de Combustible (gal)],Rutas[Placa Vehiculo],IF($D$7="","*",$D$7),Rutas[Fecha de Llegada],">="&H$3,Rutas[Fecha de Llegada],"<="&H$4) -> 669.06 | I14: =SUMIFS(Rutas[Volumen de Combustible (gal)],Rutas[Placa Vehiculo],IF($D$7="","*",$D$7),Rutas[Fecha de Llegada],">="&I$3,Rutas[Fecha de Llegada],"<="&I$4) -> 362.3 | J14: =SUMIFS(Rutas[Volumen de Combustible (gal)],Rutas[Placa Vehiculo],IF($D$7="","*",$D$7),Rutas[Fecha de Llegada],">="&J$3,Rutas[Fecha de Llegada],"<="&J$4) -> 462.8 | K14: =SUMIFS(Rutas[Volumen de Combustible (gal)],Rutas[Placa Vehiculo],IF($D$7="","*",$D$7),Rutas[Fecha de Llegada],">="&K$3,Rutas[Fecha de Llegada],"<="&K$4) -> 334.93 | L14: =SUMIFS(Rutas[Volumen de Combustible (gal)],Rutas[Placa Vehiculo],IF($D$7="","*",$D$7),Rutas[Fecha de Llegada],">="&L$3,Rutas[Fecha de Llegada],"<="&L$4) -> 340.28 | M14: =SUMIFS(Rutas[Volumen de Combustible (gal)],Rutas[Placa Vehiculo],IF($D$7="","*",$D$7),Rutas[Fecha de Llegada],">="&M$3,Rutas[Fecha de Llegada],"<="&M$4) -> 473.95 | ... Q14: =SUMIFS(Rutas[Volumen de Combustible (gal)],Rutas[Placa Vehiculo],IF($D$7="","*",$D$7),Rutas[Fecha de Llegada],">="&Q$3,Rutas[Fecha de Llegada],"<="&Q$4) -> 314.25 | R14: =SUM(F14:Q14) -> 4887.5
C15: Carga Transportada | D15: Kg | F15: =SUMIFS(Rutas[Peso de carga (BLS)],Rutas[Placa Vehiculo],IF($D$7="","*",$D$7),Rutas[Fecha de Llegada],">="&F$3,Rutas[Fecha de Llegada],"<="&F$4) -> 0 | G15: =SUMIFS(Rutas[Peso de carga (BLS)],Rutas[Placa Vehiculo],IF($D$7="","*",$D$7),Rutas[Fecha de Llegada],">="&G$3,Rutas[Fecha de Llegada],"<="&G$4) -> 0 | H15: =SUMIFS(Rutas[Peso de carga (BLS)],Rutas[Placa Vehiculo],IF($D$7="","*",$D$7),Rutas[Fecha de Llegada],">="&H$3,Rutas[Fecha de Llegada],"<="&H$4) -> 0 | I15: =SUMIFS(Rutas[Peso de carga (BLS)],Rutas[Placa Vehiculo],IF($D$7="","*",$D$7),Rutas[Fecha de Llegada],">="&I$3,Rutas[Fecha de Llegada],"<="&I$4) -> 0 | J15: =SUMIFS(Rutas[Peso de carga (BLS)],Rutas[Placa Vehiculo],IF($D$7="","*",$D$7),Rutas[Fecha de Llegada],">="&J$3,Rutas[Fecha de Llegada],"<="&J$4) -> 0 | K15: =SUMIFS(Rutas[Peso de carga (BLS)],Rutas[Placa Vehiculo],IF($D$7="","*",$D$7),Rutas[Fecha de Llegada],">="&K$3,Rutas[Fecha de Llegada],"<="&K$4) -> 0 | L15: =SUMIFS(Rutas[Peso de carga (BLS)],Rutas[Placa Vehiculo],IF($D$7="","*",$D$7),Rutas[Fecha de Llegada],">="&L$3,Rutas[Fecha de Llegada],"<="&L$4) -> 0 | M15: =SUMIFS(Rutas[Peso de carga (BLS)],Rutas[Placa Vehiculo],IF($D$7="","*",$D$7),Rutas[Fecha de Llegada],">="&M$3,Rutas[Fecha de Llegada],"<="&M$4) -> 0 | ... Q15: =SUMIFS(Rutas[Peso de carga (BLS)],Rutas[Placa Vehiculo],IF($D$7="","*",$D$7),Rutas[Fecha de Llegada],">="&Q$3,Rutas[Fecha de Llegada],"<="&Q$4) -> 0 | R15: =SUM(F15:Q15) -> 0
C16: Tiempo Total de operación | D16: Horas | F16: =F17-F18-F19 -> 488 | G16: =G17-G18-G19 -> 455 | H16: =H17-H18-H19 -> 217 | I16: =I17-I18-I19 -> 284 | J16: =J17-J18-J19 -> 317 | K16: =K17-K18-K19 -> 298 | L16: =L17-L18-L19 -> 220 | M16: =M17-M18-M19 -> 310 | ... Q16: =Q17-Q18-Q19 -> 203 | R16: =SUM(F16:Q16) -> 3711
C17: Tiempo Total de operación del equipo | D17: Horas | F17: =SUMIFS(Rutas[Horas trabjadas],Rutas[Placa Vehiculo],IF($D$7="","*",$D$7),Rutas[Fecha de Llegada],">="&F$3,Rutas[Fecha de Llegada],"<="&F$4) -> 490 | G17: =SUMIFS(Rutas[Horas trabjadas],Rutas[Placa Vehiculo],IF($D$7="","*",$D$7),Rutas[Fecha de Llegada],">="&G$3,Rutas[Fecha de Llegada],"<="&G$4) -> 457 | H17: =SUMIFS(Rutas[Horas trabjadas],Rutas[Placa Vehiculo],IF($D$7="","*",$D$7),Rutas[Fecha de Llegada],">="&H$3,Rutas[Fecha de Llegada],"<="&H$4) -> 217 | I17: =SUMIFS(Rutas[Horas trabjadas],Rutas[Placa Vehiculo],IF($D$7="","*",$D$7),Rutas[Fecha de Llegada],">="&I$3,Rutas[Fecha de Llegada],"<="&I$4) -> 284 | J17: =SUMIFS(Rutas[Horas trabjadas],Rutas[Placa Vehiculo],IF($D$7="","*",$D$7),Rutas[Fecha de Llegada],">="&J$3,Rutas[Fecha de Llegada],"<="&J$4) -> 317 | K17: =SUMIFS(Rutas[Horas trabjadas],Rutas[Placa Vehiculo],IF($D$7="","*",$D$7),Rutas[Fecha de Llegada],">="&K$3,Rutas[Fecha de Llegada],"<="&K$4) -> 300 | L17: =SUMIFS(Rutas[Horas trabjadas],Rutas[Placa Vehiculo],IF($D$7="","*",$D$7),Rutas[Fecha de Llegada],">="&L$3,Rutas[Fecha de Llegada],"<="&L$4) -> 220 | M17: =SUMIFS(Rutas[Horas trabjadas],Rutas[Placa Vehiculo],IF($D$7="","*",$D$7),Rutas[Fecha de Llegada],">="&M$3,Rutas[Fecha de Llegada],"<="&M$4) -> 310 | ... Q17: =SUMIFS(Rutas[Horas trabjadas],Rutas[Placa Vehiculo],IF($D$7="","*",$D$7),Rutas[Fecha de Llegada],">="&Q$3,Rutas[Fecha de Llegada],"<="&Q$4) -> 210 | R17: =SUM(F17:Q17) -> 3726
C18: Tiempo TotaL por mantenimiento preventivo | D18: Horas | F18: =SUMIFS(Mantenimiento[Tiempo MTO PTVO],Mantenimiento[Placa Vehiculo],IF($D$7="","*",$D$7),Mantenimiento[Fecha Salida],">="&F$3,Mantenimiento[Fecha Salida],"<="&F$4) -> 2 | G18: =SUMIFS(Mantenimiento[Tiempo MTO PTVO],Mantenimiento[Placa Vehiculo],IF($D$7="","*",$D$7),Mantenimiento[Fecha Salida],">="&G$3,Mantenimiento[Fecha Salida],"<="&G$4) -> 2 | H18: =SUMIFS(Mantenimiento[Tiempo MTO PTVO],Mantenimiento[Placa Vehiculo],IF($D$7="","*",$D$7),Mantenimiento[Fecha Salida],">="&H$3,Mantenimiento[Fecha Salida],"<="&H$4) -> 0 | I18: =SUMIFS(Mantenimiento[Tiempo MTO PTVO],Mantenimiento[Placa Vehiculo],IF($D$7="","*",$D$7),Mantenimiento[Fecha Salida],">="&I$3,Mantenimiento[Fecha Salida],"<="&I$4) -> 0 | J18: =SUMIFS(Mantenimiento[Tiempo MTO PTVO],Mantenimiento[Placa Vehiculo],IF($D$7="","*",$D$7),Mantenimiento[Fecha Salida],">="&J$3,Mantenimiento[Fecha Salida],"<="&J$4) -> 0 | K18: =SUMIFS(Mantenimiento[Tiempo MTO PTVO],Mantenimiento[Placa Vehiculo],IF($D$7="","*",$D$7),Mantenimiento[Fecha Salida],">="&K$3,Mantenimiento[Fecha Salida],"<="&K$4) -> 2 | L18: =SUMIFS(Mantenimiento[Tiempo MTO PTVO],Mantenimiento[Placa Vehiculo],IF($D$7="","*",$D$7),Mantenimiento[Fecha Salida],">="&L$3,Mantenimiento[Fecha Salida],"<="&L$4) -> 0 | M18: =SUMIFS(Mantenimiento[Tiempo MTO PTVO],Mantenimiento[Placa Vehiculo],IF($D$7="","*",$D$7),Mantenimiento[Fecha Salida],">="&M$3,Mantenimiento[Fecha Salida],"<="&M$4) -> 0 | ... Q18: =SUMIFS(Mantenimiento[Tiempo MTO PTVO],Mantenimiento[Placa Vehiculo],IF($D$7="","*",$D$7),Mantenimiento[Fecha Salida],">="&Q$3,Mantenimiento[Fecha Salida],"<="&Q$4) -> 0 | R18: =SUM(F18:Q18) -> 8
C19: Tiempo Total por reparación | D19: Horas | F19: =SUMIFS(Mantenimiento[Tiempo MTO CRTVO],Mantenimiento[Placa Vehiculo],IF($D$7="","*",$D$7),Mantenimiento[Fecha Salida],">="&F$3,Mantenimiento[Fecha Salida],"<="&F$4) -> 0 | G19: =SUMIFS(Mantenimiento[Tiempo MTO CRTVO],Mantenimiento[Placa Vehiculo],IF($D$7="","*",$D$7),Mantenimiento[Fecha Salida],">="&G$3,Mantenimiento[Fecha Salida],"<="&G$4) -> 0 | H19: =SUMIFS(Mantenimiento[Tiempo MTO CRTVO],Mantenimiento[Placa Vehiculo],IF($D$7="","*",$D$7),Mantenimiento[Fecha Salida],">="&H$3,Mantenimiento[Fecha Salida],"<="&H$4) -> 0 | I19: =SUMIFS(Mantenimiento[Tiempo MTO CRTVO],Mantenimiento[Placa Vehiculo],IF($D$7="","*",$D$7),Mantenimiento[Fecha Salida],">="&I$3,Mantenimiento[Fecha Salida],"<="&I$4) -> 0 | J19: =SUMIFS(Mantenimiento[Tiempo MTO CRTVO],Mantenimiento[Placa Vehiculo],IF($D$7="","*",$D$7),Mantenimiento[Fecha Salida],">="&J$3,Mantenimiento[Fecha Salida],"<="&J$4) -> 0 | K19: =SUMIFS(Mantenimiento[Tiempo MTO CRTVO],Mantenimiento[Placa Vehiculo],IF($D$7="","*",$D$7),Mantenimiento[Fecha Salida],">="&K$3,Mantenimiento[Fecha Salida],"<="&K$4) -> 0 | L19: =SUMIFS(Mantenimiento[Tiempo MTO CRTVO],Mantenimiento[Placa Vehiculo],IF($D$7="","*",$D$7),Mantenimiento[Fecha Salida],">="&L$3,Mantenimiento[Fecha Salida],"<="&L$4) -> 0 | M19: =SUMIFS(Mantenimiento[Tiempo MTO CRTVO],Mantenimiento[Placa Vehiculo],IF($D$7="","*",$D$7),Mantenimiento[Fecha Salida],">="&M$3,Mantenimiento[Fecha Salida],"<="&M$4) -> 0 | ... Q19: =SUMIFS(Mantenimiento[Tiempo MTO CRTVO],Mantenimiento[Placa Vehiculo],IF($D$7="","*",$D$7),Mantenimiento[Fecha Salida],">="&Q$3,Mantenimiento[Fecha Salida],"<="&Q$4) -> 7 | R19: =SUM(F19:Q19) -> 7
C20: Total de Mantenimientos | D20: Und | F20: =SUM(F21:F22) -> 1 | G20: =SUM(G21:G22) -> 1 | H20: =SUM(H21:H22) -> 0 | I20: =SUM(I21:I22) -> 0 | J20: =SUM(J21:J22) -> 0 | K20: =SUM(K21:K22) -> 1 | L20: =SUM(L21:L22) -> 0 | M20: =SUM(M21:M22) -> 0 | ... Q20: =SUM(Q21:Q22) -> 3 | R20: =SUM(F20:Q20) -> 7
C21: Nro Mantenimientos Preventivos | D21: und | F21: =COUNTIFS(Mantenimiento[Tipo],"Preventivo",Mantenimiento[Placa Vehiculo],IF($D$7="","*",$D$7),Mantenimiento[Fecha Entrada],">="&F$3,Mantenimiento[Fecha Entrada],"<="&F$4) -> 1 | G21: =COUNTIFS(Mantenimiento[Tipo],"Preventivo",Mantenimiento[Placa Vehiculo],IF($D$7="","*",$D$7),Mantenimiento[Fecha Entrada],">="&G$3,Mantenimiento[Fecha Entrada],"<="&G$4) -> 1 | H21: =COUNTIFS(Mantenimiento[Tipo],"Preventivo",Mantenimiento[Placa Vehiculo],IF($D$7="","*",$D$7),Mantenimiento[Fecha Entrada],">="&H$3,Mantenimiento[Fecha Entrada],"<="&H$4) -> 0 | I21: =COUNTIFS(Mantenimiento[Tipo],"Preventivo",Mantenimiento[Placa Vehiculo],IF($D$7="","*",$D$7),Mantenimiento[Fecha Entrada],">="&I$3,Mantenimiento[Fecha Entrada],"<="&I$4) -> 0 | J21: =COUNTIFS(Mantenimiento[Tipo],"Preventivo",Mantenimiento[Placa Vehiculo],IF($D$7="","*",$D$7),Mantenimiento[Fecha Entrada],">="&J$3,Mantenimiento[Fecha Entrada],"<="&J$4) -> 0 | K21: =COUNTIFS(Mantenimiento[Tipo],"Preventivo",Mantenimiento[Placa Vehiculo],IF($D$7="","*",$D$7),Mantenimiento[Fecha Entrada],">="&K$3,Mantenimiento[Fecha Entrada],"<="&K$4) -> 1 | L21: =COUNTIFS(Mantenimiento[Tipo],"Preventivo",Mantenimiento[Placa Vehiculo],IF($D$7="","*",$D$7),Mantenimiento[Fecha Entrada],">="&L$3,Mantenimiento[Fecha Entrada],"<="&L$4) -> 0 | M21: =COUNTIFS(Mantenimiento[Tipo],"Preventivo",Mantenimiento[Placa Vehiculo],IF($D$7="","*",$D$7),Mantenimiento[Fecha Entrada],">="&M$3,Mantenimiento[Fecha Entrada],"<="&M$4) -> 0 | ... Q21: =COUNTIFS(Mantenimiento[Tipo],"Preventivo",Mantenimiento[Placa Vehiculo],IF($D$7="","*",$D$7),Mantenimiento[Fecha Entrada],">="&Q$3,Mantenimiento[Fecha Entrada],"<="&Q$4) -> 0 | R21: =SUM(F21:Q21) -> 4
C22: Nro Mantenimientos Correctivos | D22: und | F22: =COUNTIFS(Mantenimiento[Tipo],"Correctivo",Mantenimiento[Placa Vehiculo],IF($D$7="","*",$D$7),Mantenimiento[Fecha Entrada],">="&F$3,Mantenimiento[Fecha Entrada],"<="&F$4) -> 0 | G22: =COUNTIFS(Mantenimiento[Tipo],"Correctivo",Mantenimiento[Placa Vehiculo],IF($D$7="","*",$D$7),Mantenimiento[Fecha Entrada],">="&G$3,Mantenimiento[Fecha Entrada],"<="&G$4) -> 0 | H22: =COUNTIFS(Mantenimiento[Tipo],"Correctivo",Mantenimiento[Placa Vehiculo],IF($D$7="","*",$D$7),Mantenimiento[Fecha Entrada],">="&H$3,Mantenimiento[Fecha Entrada],"<="&H$4) -> 0 | I22: =COUNTIFS(Mantenimiento[Tipo],"Correctivo",Mantenimiento[Placa Vehiculo],IF($D$7="","*",$D$7),Mantenimiento[Fecha Entrada],">="&I$3,Mantenimiento[Fecha Entrada],"<="&I$4) -> 0 | J22: =COUNTIFS(Mantenimiento[Tipo],"Correctivo",Mantenimiento[Placa Vehiculo],IF($D$7="","*",$D$7),Mantenimiento[Fecha Entrada],">="&J$3,Mantenimiento[Fecha Entrada],"<="&J$4) -> 0 | K22: =COUNTIFS(Mantenimiento[Tipo],"Correctivo",Mantenimiento[Placa Vehiculo],IF($D$7="","*",$D$7),Mantenimiento[Fecha Entrada],">="&K$3,Mantenimiento[Fecha Entrada],"<="&K$4) -> 0 | L22: =COUNTIFS(Mantenimiento[Tipo],"Correctivo",Mantenimiento[Placa Vehiculo],IF($D$7="","*",$D$7),Mantenimiento[Fecha Entrada],">="&L$3,Mantenimiento[Fecha Entrada],"<="&L$4) -> 0 | M22: =COUNTIFS(Mantenimiento[Tipo],"Correctivo",Mantenimiento[Placa Vehiculo],IF($D$7="","*",$D$7),Mantenimiento[Fecha Entrada],">="&M$3,Mantenimiento[Fecha Entrada],"<="&M$4) -> 0 | ... Q22: =COUNTIFS(Mantenimiento[Tipo],"Correctivo",Mantenimiento[Placa Vehiculo],IF($D$7="","*",$D$7),Mantenimiento[Fecha Entrada],">="&Q$3,Mantenimiento[Fecha Entrada],"<="&Q$4) -> 3 | R22: =SUM(F22:Q22) -> 3
C24: Indicadores de Mantenimiento | D24: Unidad | E24: Gráfica | F24: Enero | G24: Febrero | H24: Marzo | I24: Abril | J24: Mayo | K24: Junio | L24: Julio | M24: Agosto | N24: Septiembre | O24: Octubre | P24: Noviembre | Q24: Diciembre | R24: Total
C25: Kms Recorridos |horas de trabajo | D25: Kms|Hrs | F25: =SUMIFS(Rutas[Kms Recorridos],Rutas[Placa Vehiculo],IF($D$7="","*",$D$7),Rutas[Fecha de Llegada],">="&F$3,Rutas[Fecha de Llegada],"<="&F$4) -> 774 | G25: =SUMIFS(Rutas[Kms Recorridos],Rutas[Placa Vehiculo],IF($D$7="","*",$D$7),Rutas[Fecha de Llegada],">="&G$3,Rutas[Fecha de Llegada],"<="&G$4) -> 453 | H25: =SUMIFS(Rutas[Kms Recorridos],Rutas[Placa Vehiculo],IF($D$7="","*",$D$7),Rutas[Fecha de Llegada],">="&H$3,Rutas[Fecha de Llegada],"<="&H$4) -> 1637 | I25: =SUMIFS(Rutas[Kms Recorridos],Rutas[Placa Vehiculo],IF($D$7="","*",$D$7),Rutas[Fecha de Llegada],">="&I$3,Rutas[Fecha de Llegada],"<="&I$4) -> 1811 | J25: =SUMIFS(Rutas[Kms Recorridos],Rutas[Placa Vehiculo],IF($D$7="","*",$D$7),Rutas[Fecha de Llegada],">="&J$3,Rutas[Fecha de Llegada],"<="&J$4) -> 3263 | K25: =SUMIFS(Rutas[Kms Recorridos],Rutas[Placa Vehiculo],IF($D$7="","*",$D$7),Rutas[Fecha de Llegada],">="&K$3,Rutas[Fecha de Llegada],"<="&K$4) -> 1789 | L25: =SUMIFS(Rutas[Kms Recorridos],Rutas[Placa Vehiculo],IF($D$7="","*",$D$7),Rutas[Fecha de Llegada],">="&L$3,Rutas[Fecha de Llegada],"<="&L$4) -> 2334 | M25: =SUMIFS(Rutas[Kms Recorridos],Rutas[Placa Vehiculo],IF($D$7="","*",$D$7),Rutas[Fecha de Llegada],">="&M$3,Rutas[Fecha de Llegada],"<="&M$4) -> 2333 | ... Q25: =SUMIFS(Rutas[Kms Recorridos],Rutas[Placa Vehiculo],IF($D$7="","*",$D$7),Rutas[Fecha de Llegada],">="&Q$3,Rutas[Fecha de Llegada],"<="&Q$4) -> 2112 | R25: =SUM(F25:Q25) -> 22844
C26: Cantidad de galones cargados | D26: Gal | F26: =SUMIFS(Rutas[Volumen de Combustible (gal)],Rutas[Placa Vehiculo],IF($D$7="","*",$D$7),Rutas[Fecha de Llegada],">="&F$3,Rutas[Fecha de Llegada],"<="&F$4) -> 331.89 | G26: =SUMIFS(Rutas[Volumen de Combustible (gal)],Rutas[Placa Vehiculo],IF($D$7="","*",$D$7),Rutas[Fecha de Llegada],">="&G$3,Rutas[Fecha de Llegada],"<="&G$4) -> 642.59 | H26: =SUMIFS(Rutas[Volumen de Combustible (gal)],Rutas[Placa Vehiculo],IF($D$7="","*",$D$7),Rutas[Fecha de Llegada],">="&H$3,Rutas[Fecha de Llegada],"<="&H$4) -> 669.06 | I26: =SUMIFS(Rutas[Volumen de Combustible (gal)],Rutas[Placa Vehiculo],IF($D$7="","*",$D$7),Rutas[Fecha de Llegada],">="&I$3,Rutas[Fecha de Llegada],"<="&I$4) -> 362.3 | J26: =SUMIFS(Rutas[Volumen de Combustible (gal)],Rutas[Placa Vehiculo],IF($D$7="","*",$D$7),Rutas[Fecha de Llegada],">="&J$3,Rutas[Fecha de Llegada],"<="&J$4) -> 462.8 | K26: =SUMIFS(Rutas[Volumen de Combustible (gal)],Rutas[Placa Vehiculo],IF($D$7="","*",$D$7),Rutas[Fecha de Llegada],">="&K$3,Rutas[Fecha de Llegada],"<="&K$4) -> 334.93 | L26: =SUMIFS(Rutas[Volumen de Combustible (gal)],Rutas[Placa Vehiculo],IF($D$7="","*",$D$7),Rutas[Fecha de Llegada],">="&L$3,Rutas[Fecha de Llegada],"<="&L$4) -> 340.28 | M26: =SUMIFS(Rutas[Volumen de Combustible (gal)],Rutas[Placa Vehiculo],IF($D$7="","*",$D$7),Rutas[Fecha de Llegada],">="&M$3,Rutas[Fecha de Llegada],"<="&M$4) -> 473.95 | ... Q26: =SUMIFS(Rutas[Volumen de Combustible (gal)],Rutas[Placa Vehiculo],IF($D$7="","*",$D$7),Rutas[Fecha de Llegada],">="&Q$3,Rutas[Fecha de Llegada],"<="&Q$4) -> 314.25 | R26: =SUM(F26:Q26) -> 4887.5
C27: (Kms|Hrs) por galón de combustible | D27: Km/Gal | F27: =IFERROR(F11/F14,0) -> 2.332098 | G27: =IFERROR(G11/G14,0) -> 0.70495962 | H27: =IFERROR(H11/H14,0) -> 2.4467163 | I27: =IFERROR(I11/I14,0) -> 4.9986199 | J27: =IFERROR(J11/J14,0) -> 7.0505618 | K27: =IFERROR(K11/K14,0) -> 5.3414146 | L27: =IFERROR(L11/L14,0) -> 6.8590572 | M27: =IFERROR(M11/M14,0) -> 4.9224602 | ... R27: =IFERROR(R11/R14,0) -> 4.6739642
C28: (Kms |Hrs) por tanqueo | D28: Km/tanqueo | F28: =IFERROR(F11/F10,0) -> 193.5 | G28: =IFERROR(G11/G10,0) -> 75.5 | H28: =IFERROR(H11/H10,0) -> 272.83333 | I28: =IFERROR(I11/I10,0) -> 452.75 | J28: =IFERROR(J11/J10,0) -> 543.83333 | K28: =IFERROR(K11/K10,0) -> 447.25 | L28: =IFERROR(L11/L10,0) -> 583.5 | M28: =IFERROR(M11/M10,0) -> 388.83333 | ... R28: =IFERROR(R11/R10,0) -> 431.01887
C29: (Kms|Hrs) por mantenim. | D29: Km/Mnnto | F29: =SUMIFS(Mantenimiento[KM Entre MTO],Mantenimiento[Placa Vehiculo],IF($D$7="","*",$D$7),Mantenimiento[Fecha Salida],">="&F$3,Mantenimiento[Fecha Salida],"<="&F$4) -> 8039 | G29: =SUMIFS(Mantenimiento[KM Entre MTO],Mantenimiento[Placa Vehiculo],IF($D$7="","*",$D$7),Mantenimiento[Fecha Salida],">="&G$3,Mantenimiento[Fecha Salida],"<="&G$4) -> 7836 | H29: =SUMIFS(Mantenimiento[KM Entre MTO],Mantenimiento[Placa Vehiculo],IF($D$7="","*",$D$7),Mantenimiento[Fecha Salida],">="&H$3,Mantenimiento[Fecha Salida],"<="&H$4) -> 0 | I29: =SUMIFS(Mantenimiento[KM Entre MTO],Mantenimiento[Placa Vehiculo],IF($D$7="","*",$D$7),Mantenimiento[Fecha Salida],">="&I$3,Mantenimiento[Fecha Salida],"<="&I$4) -> 0 | J29: =SUMIFS(Mantenimiento[KM Entre MTO],Mantenimiento[Placa Vehiculo],IF($D$7="","*",$D$7),Mantenimiento[Fecha Salida],">="&J$3,Mantenimiento[Fecha Salida],"<="&J$4) -> 0 | K29: =SUMIFS(Mantenimiento[KM Entre MTO],Mantenimiento[Placa Vehiculo],IF($D$7="","*",$D$7),Mantenimiento[Fecha Salida],">="&K$3,Mantenimiento[Fecha Salida],"<="&K$4) -> 8000 | L29: =SUMIFS(Mantenimiento[KM Entre MTO],Mantenimiento[Placa Vehiculo],IF($D$7="","*",$D$7),Mantenimiento[Fecha Salida],">="&L$3,Mantenimiento[Fecha Salida],"<="&L$4) -> 0 | M29: =SUMIFS(Mantenimiento[KM Entre MTO],Mantenimiento[Placa Vehiculo],IF($D$7="","*",$D$7),Mantenimiento[Fecha Salida],">="&M$3,Mantenimiento[Fecha Salida],"<="&M$4) -> 0 | ... Q29: =SUMIFS(Mantenimiento[KM Entre MTO],Mantenimiento[Placa Vehiculo],IF($D$7="","*",$D$7),Mantenimiento[Fecha Salida],">="&Q$3,Mantenimiento[Fecha Salida],"<="&Q$4) -> 0 | R29: =AVERAGE(F29:Q29) -> 2650.25
C30: Tiempo medio entre Fallas(MTBF) | D30: Horas | F30: =F16/F34 -> #DIV/0! | G30: =G16/G34 -> #DIV/0! | H30: =H16/H34 -> #DIV/0! | I30: =I16/I34 -> #DIV/0! | J30: =J16/J34 -> #DIV/0! | K30: =K16/K34 -> #DIV/0! | L30: =L16/L34 -> #DIV/0! | M30: =M16/M34 -> #DIV/0! | ... Q30: =Q16/Q34 -> 67.666667 | R30: =IFERROR(F30/Q30,0) -> 0
C31: Tiempo medio por reparación (MMTR) | D31: Horas | F31: =IFERROR(F19/F22,0) -> 0 | G31: =IFERROR(G19/G22,0) -> 0 | H31: =IFERROR(H19/H22,0) -> 0 | I31: =IFERROR(I19/I22,0) -> 0 | J31: =IFERROR(J19/J22,0) -> 0 | K31: =IFERROR(K19/K22,0) -> 0 | L31: =IFERROR(L19/L22,0) -> 0 | M31: =IFERROR(M19/M22,0) -> 0 | ... Q31: =IFERROR(Q19/Q22,0) -> 2.3333333 | R31: =IFERROR(R12/R21,0) -> 1214.29
C32: Disponibilidad del equipo | D32: % | F32: =(F30/(F30+F31))*100 -> #DIV/0! | G32: =(G30/(G30+G31))*100 -> #DIV/0! | H32: =(H30/(H30+H31))*100 -> #DIV/0! | I32: =(I30/(I30+I31))*100 -> #DIV/0! | J32: =(J30/(J30+J31))*100 -> #DIV/0! | K32: =(K30/(K30+K31))*100 -> #DIV/0! | L32: =(L30/(L30+L31))*100 -> #DIV/0! | M32: =(M30/(M30+M31))*100 -> #DIV/0! | ... Q32: =(Q30/(Q30+Q31))*100 -> 96.666667 | R32: =IFERROR(R13/R22,0) -> 3321.0467
C33: Nro Mantenimiento Preventivo | D33: Und | F33: =COUNTIFS(Mantenimiento[Tipo],"Preventivo",Mantenimiento[Placa Vehiculo],IF($D$7="","*",$D$7),Mantenimiento[Fecha Entrada],">="&F$3,Mantenimiento[Fecha Entrada],"<="&F$4) -> 1 | G33: =COUNTIFS(Mantenimiento[Tipo],"Preventivo",Mantenimiento[Placa Vehiculo],IF($D$7="","*",$D$7),Mantenimiento[Fecha Entrada],">="&G$3,Mantenimiento[Fecha Entrada],"<="&G$4) -> 1 | H33: =COUNTIFS(Mantenimiento[Tipo],"Preventivo",Mantenimiento[Placa Vehiculo],IF($D$7="","*",$D$7),Mantenimiento[Fecha Entrada],">="&H$3,Mantenimiento[Fecha Entrada],"<="&H$4) -> 0 | I33: =COUNTIFS(Mantenimiento[Tipo],"Preventivo",Mantenimiento[Placa Vehiculo],IF($D$7="","*",$D$7),Mantenimiento[Fecha Entrada],">="&I$3,Mantenimiento[Fecha Entrada],"<="&I$4) -> 0 | J33: =COUNTIFS(Mantenimiento[Tipo],"Preventivo",Mantenimiento[Placa Vehiculo],IF($D$7="","*",$D$7),Mantenimiento[Fecha Entrada],">="&J$3,Mantenimiento[Fecha Entrada],"<="&J$4) -> 0 | K33: =COUNTIFS(Mantenimiento[Tipo],"Preventivo",Mantenimiento[Placa Vehiculo],IF($D$7="","*",$D$7),Mantenimiento[Fecha Entrada],">="&K$3,Mantenimiento[Fecha Entrada],"<="&K$4) -> 1 | L33: =COUNTIFS(Mantenimiento[Tipo],"Preventivo",Mantenimiento[Placa Vehiculo],IF($D$7="","*",$D$7),Mantenimiento[Fecha Entrada],">="&L$3,Mantenimiento[Fecha Entrada],"<="&L$4) -> 0 | M33: =COUNTIFS(Mantenimiento[Tipo],"Preventivo",Mantenimiento[Placa Vehiculo],IF($D$7="","*",$D$7),Mantenimiento[Fecha Entrada],">="&M$3,Mantenimiento[Fecha Entrada],"<="&M$4) -> 0 | ... Q33: =COUNTIFS(Mantenimiento[Tipo],"Preventivo",Mantenimiento[Placa Vehiculo],IF($D$7="","*",$D$7),Mantenimiento[Fecha Entrada],">="&Q$3,Mantenimiento[Fecha Entrada],"<="&Q$4) -> 0 | R33: =SUM(F33:Q33) -> 4
C34: Nro Mantenimiento Correctivo | D34: Und | F34: =COUNTIFS(Mantenimiento[Tipo],"Correctivo",Mantenimiento[Placa Vehiculo],IF($D$7="","*",$D$7),Mantenimiento[Fecha Entrada],">="&F$3,Mantenimiento[Fecha Entrada],"<="&F$4) -> 0 | G34: =COUNTIFS(Mantenimiento[Tipo],"Correctivo",Mantenimiento[Placa Vehiculo],IF($D$7="","*",$D$7),Mantenimiento[Fecha Entrada],">="&G$3,Mantenimiento[Fecha Entrada],"<="&G$4) -> 0 | H34: =COUNTIFS(Mantenimiento[Tipo],"Correctivo",Mantenimiento[Placa Vehiculo],IF($D$7="","*",$D$7),Mantenimiento[Fecha Entrada],">="&H$3,Mantenimiento[Fecha Entrada],"<="&H$4) -> 0 | I34: =COUNTIFS(Mantenimiento[Tipo],"Correctivo",Mantenimiento[Placa Vehiculo],IF($D$7="","*",$D$7),Mantenimiento[Fecha Entrada],">="&I$3,Mantenimiento[Fecha Entrada],"<="&I$4) -> 0 | J34: =COUNTIFS(Mantenimiento[Tipo],"Correctivo",Mantenimiento[Placa Vehiculo],IF($D$7="","*",$D$7),Mantenimiento[Fecha Entrada],">="&J$3,Mantenimiento[Fecha Entrada],"<="&J$4) -> 0 | K34: =COUNTIFS(Mantenimiento[Tipo],"Correctivo",Mantenimiento[Placa Vehiculo],IF($D$7="","*",$D$7),Mantenimiento[Fecha Entrada],">="&K$3,Mantenimiento[Fecha Entrada],"<="&K$4) -> 0 | L34: =COUNTIFS(Mantenimiento[Tipo],"Correctivo",Mantenimiento[Placa Vehiculo],IF($D$7="","*",$D$7),Mantenimiento[Fecha Entrada],">="&L$3,Mantenimiento[Fecha Entrada],"<="&L$4) -> 0 | M34: =COUNTIFS(Mantenimiento[Tipo],"Correctivo",Mantenimiento[Placa Vehiculo],IF($D$7="","*",$D$7),Mantenimiento[Fecha Entrada],">="&M$3,Mantenimiento[Fecha Entrada],"<="&M$4) -> 0 | ... Q34: =COUNTIFS(Mantenimiento[Tipo],"Correctivo",Mantenimiento[Placa Vehiculo],IF($D$7="","*",$D$7),Mantenimiento[Fecha Entrada],">="&Q$3,Mantenimiento[Fecha Entrada],"<="&Q$4) -> 3 | R34: =SUM(F34:Q34) -> 3
C35: Carga media por viaje | D35: Barriles/viaje | F35: =IFERROR(F15/F10,0) -> 0 | G35: =IFERROR(G15/G10,0) -> 0 | H35: =IFERROR(H15/H10,0) -> 0 | I35: =IFERROR(I15/I10,0) -> 0 | J35: =IFERROR(J15/J10,0) -> 0 | K35: =IFERROR(K15/K10,0) -> 0 | L35: =IFERROR(L15/L10,0) -> 0 | M35: =IFERROR(M15/M10,0) -> 0 | ... R35: =IFERROR(R15/R10,0) -> 0
C37: Indicadores Financieros | D37: Unidad | E37: Gráfica | F37: Enero | G37: Febrero | H37: Marzo | I37: Abril | J37: Mayo | K37: Junio | L37: Julio | M37: Agosto | N37: Septiembre | O37: Octubre | P37: Noviembre | Q37: Diciembre | R37: Total
C38: Ingreso medio por viaje | D38: $/viaje | F38: =IFERROR(F12/F10,0) -> 0 | G38: =IFERROR(G12/G10,0) -> 0 | H38: =IFERROR(H12/H10,0) -> 0 | I38: =IFERROR(I12/I10,0) -> 0 | J38: =IFERROR(J12/J10,0) -> 0 | K38: =IFERROR(K12/K10,0) -> 0 | L38: =IFERROR(L12/L10,0) -> 0 | M38: =IFERROR(M12/M10,0) -> 0 | ... R38: =IFERROR(R12/R10,0) -> 91.644528
C39: Gasto medio por viaje | D39: $/viaje | F39: =IFERROR(F13/F10,0) -> 149.3505 | G39: =IFERROR(G13/G10,0) -> 192.777 | H39: =IFERROR(H13/H10,0) -> 200.718 | I39: =IFERROR(I13/I10,0) -> 163.035 | J39: =IFERROR(J13/J10,0) -> 138.84 | K39: =IFERROR(K13/K10,0) -> 150.7185 | L39: =IFERROR(L13/L10,0) -> 153.126 | M39: =IFERROR(M13/M10,0) -> 142.185 | ... R39: =IFERROR(R13/R10,0) -> 187.98377
C40: Ingresos por Km | D40: $/Km | F40: =IFERROR(F12/F11,0) -> 0 | G40: =IFERROR(G12/G11,0) -> 0 | H40: =IFERROR(H12/H11,0) -> 0 | I40: =IFERROR(I12/I11,0) -> 0 | J40: =IFERROR(J12/J11,0) -> 0 | K40: =IFERROR(K12/K11,0) -> 0 | L40: =IFERROR(L12/L11,0) -> 0 | M40: =IFERROR(M12/M11,0) -> 0 | ... R40: =IFERROR(R12/R11,0) -> 0.21262301
C41: Gastos por Km | D41: $/Km | F41: =IFERROR(F13/F11,0) -> 0.77183721 | G41: =IFERROR(G13/G11,0) -> 2.5533377 | H41: =IFERROR(H13/H11,0) -> 0.7356799 | I41: =IFERROR(I13/I11,0) -> 0.36009939 | J41: =IFERROR(J13/J11,0) -> 0.2552988 | K41: =IFERROR(K13/K11,0) -> 0.33698938 | L41: =IFERROR(L13/L11,0) -> 0.26242674 | M41: =IFERROR(M13/M11,0) -> 0.36567081 | ... R41: =IFERROR(R13/R11,0) -> 0.43613815
C42: Utilidad media por viaje | D42: $/Km | F42: =IFERROR('Flujo de Caja'!D20/F10,0) -> -2403.186 | G42: =IFERROR('Flujo de Caja'!E20/G10,0) -> -1509.693 | H42: =IFERROR('Flujo de Caja'!F20/H10,0) -> -1576.869 | I42: =IFERROR('Flujo de Caja'!G20/I10,0) -> -2908.8 | J42: =IFERROR('Flujo de Caja'!H20/J10,0) -> -3324.951 | K42: =IFERROR('Flujo de Caja'!I20/K10,0) -> -3436.5073 | L42: =IFERROR('Flujo de Caja'!J20/L10,0) -> -1669.338 | M42: =IFERROR('Flujo de Caja'!K20/M10,0) -> -2215.806 | ... R42: =IFERROR('Flujo de Caja'!P20/R10,0) -> -1485.3364
C43: Utilidad media por Km | D43: $/Km | F43: =IFERROR('Flujo de Caja'!D20/F11,0) -> -12.419566 | G43: =IFERROR('Flujo de Caja'!E20/G11,0) -> -19.995934 | H43: =IFERROR('Flujo de Caja'!F20/H11,0) -> -5.7796054 | I43: =IFERROR('Flujo de Caja'!G20/I11,0) -> -6.4247377 | J43: =IFERROR('Flujo de Caja'!H20/J11,0) -> -6.1139154 | K43: =IFERROR('Flujo de Caja'!I20/K11,0) -> -7.6836386 | L43: =IFERROR('Flujo de Caja'!J20/L11,0) -> -2.8609049 | M43: =IFERROR('Flujo de Caja'!K20/M11,0) -> -5.6986009 | ... R43: =IFERROR('Flujo de Caja'!P20/R11,0) -> -3.4461052
C44: Margen Bruto | D44: % | F44: ='Flujo de Caja'!D21 -> -6.9938841 | G44: ='Flujo de Caja'!E21 | H44: ='Flujo de Caja'!F21 | I44: ='Flujo de Caja'!G21 | J44: ='Flujo de Caja'!H21 | K44: ='Flujo de Caja'!I21 | L44: ='Flujo de Caja'!J21 | M44: ='Flujo de Caja'!K21 | ... R44: ='Flujo de Caja'!P21 -> -0.83676536
C47: KILOMETROS RECORRIDOS POR GALON
C49: Equipo | D49: Unidad | E49: Gráfica | F49: Enero | G49: Febrero | H49: Marzo | I49: Abril | J49: Mayo | K49: Junio | L49: Julio | M49: Agosto | N49: Septiembre | O49: Octubre | P49: Noviembre | Q49: Diciembre | R49: Total
C50: =CONCATENATE(VLOOKUP(D50,Vehiculos[[PLACA]:[MODELO]],4,0)," ",VLOOKUP(D50,Vehiculos[[PLACA]:[MODELO]],2,0)," ",VLOOKUP(D50,Vehiculos[[PLACA]:[MODELO]],3,0)) -> CABEZAL ARTICULADO SHACMAN | D50: QAA-3164 | F50: =IFERROR(F79/F171,0) -> 2.332098 | G50: =IFERROR(G79/G171,0) -> 0.70495962 | H50: =IFERROR(H79/H171,0) -> 2.4467163 | I50: =IFERROR(I79/I171,0) -> 4.9986199 | J50: =IFERROR(J79/J171,0) -> 7.0505618 | K50: =IFERROR(K79/K171,0) -> 5.3414146 | L50: =IFERROR(L79/L171,0) -> 6.8590572 | M50: =IFERROR(M79/M171,0) -> 4.9224602 | ... Q50: =IFERROR(Q79/Q171,0) -> 6.7207637 | R50: =SUM(F50:Q50) -> 61.287638
C51: =CONCATENATE(VLOOKUP(D51,Vehiculos[[PLACA]:[MODELO]],4,0)," ",VLOOKUP(D51,Vehiculos[[PLACA]:[MODELO]],2,0)," ",VLOOKUP(D51,Vehiculos[[PLACA]:[MODELO]],3,0)) -> CABEZAL ARTICULADO SHACMAN | D51: QAA-3166 | F51: =IFERROR(F80/F172,0) -> 1.3684418 | G51: =IFERROR(G80/G172,0) -> 0.8512288 | H51: =IFERROR(H80/H172,0) -> 6.279022 | I51: =IFERROR(I80/I172,0) -> 4.0752146 | J51: =IFERROR(J80/J172,0) -> 6.1487657 | K51: =IFERROR(K80/K172,0) -> 4.8599081 | L51: =IFERROR(L80/L172,0) -> 5.440806 | M51: =IFERROR(M80/M172,0) -> 4.0776862 | ... Q51: =IFERROR(Q80/Q172,0) -> 0 | R51: =SUM(F51:Q51) -> 33.101073
C52: =CONCATENATE(VLOOKUP(D52,Vehiculos[[PLACA]:[MODELO]],4,0)," ",VLOOKUP(D52,Vehiculos[[PLACA]:[MODELO]],2,0)," ",VLOOKUP(D52,Vehiculos[[PLACA]:[MODELO]],3,0)) -> CABEZAL ARTICULADO DAF | D52: QAA-2912 | F52: =IFERROR(F81/F173,0) -> 6.1493337 | G52: =IFERROR(G81/G173,0) -> 5.5868448 | H52: =IFERROR(H81/H173,0) -> 5.7042583 | I52: =IFERROR(I81/I173,0) -> 4.9947383 | J52: =IFERROR(J81/J173,0) -> 5.4432751 | K52: =IFERROR(K81/K173,0) -> 5.3614881 | L52: =IFERROR(L81/L173,0) -> 4.9733959 | M52: =IFERROR(M81/M173,0) -> 5.3302509 | ... Q52: =IFERROR(Q81/Q173,0) -> 6.2778139 | R52: =SUM(F52:Q52) -> 67.584746
C53: =CONCATENATE(VLOOKUP(D53,Vehiculos[[PLACA]:[MODELO]],4,0)," ",VLOOKUP(D53,Vehiculos[[PLACA]:[MODELO]],2,0)," ",VLOOKUP(D53,Vehiculos[[PLACA]:[MODELO]],3,0)) -> CABEZAL ARTICULADO DAF | D53: QAA-2915 | F53: =IFERROR(F82/F174,0) -> 1.0713347 | G53: =IFERROR(G82/G174,0) -> 6.7902073 | H53: =IFERROR(H82/H174,0) -> 4.6440661 | I53: =IFERROR(I82/I174,0) -> 5.2334872 | J53: =IFERROR(J82/J174,0) -> 5.9057429 | K53: =IFERROR(K82/K174,0) -> 5.0066142 | L53: =IFERROR(L82/L174,0) -> 5.8486758 | M53: =IFERROR(M82/M174,0) -> 5.6708334 | ... Q53: =IFERROR(Q82/Q174,0) -> 6.1898846 | R53: =SUM(F53:Q53) -> 64.588162
C54: =CONCATENATE(VLOOKUP(D54,Vehiculos[[PLACA]:[MODELO]],4,0)," ",VLOOKUP(D54,Vehiculos[[PLACA]:[MODELO]],2,0)," ",VLOOKUP(D54,Vehiculos[[PLACA]:[MODELO]],3,0)) -> CABEZAL ARTICULADO DAF | D54: QAA-2916 | F54: =IFERROR(F83/F175,0) -> 0.88087496 | G54: =IFERROR(G83/G175,0) -> 0.71199193 | H54: =IFERROR(H83/H175,0) -> 5.7333182 | I54: =IFERROR(I83/I175,0) -> 5.3742962 | J54: =IFERROR(J83/J175,0) -> 5.8095103 | K54: =IFERROR(K83/K175,0) -> 5.8555918 | L54: =IFERROR(L83/L175,0) -> 6.0272342 | M54: =IFERROR(M83/M175,0) -> 5.2551461 | ... Q54: =IFERROR(Q83/Q175,0) -> 6.4681512 | R54: =SUM(F54:Q54) -> 60.205539
C55: =CONCATENATE(VLOOKUP(D55,Vehiculos[[PLACA]:[MODELO]],4,0)," ",VLOOKUP(D55,Vehiculos[[PLACA]:[MODELO]],2,0)," ",VLOOKUP(D55,Vehiculos[[PLACA]:[MODELO]],3,0)) -> RIGIDO CAMIÓN RIGIDO HINO | D55: PAB-3424 | F55: =IFERROR(F84/F176,0) -> 3.0775348 | G55: =IFERROR(G84/G176,0) -> 3.7069767 | H55: =IFERROR(H84/H176,0) -> 3.2194444 | I55: =IFERROR(I84/I176,0) -> 6.7366667 | J55: =IFERROR(J84/J176,0) -> 8.3081967 | K55: =IFERROR(K84/K176,0) -> 7.5052632 | L55: =IFERROR(L84/L176,0) -> 4.42 | M55: =IFERROR(M84/M176,0) -> 5.82 | ... Q55: =IFERROR(Q84/Q176,0) -> 5.7885714 | R55: =SUM(F55:Q55) -> 65.259229
C56: =CONCATENATE(VLOOKUP(D56,Vehiculos[[PLACA]:[MODELO]],4,0)," ",VLOOKUP(D56,Vehiculos[[PLACA]:[MODELO]],2,0)," ",VLOOKUP(D56,Vehiculos[[PLACA]:[MODELO]],3,0)) -> CABEZAL ARTICULADO SHACMAN | D56: QAA-3165 | F56: =IFERROR(F85/F177,0) -> 1.8503194 | G56: =IFERROR(G85/G177,0) -> 0.92788299 | H56: =IFERROR(H85/H177,0) -> 5.1398752 | I56: =IFERROR(I85/I177,0) -> 3.6030928 | J56: =IFERROR(J85/J177,0) -> 4.8109464 | K56: =IFERROR(K85/K177,0) -> 5.6000548 | L56: =IFERROR(L85/L177,0) -> 5.0341513 | M56: =IFERROR(M85/M177,0) -> 0 | ... Q56: =IFERROR(Q85/Q177,0) -> 7.5710398 | R56: =SUM(F56:Q56) -> 56.266983
C57: =CONCATENATE(VLOOKUP(D57,Vehiculos[[PLACA]:[MODELO]],4,0)," ",VLOOKUP(D57,Vehiculos[[PLACA]:[MODELO]],2,0)," ",VLOOKUP(D57,Vehiculos[[PLACA]:[MODELO]],3,0)) -> CABEZAL ARTICULADO HINO | D57: QAA-1976 | F57: =IFERROR(F86/F178,0) -> 5.9678204 | G57: =IFERROR(G86/G178,0) -> 0 | H57: =IFERROR(H86/H178,0) -> 4.8440552 | I57: =IFERROR(I86/I178,0) -> 3.7864247 | J57: =IFERROR(J86/J178,0) -> 5.4870423 | K57: =IFERROR(K86/K178,0) -> 3.9308161 | L57: =IFERROR(L86/L178,0) -> 3.285911 | M57: =IFERROR(M86/M178,0) -> 3.8612491 | ... Q57: =IFERROR(Q86/Q178,0) -> 0 | R57: =SUM(F57:Q57) -> 31.163319
C58: =CONCATENATE(VLOOKUP(D58,Vehiculos[[PLACA]:[MODELO]],4,0)," ",VLOOKUP(D58,Vehiculos[[PLACA]:[MODELO]],2,0)," ",VLOOKUP(D58,Vehiculos[[PLACA]:[MODELO]],3,0)) -> RIGIDO CAMIÓN RIGIDO HINO | D58: IAA-2747 | F58: =IFERROR(F87/F179,0) -> 7.240678 | G58: =IFERROR(G87/G179,0) -> 4.997619 | H58: =IFERROR(H87/H179,0) -> 2.8828571 | I58: =IFERROR(I87/I179,0) -> 11.196721 | J58: =IFERROR(J87/J179,0) -> 11.24918 | K58: =IFERROR(K87/K179,0) -> 10.465574 | L58: =IFERROR(L87/L179,0) -> 10.213115 | M58: =IFERROR(M87/M179,0) -> 11.989655 | ... Q58: =IFERROR(Q87/Q179,0) -> 9.0880829 | R58: =SUM(F58:Q58) -> 105.41422
C59: =CONCATENATE(VLOOKUP(D59,Vehiculos[[PLACA]:[MODELO]],3,0)," ",VLOOKUP(D59,Vehiculos[[PLACA]:[MODELO]],4,0)," ",VLOOKUP(D59,Vehiculos[[PLACA]:[MODELO]],3,0)) -> QINGLING CABEZAL QINGLING | D59: PFG-2722 | F59: =IFERROR(F88/F180,0) -> 0 | G59: =IFERROR(G88/G180,0) -> 0 | H59: =IFERROR(H88/H180,0) -> 0 | I59: =IFERROR(I88/I180,0) -> 0 | J59: =IFERROR(J88/J180,0) -> 0 | K59: =IFERROR(K88/K180,0) -> 5.915 | L59: =IFERROR(L88/L180,0) -> 9.6597015 | M59: =IFERROR(M88/M180,0) -> 7.8078125 | ... Q59: =IFERROR(Q88/Q180,0) -> 5.6534024 | R59: =SUM(F59:Q59) -> 49.465599
C60: =CONCATENATE(VLOOKUP(D60,Vehiculos[[PLACA]:[MODELO]],4,0)," ",VLOOKUP(D60,Vehiculos[[PLACA]:[MODELO]],2,0)," ",VLOOKUP(D60,Vehiculos[[PLACA]:[MODELO]],3,0)) -> DMAX CAMIONETA CHEVROLET | D60: PFF-2857 | F60: =IFERROR(F89/F181,0) -> 11.705515 | G60: =IFERROR(G89/G181,0) -> 3.7855377 | H60: =IFERROR(H89/H181,0) -> 55.539499 | I60: =IFERROR(I89/I181,0) -> 44.986764 | J60: =IFERROR(J89/J181,0) -> 37.184933 | K60: =IFERROR(K89/K181,0) -> 37.782313 | L60: =IFERROR(L89/L181,0) -> 39.941762 | M60: =IFERROR(M89/M181,0) -> 39.402016 | ... Q60: =IFERROR(Q89/Q181,0) -> 27.542373 | R60: =SUM(F60:Q60) -> 410.1254
C61: =CONCATENATE(VLOOKUP(D61,Vehiculos[[PLACA]:[MODELO]],3,0)," ",VLOOKUP(D61,Vehiculos[[PLACA]:[MODELO]],4,0)," ",VLOOKUP(D61,Vehiculos[[PLACA]:[MODELO]],3,0)) -> DAF CABEZAL DAF | D61: QAA-3074 | O61: =IFERROR(O91/O182,0) -> 4.6727682 | P61: =IFERROR(P91/P182,0) -> 13.455873 | Q61: =IFERROR(Q91/Q182,0) -> 6.2461174 | R61: =SUM(F61:Q61) -> 24.374759
C62: =CONCATENATE(VLOOKUP(D62,Vehiculos[[PLACA]:[MODELO]],4,0)," ",VLOOKUP(D62,Vehiculos[[PLACA]:[MODELO]],2,0)," ",VLOOKUP(D62,Vehiculos[[PLACA]:[MODELO]],3,0)) -> CABEZAL ARTICULADO DAF | D62: QAA-3220 | F62: =IFERROR(F90/F183,0) -> 0 | G62: =IFERROR(G90/G183,0) -> 0 | H62: =IFERROR(H90/H183,0) -> 0 | I62: =IFERROR(I90/I183,0) -> 0 | J62: =IFERROR(J90/J183,0) -> 24.792187 | K62: =IFERROR(K90/K183,0) -> 0 | L62: =IFERROR(L90/L183,0) -> 0 | M62: =IFERROR(M90/M183,0) -> 5.6223885 | ... Q62: =IFERROR(Q90/Q183,0) -> 6.3114625 | R62: =SUM(F62:Q62) -> 53.306805
C63: =CONCATENATE(VLOOKUP(D63,Vehiculos[[PLACA]:[MODELO]],3,0)," ",VLOOKUP(D63,Vehiculos[[PLACA]:[MODELO]],4,0)," ",VLOOKUP(D63,Vehiculos[[PLACA]:[MODELO]],3,0)) -> DAF CABEZAL DAF | D63: QAA-3108 | F63: =IFERROR(F93/F185,0) -> 0 | G63: =IFERROR(G93/G185,0) -> 0 | H63: =IFERROR(H93/H185,0) -> 0 | I63: =IFERROR(I93/I185,0) -> 0 | K63: =IFERROR(K93/K185,0) -> 0.015009606 | L63: =IFERROR(L93/L185,0) -> 0 | N63: =IFERROR(N93/N185,0) -> 0 | Q63: =IFERROR(Q92/Q184,0) -> 5.9038534 | R63: =SUM(F63:Q63) -> 5.918863
C64: =CONCATENATE(VLOOKUP(D64,Vehiculos[[PLACA]:[MODELO]],4,0)," ",VLOOKUP(D64,Vehiculos[[PLACA]:[MODELO]],2,0)," ",VLOOKUP(D64,Vehiculos[[PLACA]:[MODELO]],3,0)) -> CABEZAL ARTICULADO HINO | D64: QAA-1974 | F64: =IFERROR(F93/F185,0) -> 0 | G64: =IFERROR(G93/G185,0) -> 0 | H64: =IFERROR(H93/H185,0) -> 0 | I64: =IFERROR(I93/I185,0) -> 0 | J64: =IFERROR(J93/J185,0) -> 0.61531532 | K64: =IFERROR(K93/K185,0) -> 0.015009606 | L64: =IFERROR(L93/L185,0) -> 0 | M64: =IFERROR(M93/M185,0) -> 0 | ... Q64: =IFERROR(Q93/Q185,0) -> 0 | R64: =SUM(F64:Q64) -> 0.63032492
